Workbook
Name UPDATE: 'Data Sheet'!$E$1

Sheet DCF>

Sheet DCF
B2: ="DCF Vatuation - "&'Data Sheet'!B1 -> DCF Vatuation - ASIAN PAINTS LTD
B7: Calculation of PV of FCFF | F7: ='Raw FS'!N2 -> 45717 | G7: =F7+366 -> 46083 | H7: =G7+366 -> 46449 | I7: =H7+366 -> 46815 | J7: =I7+366 -> 47181 | K7: =J7+366 -> 47547
B9: EBIT | F9: ='Data Sheet'!K33-'Data Sheet'!K26 -> 5287.61 | G9: =F9*(1+$E$19) -> 6535.7563 | H9: =G9*(1+$E$19) -> 8078.529 | I9: =H9*(1+$E$19) -> 9985.4749 | J9: =I9*(1+$E$19) -> 12342.558 | K9: =J9*(1+$E$19) -> 15256.032 | L9: -
B10: Tax Rate | F10: 0.25 | G10: =F10 -> 0.25 | H10: =G10 -> 0.25 | I10: =H10 -> 0.25 | J10: =I10 -> 0.25 | K10: =J10 -> 0.25 | L10: -
B11: EBIT(1-T) | F11: =F9*(1-F10) -> 3965.7075 | G11: =G9*(1-G10) -> 4901.8172 | H11: =H9*(1-H10) -> 6058.8968 | I11: =I9*(1-I10) -> 7489.1062 | J11: =J9*(1-J10) -> 9256.9182 | K11: =K9*(1-K10) -> 11442.024 | L11: -
B12: Less: Reinvestment | F12: ='Intrisic Growth'!K55 -> 0.48354676 | G12: =F12+(($K$12-F12))/4 -> 0.49021043 | H12: =G12+(($K$12-G12))/4 -> 0.49520818 | I12: =H12+(($K$12-H12))/4 -> 0.49895649 | J12: =I12+(($K$12-I12))/4 -> 0.50176772 | K12: ='Intrisic Growth'!K58 -> 0.51020143 | L12: -
B13: Free Cash Flow to Firm | F13: =F11*(1-F12) -> 2048.1025 | G13: =G11*(1-G12) -> 2498.8953 | H13: =H11*(1-H12) -> 3058.4815 | I13: =I11*(1-I12) -> 3752.3681 | J13: =J11*(1-J12) -> 4612.0954 | K13: =K11*(1-K12) -> 5604.2871 | L13: -
B14: Mid Convertion | G14: 0.5 | H14: =G14+1 -> 1.5 | I14: =H14+1 -> 2.5 | J14: =I14+1 -> 3.5 | K14: =J14+1 -> 4.5 | L14: -
B15: Discounting Factor | G15: =1/(1+$E$21)^G14 -> 0.94512154 | H15: =1/(1+$E$21)^H14 -> 0.84423427 | I15: =1/(1+$E$21)^I14 -> 0.75411625 | J15: =1/(1+$E$21)^J14 -> 0.6736179 | K15: =1/(1+$E$21)^K14 -> 0.60171237 | L15: -
L16: -
B17: PV of FCFF | G17: =G13*G15 -> 2361.7598 | H17: =H13*H15 -> 2582.0749 | I17: =I13*I15 -> 2829.7217 | J17: =J13*J15 -> 3106.79 | K17: =K13*K15 -> 3372.1689 | L17: -
B19: Expected Growth | E19: ='Intrisic Growth'!K68 -> 0.23605113
B20: Terminal Growth | E20: 0.04
B21: WACC | E21: ='WACC(Geometric)'!J46 -> 0.1195015
B23: Calculation of Terminal Value
B25: FCFF (n+1) | E25: =K13*(1+E19) -> 6927.1854
B26: WACC | E26: =E21 -> 0.1195015
B27: Terminal Growth Rate | E27: =E20 -> 0.04
B29: Terminal Value | E29: =E25/(E26-E27) -> 87132.763
B31: Calculation of Equity Value | G31: Sensitivity Analysis
B33: PV of FCFF | E33: =SUM(G17:K17) -> 14252.515 | G33: =E35 -> 101385.28 | H33: 0.105 | I33: 0.11 | J33: 0.115 | K33: 0.1195 | L33: 0.125
B34: Terminal Value | E34: =E29 -> 87132.763 | G34: 0.035 | H34: 113212.31 | I34: 106614.99 | J34: 100842.33 | K34: 96231.041 | L34: 91221.243
B35: Value of Operating Assets | E35: =SUM(E33:E34) -> 101385.28 | G35: 0.04 | H35: 120824.6 | I35: 113212.31 | J35: 106614.99 | K35: 101386.92 | L35: 95748.815
G36: 0.0433 | H36: 126524.56 | I36: 118108.37 | J36: 110865.98 | K36: 105160.46 | L36: 99040.587
B37: Add: Cash | E37: ='Data Sheet'!K69 -> 781.98 | G37: 0.045 | H37: 129705.61 | I37: 120824.6 | J37: 113212.31 | K37: 107234.87 | L37: 100842.33
B38: Less: Debt | E38: =SUM('Raw FS'!N7:N8) -> 864 | G38: 0.05 | H38: 140201.34 | I38: 129705.61 | J38: 120824.6 | K38: 113924.25 | L38: 106614.99
B39: Value of Equity | E39: =E35+E37-E38 -> 101303.26
B40: No of Share | E40: ='Data Sheet'!B6 -> 95.961577
B42: Equity Value per Share | E42: =E39/E40 -> 1055.6648
B44: Share Price | E44: 2207
B45: Discount/Premium | E45: =E44/E42 -> 2.0906258
B47: Stock is overvalued | E47: =(E44-E42)/E42 -> 1.0906258

Sheet WACC(Geometric)
B4: Asian Paints
B7: Wieghhted Average Cost of Capital (WACC)
B9: All Figures are in unless stated otherwise
B11: Peers Comps
G12: Debt / | H12: Debt / | I12: Levered | J12: Unleverd
B13: Name OF the Com | C13: Country | D13: Total Debt | E13: Total Equity | F13: Tax Rate 1 | G13: Equity | H13: Capital | I13: Beta 2 | J13: Beta 3
B15: Asian Paints | C15: India | D15: 3557.09 | E15: 203411.79 | F15: 0.3 | G15: =D15/E15 -> 0.017487138 | H15: =D15/(D15+E15) -> 0.017186593 | I15: ='WACC(Arithmetic)'!I15 -> 1.2350587 | J15: =I15/(1+(1-F15)*G15) -> 1.2201231
B16: Berger Paints | C16: India | D16: 697.33 | E16: 48348.31 | F16: 0.3 | G16: =D16/E16 -> 0.014423048 | H16: =D16/(D16+E16) -> 0.014217981 | I16: ='WACC(Arithmetic)'!I16 -> 1.1107726 | J16: =I16/(1+(1-F16)*G16) -> 1.0996702
B17: Kansai Nerolac | C17: India | D17: 275.42 | E17: 13787.62 | F17: 0.3 | G17: =D17/E17 -> 0.019975891 | H17: =D17/(D17+E17) -> 0.01958467 | I17: ='WACC(Arithmetic)'!I17 -> 0.92242955 | J17: =I17/(1+(1-F17)*G17) -> 0.90970898
B18: Indigo Paints | C18: India | D18: 17.2 | E18: 3484.14 | F18: 0.3 | G18: =D18/E18 -> 0.0049366558 | H18: =D18/(D18+E18) -> 0.004912405 | I18: ='WACC(Arithmetic)'!I18 -> 1.0513967 | J18: =I18/(1+(1-F18)*G18) -> 1.0477759
E20: Average | F20: =AVERAGE(F15:F18) -> 0.3 | G20: =AVERAGE(G16:G18) -> 0.013111865 | H20: =AVERAGE(H15:H18) -> 0.013975413 | I20: =AVERAGE(I16:I18) -> 1.0281996 | J20: =AVERAGE(J16:J18) -> 1.0190517
E21: Median | F21: =MEDIAN(F15:F18) -> 0.3 | G21: =MEDIAN(G15:G18) -> 0.015955093 | H21: =MEDIAN(H15:H18) -> 0.015702287 | I21: =MEDIAN(I15:I18) -> 1.0810846 | J21: =MEDIAN(J15:J18) -> 1.0737231
B24: Cost of DEBT | G24: Cost of Equity
B26: Pre-Tax Cost of Debt | E26: =227/3557.09 -> 0.063816209 | G26: Risk Free Rate | J26: 0.0684
B27: Tax Rate | E27: =F15 -> 0.3 | G27: Equity Risk Premium | J27: ='Market Return'!F8-'WACC(Geometric)'!J26 -> 0.048103341
B28: Post Tax Cost of Debt | E28: =E26*(1-E27) -> 0.044671347 | G28: Levered Beta 4 | J28: =J36 -> 1.0843759
G29: Cost of Equity | J29: =J26+J27*J28 -> 0.12056211
B31: Capital Structure | G31: Levered Beta
D33: Current | E33: Target | G33: Comps Median Unlevered Beta | J33: =J21 -> 1.0737231
B34: Total Debt | C34: =D15 -> 3557.09 | D34: =C34/C36 -> 0.017186593 | E34: =H20 -> 0.013975413 | G34: Target Debt / Equity | J34: =E38 -> 0.014173493
B35: Market Capitalization | C35: =E15 -> 203411.79 | D35: =C35/C36 -> 0.98281341 | E35: =E36-E34 -> 0.98602459 | G35: Tax Rate | J35: =E27 -> 0.3
B36: Total Capital | C36: =SUM(C34:C35) -> 206968.88 | D36: =SUM(D34:D35) -> 1 | E36: =D36 -> 1 | G36: Levered Beta | J36: =J33*(1+(1-J35)*J34) -> 1.0843759
B38: Debt / Equity | D38: =D34/D35 -> 0.017487138 | E38: =E34/E35 -> 0.014173493 | G38: Weight Average Cost of Capital
B40: Notes: | G40: Cost of Equity | J40: =J29 -> 0.12056211
B41: 1. Tax Rate considered as Marginal Tax Rate for the country | G41: Equity Weight | J41: =E35 -> 0.98602459
B42: 2. Levered beta is based on 5 year monthly data
B43: 3. Unlevered Beta = Levered Beta/(1+(1-tax rate)*Debt/Equity) | G43: Cost of Debt | J43: =E28 -> 0.044671347
B44: 4. Levered Beta = Unlevered Beta *(1+(1-Tax Rate)*Debt/Equity) | G44: Debt Weight | J44: =E34 -> 0.013975413
G46: WACC | J46: =(J40*J41)+(J43*J44) -> 0.1195015

Sheet Financials>

Sheet Historical FS 
B2: ="Historical Financial Statement - "&'Data Sheet'!B1 -> Historical Financial Statement - ASIAN PAINTS LTD
B3: Years | C3: ='Data Sheet'!B16 -> 42460 | D3: ='Data Sheet'!C16 -> 42825 | E3: ='Data Sheet'!D16 -> 43190 | F3: ='Data Sheet'!E16 -> 43555 | G3: ='Data Sheet'!F16 -> 43921 | H3: ='Data Sheet'!G16 -> 44286 | I3: ='Data Sheet'!H16 -> 44651 | J3: ='Data Sheet'!I16 -> 45016 | ... L3: ='Data Sheet'!K16 -> 45747 | M3: LTM
A5: # | B5: Income Statement
B6: Sales | C6: =IFERROR('Data Sheet'!B17,0) -> 14271.49 | D6: =IFERROR('Data Sheet'!C17,0) -> 15061.99 | E6: =IFERROR('Data Sheet'!D17,0) -> 16824.55 | F6: =IFERROR('Data Sheet'!E17,0) -> 19240.13 | G6: =IFERROR('Data Sheet'!F17,0) -> 20211.25 | H6: =IFERROR('Data Sheet'!G17,0) -> 21712.79 | I6: =IFERROR('Data Sheet'!H17,0) -> 29101.28 | J6: =IFERROR('Data Sheet'!I17,0) -> 34488.59 | ... L6: =IFERROR('Data Sheet'!K17,0) -> 33905.62 | M6: =IFERROR(SUM('Data Sheet'!H42:K42),0) -> 34695.75
B7: Sales Growth | D7: =D6/C6-1 -> 0.055390152 | E7: =E6/D6-1 -> 0.11702039 | F7: =F6/E6-1 -> 0.14357472 | G7: =G6/F6-1 -> 0.050473671 | H7: =H6/G6-1 -> 0.074292288 | I7: =I6/H6-1 -> 0.34028285 | J7: =J6/I6-1 -> 0.18512278 | K7: =K6/J6-1 -> 0.029173127 | ... M7: =M6/L6-1 -> 0.023303806
B9: COGS | C9: =IFERROR(SUM('Data Sheet'!B18,'Data Sheet'!B20:B22)-1*'Data Sheet'!B19,0) -> 9413.84 | D9: =IFERROR(SUM('Data Sheet'!C18,'Data Sheet'!C20:C22)-1*'Data Sheet'!C19,0) -> 9732.66 | E9: =IFERROR(SUM('Data Sheet'!D18,'Data Sheet'!D20:D22)-1*'Data Sheet'!D19,0) -> 11194.17 | F9: =IFERROR(SUM('Data Sheet'!E18,'Data Sheet'!E20:E22)-1*'Data Sheet'!E19,0) -> 12905.81 | G9: =IFERROR(SUM('Data Sheet'!F18,'Data Sheet'!F20:F22)-1*'Data Sheet'!F19,0) -> 13175.16 | H9: =IFERROR(SUM('Data Sheet'!G18,'Data Sheet'!G20:G22)-1*'Data Sheet'!G19,0) -> 14035.07 | I9: =IFERROR(SUM('Data Sheet'!H18,'Data Sheet'!H20:H22)-1*'Data Sheet'!H19,0) -> 20590.57 | J9: =IFERROR(SUM('Data Sheet'!I18,'Data Sheet'!I20:I22)-1*'Data Sheet'!I19,0) -> 23766.7 | ... L9: =IFERROR(SUM('Data Sheet'!K18,'Data Sheet'!K20:K22)-1*'Data Sheet'!K19,0) -> 22741.27 | M9: =IFERROR(SUM('Data Sheet'!H43:K43),0) -> 28350.24
B10: COGS % Sales | C10: =C9/C6 -> 0.65962559 | D10: =D9/D6 -> 0.64617358 | E10: =E9/E6 -> 0.66534736 | F10: =F9/F6 -> 0.67077561 | G10: =G9/G6 -> 0.6518726 | H10: =H9/H6 -> 0.64639643 | I10: =I9/I6 -> 0.7075486 | J10: =J9/J6 -> 0.68911776 | ... M10: =M9/M6 -> 0.81710988
B12: Gross Profit | C12: =C6-C9 -> 4857.65 | D12: =D6-D9 -> 5329.33 | E12: =E6-E9 -> 5630.38 | F12: =F6-F9 -> 6334.32 | G12: =G6-G9 -> 7036.09 | H12: =H6-H9 -> 7677.72 | I12: =I6-I9 -> 8510.71 | J12: =J6-J9 -> 10721.89 | ... M12: =M6-M9 -> 6345.51
B13: Gross Margin | C13: =C12/C6 -> 0.34037441 | D13: =D12/D6 -> 0.35382642 | E13: =E12/E6 -> 0.33465264 | F13: =F12/F6 -> 0.32922439 | G13: =G12/G6 -> 0.3481274 | H13: =H12/H6 -> 0.35360357 | I13: =I12/I6 -> 0.2924514 | J13: =J12/J6 -> 0.31088224 | ... M13: =M12/M6 -> 0.18289012
B15: Selling & General Expenses | C15: =IFERROR(SUM('Data Sheet'!B23:B24),0) -> 2132.61 | D15: =IFERROR(SUM('Data Sheet'!C23:C24),0) -> 2335.57 | E15: =IFERROR(SUM('Data Sheet'!D23:D24),0) -> 2426.37 | F15: =IFERROR(SUM('Data Sheet'!E23:E24),0) -> 2569.38 | G15: =IFERROR(SUM('Data Sheet'!F23:F24),0) -> 2868.7 | H15: =IFERROR(SUM('Data Sheet'!G23:G24),0) -> 2822.12 | I15: =IFERROR(SUM('Data Sheet'!H23:H24),0) -> 3707.1 | J15: =IFERROR(SUM('Data Sheet'!I23:I24),0) -> 4462.05 | ... M15: =IFERROR(SUM('Data Sheet'!L23:L24),0) -> 0
B16: S&G % Sales | C16: =C15/C6 -> 0.14943149 | D16: =D15/D6 -> 0.15506384 | E16: =E15/E6 -> 0.14421604 | F16: =F15/F6 -> 0.13354276 | G16: =G15/G6 -> 0.1419358 | H16: =H15/H6 -> 0.12997501 | I16: =I15/I6 -> 0.12738615 | J16: =J15/J6 -> 0.12937757 | ... M16: =M15/M6 -> 0
B18: EBITDA | C18: =C12-C15 -> 2725.04 | D18: =D12-D15 -> 2993.76 | E18: =E12-E15 -> 3204.01 | F18: =F12-F15 -> 3764.94 | G18: =G12-G15 -> 4167.39 | H18: =H12-H15 -> 4855.6 | I18: =I12-I15 -> 4803.61 | J18: =J12-J15 -> 6259.84 | ... L18: =L12-L15 -> 6006.21 | M18: =IFERROR(SUM('Data Sheet'!H50:K50,'Data Sheet'!H45:K45,'Data Sheet'!H46:K46,'Data Sheet'!K46),0) -> 7802.52
B19: EBIDTA Margin | C19: =C18/C6 -> 0.19094292 | D19: =D18/D6 -> 0.19876258 | E19: =E18/E6 -> 0.19043659 | F19: =F18/F6 -> 0.19568163 | G19: =G18/G6 -> 0.2061916 | H19: =H18/H6 -> 0.22362856 | I19: =I18/I6 -> 0.16506525 | J19: =J18/J6 -> 0.18150467 | ... M19: =M18/M6 -> 0.22488403
B21: Interest | C21: =IFERROR('Data Sheet'!B27,0) -> 49 | D21: =IFERROR('Data Sheet'!C27,0) -> 37.33 | E21: =IFERROR('Data Sheet'!D27,0) -> 41.47 | F21: =IFERROR('Data Sheet'!E27,0) -> 110.47 | G21: =IFERROR('Data Sheet'!F27,0) -> 107.95 | H21: =IFERROR('Data Sheet'!G27,0) -> 91.63 | I21: =IFERROR('Data Sheet'!H27,0) -> 95.41 | J21: =IFERROR('Data Sheet'!I27,0) -> 144.45 | ... L21: =IFERROR('Data Sheet'!K27,0) -> 227.02 | M21: =IFERROR(SUM('Data Sheet'!H46:K46),0) -> 189.1
B22: Interest % Sales | C22: =C21/C6 -> 0.0034334187 | D22: =D21/D6 -> 0.0024784242 | E22: =E21/E6 -> 0.0024648505 | F22: =F21/F6 -> 0.0057416452 | G22: =G21/G6 -> 0.0053410848 | H22: =H21/H6 -> 0.0042200933 | I22: =I21/I6 -> 0.0032785499 | J22: =J21/J6 -> 0.0041883417 | ... M22: =M21/M6 -> 0.0054502353
B24: Depreciation | C24: =IFERROR('Data Sheet'!B26,0) -> 275.58 | D24: =IFERROR('Data Sheet'!C26,0) -> 334.79 | E24: =IFERROR('Data Sheet'!D26,0) -> 360.47 | F24: =IFERROR('Data Sheet'!E26,0) -> 622.14 | G24: =IFERROR('Data Sheet'!F26,0) -> 780.5 | H24: =IFERROR('Data Sheet'!G26,0) -> 791.27 | I24: =IFERROR('Data Sheet'!H26,0) -> 816.36 | J24: =IFERROR('Data Sheet'!I26,0) -> 858.02 | ... L24: =IFERROR('Data Sheet'!K26,0) -> 1026.34 | M24: =IFERROR(SUM('Data Sheet'!H45),0) -> 301.1
B25: Depreciation % Sales | C25: =C24/C6 -> 0.019309827 | D25: =D24/D6 -> 0.022227475 | E25: =E24/E6 -> 0.021425239 | F25: =F24/F6 -> 0.03233554 | G25: =G24/G6 -> 0.038617107 | H25: =H24/H6 -> 0.036442576 | I25: =I24/I6 -> 0.028052374 | J25: =J24/J6 -> 0.024878373 | ... M25: =M24/M6 -> 0.0086782963
B27: Earning Before Tax | C27: =C18-SUM(C21,C24) -> 2400.46 | D27: =D18-SUM(D21,D24) -> 2621.64 | E27: =E18-SUM(E21,E24) -> 2802.07 | F27: =F18-SUM(F21,F24) -> 3032.33 | G27: =G18-SUM(G21,G24) -> 3278.94 | H27: =H18-SUM(H21,H24) -> 3972.7 | I27: =I18-SUM(I21,I24) -> 3891.84 | J27: =J18-SUM(J21,J24) -> 5257.37 | ... M27: =M18-SUM(M21,M24) -> 7312.32
B28: EBT % Sales | C28: =C27/C6 -> 0.16819968 | D28: =D27/D6 -> 0.17405668 | E28: =E27/E6 -> 0.1665465 | F28: =F27/F6 -> 0.15760444 | G28: =G27/G6 -> 0.16223341 | H28: =H27/H6 -> 0.18296589 | I28: =I27/I6 -> 0.13373432 | J28: =J27/J6 -> 0.15243795 | ... M28: =M27/M6 -> 0.2107555
B30: Tax | C30: =IFERROR('Data Sheet'!B29,0) -> 844.49 | D30: =IFERROR('Data Sheet'!C29,0) -> 943.29 | E30: =IFERROR('Data Sheet'!D29,0) -> 1040.96 | F30: =IFERROR('Data Sheet'!E29,0) -> 1098.06 | G30: =IFERROR('Data Sheet'!F29,0) -> 854.85 | H30: =IFERROR('Data Sheet'!G29,0) -> 1097.6 | I30: =IFERROR('Data Sheet'!H29,0) -> 1102.91 | J30: =IFERROR('Data Sheet'!I29,0) -> 1493.5 | ... L30: =IFERROR('Data Sheet'!K29,0) -> 1393.36 | M30: =IFERROR(SUM('Data Sheet'!H48:K48),0) -> 1501.54
B31: Effective Tax Rate | C31: =C30/C27 -> 0.3518034 | D31: =D30/D27 -> 0.35980913 | E31: =E30/E27 -> 0.37149679 | F31: =F30/F27 -> 0.36211758 | G31: =G30/G27 -> 0.26070925 | H31: =H30/H27 -> 0.27628565 | I31: =I30/I27 -> 0.28339038 | J31: =J30/J27 -> 0.2840774 | ... M31: =M30/M27 -> 0.20534386
B33: Net Profit | C33: =IFERROR(C27-C30,0) -> 1555.97 | D33: =IFERROR(D27-D30,0) -> 1678.35 | E33: =IFERROR(E27-E30,0) -> 1761.11 | F33: =IFERROR(F27-F30,0) -> 1934.27 | G33: =IFERROR(G27-G30,0) -> 2424.09 | H33: =IFERROR(H27-H30,0) -> 2875.1 | I33: =IFERROR(I27-I30,0) -> 2788.93 | J33: =IFERROR(J27-J30,0) -> 3763.87 | ... M33: =IFERROR(M27-M30,0) -> 5810.78
B34: Net Profit Margin | C34: =C33/C6 -> 0.10902646 | D34: =D33/D6 -> 0.1114295 | E34: =E33/E6 -> 0.10467501 | F34: =F33/F6 -> 0.1005331 | G34: =G33/G6 -> 0.11993766 | H34: =H33/H6 -> 0.13241504 | I34: =I33/I6 -> 0.095835303 | J34: =J33/J6 -> 0.10913377 | ... M34: =M33/M6 -> 0.16747815
B36: No. of Equity Shares | C36: =IFERROR('Data Sheet'!B93,0) -> 95.92 | D36: =IFERROR('Data Sheet'!C93,0) -> 95.92 | E36: =IFERROR('Data Sheet'!D93,0) -> 95.92 | F36: =IFERROR('Data Sheet'!E93,0) -> 95.92 | G36: =IFERROR('Data Sheet'!F93,0) -> 95.92 | H36: =IFERROR('Data Sheet'!G93,0) -> 95.92 | I36: =IFERROR('Data Sheet'!H93,0) -> 95.92 | J36: =IFERROR('Data Sheet'!I93,0) -> 95.92 | ... M36: =IFERROR('Data Sheet'!L93,0) -> 0
B38: Earning per Shares | C38: =IFERROR(C33/C36,0) -> 16.221539 | D38: =IFERROR(D33/D36,0) -> 17.497394 | E38: =IFERROR(E33/E36,0) -> 18.360196 | F38: =IFERROR(F33/F36,0) -> 20.16545 | G38: =IFERROR(G33/G36,0) -> 25.271997 | H38: =IFERROR(H33/H36,0) -> 29.973937 | I38: =IFERROR(I33/I36,0) -> 29.075584 | J38: =IFERROR(J33/J36,0) -> 39.239679 | ... M38: =IFERROR(M33/M36,0) -> 0
B39: EPS Growth % | D39: =IFERROR(D38/C38-1,0) -> 0.078651902 | E39: =IFERROR(E38/D38-1,0) -> 0.049310335 | F39: =IFERROR(F38/E38-1,0) -> 0.098324352 | G39: =IFERROR(G38/F38-1,0) -> 0.25323249 | H39: =IFERROR(H38/G38-1,0) -> 0.18605332 | I39: =IFERROR(I38/H38-1,0) -> -0.029971131 | J39: =IFERROR(J38/I38-1,0) -> 0.34957493 | K39: =IFERROR(K38/J38-1,0) -> 0.25847333 | ... M39: =IFERROR(M38/L38-1,0) -> -1
B41: Dividend per Share | C41: =IFERROR('Data Sheet'!B31/'Historical FS '!C36,0) -> 7.5 | D41: =IFERROR('Data Sheet'!C31/'Historical FS '!D36,0) -> 10.300042 | E41: =IFERROR('Data Sheet'!D31/'Historical FS '!E36,0) -> 8.6999583 | F41: =IFERROR('Data Sheet'!E31/'Historical FS '!F36,0) -> 10.5 | G41: =IFERROR('Data Sheet'!F31/'Historical FS '!G36,0) -> 12 | H41: =IFERROR('Data Sheet'!G31/'Historical FS '!H36,0) -> 17.849979 | I41: =IFERROR('Data Sheet'!H31/'Historical FS '!I36,0) -> 19.150021 | J41: =IFERROR('Data Sheet'!I31/'Historical FS '!J36,0) -> 25.650021 | ... M41: =IFERROR('Data Sheet'!L31/'Historical FS '!M36,0) -> 0
B42: Dividend pay out Ratio | C42: =IFERROR(C41/C38,0) -> 0.46234825 | D42: =IFERROR(D41/D38,0) -> 0.58866148 | E42: =IFERROR(E41/E38,0) -> 0.47384888 | F42: =IFERROR(F41/F38,0) -> 0.52069256 | G42: =IFERROR(G41/G38,0) -> 0.47483386 | H42: =IFERROR(H41/H38,0) -> 0.59551668 | I42: =IFERROR(I41/I38,0) -> 0.65862894 | J42: =IFERROR(J41/J38,0) -> 0.65367561 | ... M42: =IFERROR(M41/M38,0) -> 0
B44: Retained Earning | C44: =IFERROR(1-C42,0) -> 0.53765175 | D44: =IFERROR(1-D42,0) -> 0.41133852 | E44: =IFERROR(1-E42,0) -> 0.52615112 | F44: =IFERROR(1-F42,0) -> 0.47930744 | G44: =IFERROR(1-G42,0) -> 0.52516614 | H44: =IFERROR(1-H42,0) -> 0.40448332 | I44: =IFERROR(1-I42,0) -> 0.34137106 | J44: =IFERROR(1-J42,0) -> 0.34632439 | ... M44: =IFERROR(1-M42,0) -> 1
B45: Retained Earning | C45: =IFERROR(IF(C38>C41,1-C42,0),0) -> 0.53765175 | D45: =IFERROR(IF(D38>D41,1-D42,0),0) -> 0.41133852 | E45: =IFERROR(IF(E38>E41,1-E42,0),0) -> 0.52615112 | F45: =IFERROR(IF(F38>F41,1-F42,0),0) -> 0.47930744 | G45: =IFERROR(IF(G38>G41,1-G42,0),0) -> 0.52516614 | H45: =IFERROR(IF(H38>H41,1-H42,0),0) -> 0.40448332 | I45: =IFERROR(IF(I38>I41,1-I42,0),0) -> 0.34137106 | J45: =IFERROR(IF(J38>J41,1-J42,0),0) -> 0.34632439 | ... M45: =IFERROR(IF(M38>M41,1-M42,0),0) -> 0
A47: # | B47: Balance Sheet
B48: Equity Share Capital | C48: =IFERROR('Data Sheet'!B57,0) -> 95.92 | D48: =IFERROR('Data Sheet'!C57,0) -> 95.92 | E48: =IFERROR('Data Sheet'!D57,0) -> 95.92 | F48: =IFERROR('Data Sheet'!E57,0) -> 95.92 | G48: =IFERROR('Data Sheet'!F57,0) -> 95.92 | H48: =IFERROR('Data Sheet'!G57,0) -> 95.92 | I48: =IFERROR('Data Sheet'!H57,0) -> 95.92 | J48: =IFERROR('Data Sheet'!I57,0) -> 95.92 | ... L48: =IFERROR('Data Sheet'!K57,0) -> 95.92
B49: Reserves | C49: =IFERROR('Data Sheet'!B58,0) -> 6428.9 | D49: =IFERROR('Data Sheet'!C58,0) -> 7507.97 | E49: =IFERROR('Data Sheet'!D58,0) -> 8314.31 | F49: =IFERROR('Data Sheet'!E58,0) -> 9374.63 | G49: =IFERROR('Data Sheet'!F58,0) -> 10034.24 | H49: =IFERROR('Data Sheet'!G58,0) -> 12710.37 | I49: =IFERROR('Data Sheet'!H58,0) -> 13715.64 | J49: =IFERROR('Data Sheet'!I58,0) -> 15896.31 | ... L49: =IFERROR('Data Sheet'!K58,0) -> 19303.89
B50: Borrowings | C50: =IFERROR('Data Sheet'!B59,0) -> 323.29 | D50: =IFERROR('Data Sheet'!C59,0) -> 560.34 | E50: =IFERROR('Data Sheet'!D59,0) -> 533.43 | F50: =IFERROR('Data Sheet'!E59,0) -> 1319.6 | G50: =IFERROR('Data Sheet'!F59,0) -> 1118.5 | H50: =IFERROR('Data Sheet'!G59,0) -> 1093.12 | I50: =IFERROR('Data Sheet'!H59,0) -> 1586.88 | J50: =IFERROR('Data Sheet'!I59,0) -> 1932.62 | ... L50: =IFERROR('Data Sheet'!K59,0) -> 2290.29
B51: Other Liabilities | C51: =IFERROR('Data Sheet'!B60,0) -> 3710.92 | D51: =IFERROR('Data Sheet'!C60,0) -> 4240.96 | E51: =IFERROR('Data Sheet'!D60,0) -> 4819.82 | F51: =IFERROR('Data Sheet'!E60,0) -> 5458.69 | G51: =IFERROR('Data Sheet'!F60,0) -> 4889.31 | H51: =IFERROR('Data Sheet'!G60,0) -> 6455.93 | I51: =IFERROR('Data Sheet'!H60,0) -> 7559.99 | J51: =IFERROR('Data Sheet'!I60,0) -> 7854.48 | ... L51: =IFERROR('Data Sheet'!K60,0) -> 8665.15
B52: Total Liabilities | C52: =SUM(C48:C51) -> 10559.03 | D52: =SUM(D48:D51) -> 12405.19 | E52: =SUM(E48:E51) -> 13763.48 | F52: =SUM(F48:F51) -> 16248.84 | G52: =SUM(G48:G51) -> 16137.97 | H52: =SUM(H48:H51) -> 20355.34 | I52: =SUM(I48:I51) -> 22958.43 | J52: =SUM(J48:J51) -> 25779.33 | ... L52: =SUM(L48:L51) -> 30355.25
B54: Fixed Assets Net Block | C54: =IFERROR('Data Sheet'!B62,0) -> 3416.35 | D54: =IFERROR('Data Sheet'!C62,0) -> 3303.74 | E54: =IFERROR('Data Sheet'!D62,0) -> 3732.24 | F54: =IFERROR('Data Sheet'!E62,0) -> 6496.56 | G54: =IFERROR('Data Sheet'!F62,0) -> 6272.31 | H54: =IFERROR('Data Sheet'!G62,0) -> 5858.52 | I54: =IFERROR('Data Sheet'!H62,0) -> 5519.06 | J54: =IFERROR('Data Sheet'!I62,0) -> 5770.46 | ... L54: =IFERROR('Data Sheet'!K62,0) -> 9220.1
B55: Capital Work in Progress | C55: =IFERROR('Data Sheet'!B63,0) -> 106.59 | D55: =IFERROR('Data Sheet'!C63,0) -> 257.54 | E55: =IFERROR('Data Sheet'!D63,0) -> 1405.11 | F55: =IFERROR('Data Sheet'!E63,0) -> 209.67 | G55: =IFERROR('Data Sheet'!F63,0) -> 140.24 | H55: =IFERROR('Data Sheet'!G63,0) -> 182.98 | I55: =IFERROR('Data Sheet'!H63,0) -> 426.43 | J55: =IFERROR('Data Sheet'!I63,0) -> 1019.59 | ... L55: =IFERROR('Data Sheet'!K63,0) -> 1254.49
B56: Investments | C56: =IFERROR('Data Sheet'!B64,0) -> 2712.13 | D56: =IFERROR('Data Sheet'!C64,0) -> 2651.99 | E56: =IFERROR('Data Sheet'!D64,0) -> 2140.7 | F56: =IFERROR('Data Sheet'!E64,0) -> 2568.58 | G56: =IFERROR('Data Sheet'!F64,0) -> 2018.85 | H56: =IFERROR('Data Sheet'!G64,0) -> 4736.8 | I56: =IFERROR('Data Sheet'!H64,0) -> 3247.53 | J56: =IFERROR('Data Sheet'!I64,0) -> 4261.71 | ... L56: =IFERROR('Data Sheet'!K64,0) -> 4724.75
B57: Other Assets | C57: =IFERROR('Data Sheet'!B65-SUM('Data Sheet'!B67:B69),0) -> 714.72 | D57: =IFERROR('Data Sheet'!C65-SUM('Data Sheet'!C67:C69),0) -> 1317.17 | E57: =IFERROR('Data Sheet'!D65-SUM('Data Sheet'!D67:D69),0) -> 1691.84 | F57: =IFERROR('Data Sheet'!E65-SUM('Data Sheet'!E67:E69),0) -> 1471.96 | G57: =IFERROR('Data Sheet'!F65-SUM('Data Sheet'!F67:F69),0) -> 1738.71 | H57: =IFERROR('Data Sheet'!G65-SUM('Data Sheet'!G67:G69),0) -> 2565.52 | I57: =IFERROR('Data Sheet'!H65-SUM('Data Sheet'!H67:H69),0) -> 2876.66 | J57: =IFERROR('Data Sheet'!I65-SUM('Data Sheet'!I67:I69),0) -> 3036.17 | ... L57: =IFERROR('Data Sheet'!K65-SUM('Data Sheet'!K67:K69),0) -> 3341.01
B58: Total Non Current Assets | C58: =SUM(C54:C57) -> 6949.79 | D58: =SUM(D54:D57) -> 7530.44 | E58: =SUM(E54:E57) -> 8969.89 | F58: =SUM(F54:F57) -> 10746.77 | G58: =SUM(G54:G57) -> 10170.11 | H58: =SUM(H54:H57) -> 13343.82 | I58: =SUM(I54:I57) -> 12069.68 | J58: =SUM(J54:J57) -> 14087.93 | ... L58: =SUM(L54:L57) -> 18540.35
B60: Receivables | C60: =IFERROR('Data Sheet'!B67,0) -> 1186.84 | D60: =IFERROR('Data Sheet'!C67,0) -> 1446.6 | E60: =IFERROR('Data Sheet'!D67,0) -> 1730.63 | F60: =IFERROR('Data Sheet'!E67,0) -> 1907.33 | G60: =IFERROR('Data Sheet'!F67,0) -> 1795.22 | H60: =IFERROR('Data Sheet'!G67,0) -> 2602.17 | I60: =IFERROR('Data Sheet'!H67,0) -> 3871.44 | J60: =IFERROR('Data Sheet'!I67,0) -> 4636.94 | ... L60: =IFERROR('Data Sheet'!K67,0) -> 4313.65
B61: Inventory | C61: =IFERROR('Data Sheet'!B68,0) -> 1998.24 | D61: =IFERROR('Data Sheet'!C68,0) -> 2626.94 | E61: =IFERROR('Data Sheet'!D68,0) -> 2658.31 | F61: =IFERROR('Data Sheet'!E68,0) -> 3149.86 | G61: =IFERROR('Data Sheet'!F68,0) -> 3389.81 | H61: =IFERROR('Data Sheet'!G68,0) -> 3798.6 | I61: =IFERROR('Data Sheet'!H68,0) -> 6152.98 | J61: =IFERROR('Data Sheet'!I68,0) -> 6210.64 | ... L61: =IFERROR('Data Sheet'!K68,0) -> 6719.27
B62: Cash & Bank | C62: =IFERROR('Data Sheet'!B69,0) -> 424.2 | D62: =IFERROR('Data Sheet'!C69,0) -> 801.21 | E62: =IFERROR('Data Sheet'!D69,0) -> 404.65 | F62: =IFERROR('Data Sheet'!E69,0) -> 444.88 | G62: =IFERROR('Data Sheet'!F69,0) -> 782.83 | H62: =IFERROR('Data Sheet'!G69,0) -> 610.75 | I62: =IFERROR('Data Sheet'!H69,0) -> 864.33 | J62: =IFERROR('Data Sheet'!I69,0) -> 843.82 | ... L62: =IFERROR('Data Sheet'!K69,0) -> 781.98
B63: Total Current Asset | C63: =SUM(C60:C62) -> 3609.28 | D63: =SUM(D60:D62) -> 4874.75 | E63: =SUM(E60:E62) -> 4793.59 | F63: =SUM(F60:F62) -> 5502.07 | G63: =SUM(G60:G62) -> 5967.86 | H63: =SUM(H60:H62) -> 7011.52 | I63: =SUM(I60:I62) -> 10888.75 | J63: =SUM(J60:J62) -> 11691.4 | ... L63: =SUM(L60:L62) -> 11814.9
B65: Total Assets | C65: =IFERROR(C63+C58,0) -> 10559.07 | D65: =IFERROR(D63+D58,0) -> 12405.19 | E65: =IFERROR(E63+E58,0) -> 13763.48 | F65: =IFERROR(F63+F58,0) -> 16248.84 | G65: =IFERROR(G63+G58,0) -> 16137.97 | H65: =IFERROR(H63+H58,0) -> 20355.34 | I65: =IFERROR(I63+I58,0) -> 22958.43 | J65: =IFERROR(J63+J58,0) -> 25779.33 | ... L65: =IFERROR(L63+L58,0) -> 30355.25
B67: Check | C67: =C65=C52 -> FALSE | D67: =D65=D52 -> TRUE | E67: =E65=E52 -> TRUE | F67: =F65=F52 -> TRUE | G67: =G65=G52 -> TRUE | H67: =H65=H52 -> TRUE | I67: =I65=I52 -> TRUE | J67: =J65=J52 -> TRUE | ... L67: =L65=L52 -> TRUE
A69: # | B69: Cash Flow Statement
B70: Operating Activities
B71: Profit from operations | C71: =IFERROR('Cash Flow Data'!E6,0) -> 2848 | D71: =IFERROR('Cash Flow Data'!F6,0) -> 3056 | E71: =IFERROR('Cash Flow Data'!G6,0) -> 3274 | F71: =IFERROR('Cash Flow Data'!H6,0) -> 3861 | G71: =IFERROR('Cash Flow Data'!I6,0) -> 4380 | H71: =IFERROR('Cash Flow Data'!J6,0) -> 4970 | I71: =IFERROR('Cash Flow Data'!K6,0) -> 4957 | J71: =IFERROR('Cash Flow Data'!L6,0) -> 6460 | ... L71: =IFERROR('Cash Flow Data'!N6,0) -> 6390
B72: Receivables | C72: =IFERROR('Cash Flow Data'!E7,0) -> -146 | D72: =IFERROR('Cash Flow Data'!F7,0) -> -475 | E72: =IFERROR('Cash Flow Data'!G7,0) -> -483 | F72: =IFERROR('Cash Flow Data'!H7,0) -> -205 | G72: =IFERROR('Cash Flow Data'!I7,0) -> 160 | H72: =IFERROR('Cash Flow Data'!J7,0) -> -1342 | I72: =IFERROR('Cash Flow Data'!K7,0) -> -1326 | J72: =IFERROR('Cash Flow Data'!L7,0) -> -834 | ... L72: =IFERROR('Cash Flow Data'!N7,0) -> 282
B73: Inventory | C73: =IFERROR('Cash Flow Data'!E8,0) -> 202 | D73: =IFERROR('Cash Flow Data'!F8,0) -> -629 | E73: =IFERROR('Cash Flow Data'!G8,0) -> -39 | F73: =IFERROR('Cash Flow Data'!H8,0) -> -492 | G73: =IFERROR('Cash Flow Data'!I8,0) -> -251 | H73: =IFERROR('Cash Flow Data'!J8,0) -> -409 | I73: =IFERROR('Cash Flow Data'!K8,0) -> -2354 | J73: =IFERROR('Cash Flow Data'!L8,0) -> -56 | ... L73: =IFERROR('Cash Flow Data'!N8,0) -> -805
B74: Payables | C74: =IFERROR('Cash Flow Data'!E9,0) -> 142 | D74: =IFERROR('Cash Flow Data'!F9,0) -> 501 | E74: =IFERROR('Cash Flow Data'!G9,0) -> 442 | F74: =IFERROR('Cash Flow Data'!H9,0) -> 287 | G74: =IFERROR('Cash Flow Data'!I9,0) -> -647 | H74: =IFERROR('Cash Flow Data'!J9,0) -> 1544 | I74: =IFERROR('Cash Flow Data'!K9,0) -> 644 | J74: =IFERROR('Cash Flow Data'!L9,0) -> -539 | ... L74: =IFERROR('Cash Flow Data'!N9,0) -> -160
B75: Other WC items | C75: =IFERROR('Cash Flow Data'!E10,0) -> 0 | D75: =IFERROR('Cash Flow Data'!F10,0) -> 0 | E75: =IFERROR('Cash Flow Data'!G10,0) -> 0 | F75: =IFERROR('Cash Flow Data'!H10,0) -> 0 | G75: =IFERROR('Cash Flow Data'!I10,0) -> 0 | H75: =IFERROR('Cash Flow Data'!J10,0) -> 0 | I75: =IFERROR('Cash Flow Data'!K10,0) -> 242 | J75: =IFERROR('Cash Flow Data'!L10,0) -> 657 | ... L75: =IFERROR('Cash Flow Data'!N10,0) -> 114
B76: Working capital changes | C76: =IFERROR('Cash Flow Data'!E11,0) -> 198 | D76: =IFERROR('Cash Flow Data'!F11,0) -> -603 | E76: =IFERROR('Cash Flow Data'!G11,0) -> -80 | F76: =IFERROR('Cash Flow Data'!H11,0) -> -410 | G76: =IFERROR('Cash Flow Data'!I11,0) -> -737 | H76: =IFERROR('Cash Flow Data'!J11,0) -> -206 | I76: =IFERROR('Cash Flow Data'!K11,0) -> -2795 | J76: =IFERROR('Cash Flow Data'!L11,0) -> -772 | ... L76: =IFERROR('Cash Flow Data'!N11,0) -> -570
B77: Direct taxes | C77: =IFERROR('Cash Flow Data'!E12,0) -> -802 | D77: =IFERROR('Cash Flow Data'!F12,0) -> -925 | E77: =IFERROR('Cash Flow Data'!G12,0) -> -1081 | F77: =IFERROR('Cash Flow Data'!H12,0) -> -982 | G77: =IFERROR('Cash Flow Data'!I12,0) -> -1011 | H77: =IFERROR('Cash Flow Data'!J12,0) -> -1080 | I77: =IFERROR('Cash Flow Data'!K12,0) -> -1176 | J77: =IFERROR('Cash Flow Data'!L12,0) -> -1494 | ... L77: =IFERROR('Cash Flow Data'!N12,0) -> -1396
B78: Cash from Operating Activities | C78: =SUM(C71:C77) -> 2442 | D78: =SUM(D71:D77) -> 925 | E78: =SUM(E71:E77) -> 2033 | F78: =SUM(F71:F77) -> 2059 | G78: =SUM(G71:G77) -> 1894 | H78: =SUM(H71:H77) -> 3477 | I78: =SUM(I71:I77) -> -1808 | J78: =SUM(J71:J77) -> 3422 | ... L78: =SUM(L71:L77) -> 3855
B80: Investing Activities
B81: Fixed assets purchased | C81: =IFERROR('Cash Flow Data'!E16,0) -> -817 | D81: =IFERROR('Cash Flow Data'!F16,0) -> -684 | E81: =IFERROR('Cash Flow Data'!G16,0) -> -1426 | F81: =IFERROR('Cash Flow Data'!H16,0) -> -1151 | G81: =IFERROR('Cash Flow Data'!I16,0) -> -414 | H81: =IFERROR('Cash Flow Data'!J16,0) -> -289 | I81: =IFERROR('Cash Flow Data'!K16,0) -> -551 | J81: =IFERROR('Cash Flow Data'!L16,0) -> -1446 | ... M81: =IFERROR('Cash Flow Data'!O16,0) -> 0
B82: Fixed assets sold | C82: =IFERROR('Cash Flow Data'!E17,0) -> 15 | D82: =IFERROR('Cash Flow Data'!F17,0) -> 17 | E82: =IFERROR('Cash Flow Data'!G17,0) -> 17 | F82: =IFERROR('Cash Flow Data'!H17,0) -> 17 | G82: =IFERROR('Cash Flow Data'!I17,0) -> 37 | H82: =IFERROR('Cash Flow Data'!J17,0) -> 28 | I82: =IFERROR('Cash Flow Data'!K17,0) -> 40 | J82: =IFERROR('Cash Flow Data'!L17,0) -> 26 | ... L82: =IFERROR('Cash Flow Data'!N17,0) -> 10
B83: Investments purchased | C83: =IFERROR('Cash Flow Data'!E18,0) -> -282 | D83: =IFERROR('Cash Flow Data'!F18,0) -> -153 | E83: =IFERROR('Cash Flow Data'!G18,0) -> -320 | F83: =IFERROR('Cash Flow Data'!H18,0) -> -573 | G83: =IFERROR('Cash Flow Data'!I18,0) -> -25 | H83: =IFERROR('Cash Flow Data'!J18,0) -> -140 | I83: =IFERROR('Cash Flow Data'!K18,0) -> 0 | J83: =IFERROR('Cash Flow Data'!L18,0) -> -146 | ... L83: =IFERROR('Cash Flow Data'!N18,0) -> -1
B84: Investments sold | C84: =IFERROR('Cash Flow Data'!E19,0) -> 205 | D84: =IFERROR('Cash Flow Data'!F19,0) -> 357 | E84: =IFERROR('Cash Flow Data'!G19,0) -> 362 | F84: =IFERROR('Cash Flow Data'!H19,0) -> 733 | G84: =IFERROR('Cash Flow Data'!I19,0) -> 118 | H84: =IFERROR('Cash Flow Data'!J19,0) -> 272 | I84: =IFERROR('Cash Flow Data'!K19,0) -> 207 | J84: =IFERROR('Cash Flow Data'!L19,0) -> 446 | ... L84: =IFERROR('Cash Flow Data'!N19,0) -> 421
B85: Interest received | C85: =IFERROR('Cash Flow Data'!E20,0) -> 15 | D85: =IFERROR('Cash Flow Data'!F20,0) -> 32 | E85: =IFERROR('Cash Flow Data'!G20,0) -> 39 | F85: =IFERROR('Cash Flow Data'!H20,0) -> 40 | G85: =IFERROR('Cash Flow Data'!I20,0) -> 65 | H85: =IFERROR('Cash Flow Data'!J20,0) -> 73 | I85: =IFERROR('Cash Flow Data'!K20,0) -> 77 | J85: =IFERROR('Cash Flow Data'!L20,0) -> 87 | ... L85: =IFERROR('Cash Flow Data'!N20,0) -> 155
B86: Dividends received | C86: =IFERROR('Cash Flow Data'!E21,0) -> 69 | D86: =IFERROR('Cash Flow Data'!F21,0) -> 74 | E86: =IFERROR('Cash Flow Data'!G21,0) -> 38 | F86: =IFERROR('Cash Flow Data'!H21,0) -> 40 | G86: =IFERROR('Cash Flow Data'!I21,0) -> 27 | H86: =IFERROR('Cash Flow Data'!J21,0) -> 8 | I86: =IFERROR('Cash Flow Data'!K21,0) -> 15 | J86: =IFERROR('Cash Flow Data'!L21,0) -> 56 | ... L86: =IFERROR('Cash Flow Data'!N21,0) -> 136
B87: Investment in group cos | C87: =IFERROR('Cash Flow Data'!E22,0) -> 0 | D87: =IFERROR('Cash Flow Data'!F22,0) -> 0 | E87: =IFERROR('Cash Flow Data'!G22,0) -> 0 | F87: =IFERROR('Cash Flow Data'!H22,0) -> 0 | G87: =IFERROR('Cash Flow Data'!I22,0) -> 0 | H87: =IFERROR('Cash Flow Data'!J22,0) -> 0 | I87: =IFERROR('Cash Flow Data'!K22,0) -> 0 | J87: =IFERROR('Cash Flow Data'!L22,0) -> -180 | ... L87: =IFERROR('Cash Flow Data'!N22,0) -> 0
B88: Redemp n Canc of Shares | C88: =IFERROR('Cash Flow Data'!E23,0) -> 0 | D88: =IFERROR('Cash Flow Data'!F23,0) -> 0 | E88: =IFERROR('Cash Flow Data'!G23,0) -> 141 | F88: =IFERROR('Cash Flow Data'!H23,0) -> 0 | G88: =IFERROR('Cash Flow Data'!I23,0) -> 17 | H88: =IFERROR('Cash Flow Data'!J23,0) -> 0 | I88: =IFERROR('Cash Flow Data'!K23,0) -> 0 | J88: =IFERROR('Cash Flow Data'!L23,0) -> 0 | ... L88: =IFERROR('Cash Flow Data'!N23,0) -> 38
B89: Acquisition of companies | C89: =IFERROR('Cash Flow Data'!E24,0) -> 0 | D89: =IFERROR('Cash Flow Data'!F24,0) -> 0 | E89: =IFERROR('Cash Flow Data'!G24,0) -> -525 | F89: =IFERROR('Cash Flow Data'!H24,0) -> 0 | G89: =IFERROR('Cash Flow Data'!I24,0) -> 0 | H89: =IFERROR('Cash Flow Data'!J24,0) -> 0 | I89: =IFERROR('Cash Flow Data'!K24,0) -> 0 | J89: =IFERROR('Cash Flow Data'!L24,0) -> 0 | ... L89: =IFERROR('Cash Flow Data'!N24,0) -> 0
B90: Other investing items | C90: =IFERROR('Cash Flow Data'!E25,0) -> -70 | D90: =IFERROR('Cash Flow Data'!F25,0) -> -324 | E90: =IFERROR('Cash Flow Data'!G25,0) -> 118 | F90: =IFERROR('Cash Flow Data'!H25,0) -> -24 | G90: =IFERROR('Cash Flow Data'!I25,0) -> -343 | H90: =IFERROR('Cash Flow Data'!J25,0) -> -493 | I90: =IFERROR('Cash Flow Data'!K25,0) -> -105 | J90: =IFERROR('Cash Flow Data'!L25,0) -> -126 | ... L90: =IFERROR('Cash Flow Data'!N25,0) -> 130
B91: Cash From Investing Activities | C91: =SUM(C81:C90) -> -865 | D91: =SUM(D81:D90) -> -681 | E91: =SUM(E81:E90) -> -1556 | F91: =SUM(F81:F90) -> -918 | G91: =SUM(G81:G90) -> -518 | H91: =SUM(H81:H90) -> -541 | I91: =SUM(I81:I90) -> -317 | J91: =SUM(J81:J90) -> -1283 | ... L91: =SUM(L81:L90) -> -941
B93: Financing Activities
B94: Proceeds from shares | C94: =IFERROR('Cash Flow Data'!E29,0) -> 0 | D94: =IFERROR('Cash Flow Data'!F29,0) -> 0 | E94: =IFERROR('Cash Flow Data'!G29,0) -> 0 | F94: =IFERROR('Cash Flow Data'!H29,0) -> 0 | G94: =IFERROR('Cash Flow Data'!I29,0) -> 0 | H94: =IFERROR('Cash Flow Data'!J29,0) -> 0 | I94: =IFERROR('Cash Flow Data'!K29,0) -> 0 | J94: =IFERROR('Cash Flow Data'!L29,0) -> 0 | ... L94: =IFERROR('Cash Flow Data'!N29,0) -> 0
B95: Proceeds from borrowings | C95: =IFERROR('Cash Flow Data'!E30,0) -> 8 | D95: =IFERROR('Cash Flow Data'!F30,0) -> 271 | E95: =IFERROR('Cash Flow Data'!G30,0) -> 10 | F95: =IFERROR('Cash Flow Data'!H30,0) -> 243 | G95: =IFERROR('Cash Flow Data'!I30,0) -> 221 | H95: =IFERROR('Cash Flow Data'!J30,0) -> 155 | I95: =IFERROR('Cash Flow Data'!K30,0) -> 418 | J95: =IFERROR('Cash Flow Data'!L30,0) -> 254 | ... L95: =IFERROR('Cash Flow Data'!N30,0) -> 415
B96: Repayment of borrowings | C96: =IFERROR('Cash Flow Data'!E31,0) -> -119 | D96: =IFERROR('Cash Flow Data'!F31,0) -> -58 | E96: =IFERROR('Cash Flow Data'!G31,0) -> -54 | F96: =IFERROR('Cash Flow Data'!H31,0) -> -26 | G96: =IFERROR('Cash Flow Data'!I31,0) -> -279 | H96: =IFERROR('Cash Flow Data'!J31,0) -> -14 | I96: =IFERROR('Cash Flow Data'!K31,0) -> -8 | J96: =IFERROR('Cash Flow Data'!L31,0) -> -25 | ... L96: =IFERROR('Cash Flow Data'!N31,0) -> -428
B97: Interest paid fin | C97: =IFERROR('Cash Flow Data'!E32,0) -> -40 | D97: =IFERROR('Cash Flow Data'!F32,0) -> -36 | E97: =IFERROR('Cash Flow Data'!G32,0) -> -35 | F97: =IFERROR('Cash Flow Data'!H32,0) -> -106 | G97: =IFERROR('Cash Flow Data'!I32,0) -> -101 | H97: =IFERROR('Cash Flow Data'!J32,0) -> -89 | I97: =IFERROR('Cash Flow Data'!K32,0) -> -94 | J97: =IFERROR('Cash Flow Data'!L32,0) -> -142 | ... L97: =IFERROR('Cash Flow Data'!N32,0) -> -203
B98: Dividends paid | C98: =IFERROR('Cash Flow Data'!E33,0) -> -764 | D98: =IFERROR('Cash Flow Data'!F33,0) -> -947 | E98: =IFERROR('Cash Flow Data'!G33,0) -> -1218 | F98: =IFERROR('Cash Flow Data'!H33,0) -> -1049 | G98: =IFERROR('Cash Flow Data'!I33,0) -> -2121 | H98: =IFERROR('Cash Flow Data'!J33,0) -> -499 | I98: =IFERROR('Cash Flow Data'!K33,0) -> -1763 | J98: =IFERROR('Cash Flow Data'!L33,0) -> -1936 | ... L98: =IFERROR('Cash Flow Data'!N33,0) -> -3140
B99: Financial liabilities | C99: =IFERROR('Cash Flow Data'!E34,0) -> 0 | D99: =IFERROR('Cash Flow Data'!F34,0) -> 0 | E99: =IFERROR('Cash Flow Data'!G34,0) -> 0 | F99: =IFERROR('Cash Flow Data'!H34,0) -> -180 | G99: =IFERROR('Cash Flow Data'!I34,0) -> -179 | H99: =IFERROR('Cash Flow Data'!J34,0) -> -203 | I99: =IFERROR('Cash Flow Data'!K34,0) -> -221 | J99: =IFERROR('Cash Flow Data'!L34,0) -> -256 | ... L99: =IFERROR('Cash Flow Data'!N34,0) -> -325
B100: Other financing items | C100: =IFERROR('Cash Flow Data'!E35,0) -> 66 | D100: =IFERROR('Cash Flow Data'!F35,0) -> 13 | E100: =IFERROR('Cash Flow Data'!G35,0) -> -82 | F100: =IFERROR('Cash Flow Data'!H35,0) -> 0 | G100: =IFERROR('Cash Flow Data'!I35,0) -> -6 | H100: =IFERROR('Cash Flow Data'!J35,0) -> 0 | I100: =IFERROR('Cash Flow Data'!K35,0) -> -140 | J100: =IFERROR('Cash Flow Data'!L35,0) -> -36 | ... L100: =IFERROR('Cash Flow Data'!N35,0) -> -72
B101: Cash from Financing Activities | C101: =SUM(C94:C100) -> -849 | D101: =SUM(D94:D100) -> -757 | E101: =SUM(E94:E100) -> -1379 | F101: =SUM(F94:F100) -> -1118 | G101: =SUM(G94:G100) -> -2465 | H101: =SUM(H94:H100) -> -650 | I101: =SUM(I94:I100) -> -1808 | J101: =SUM(J94:J100) -> -2141 | ... L101: =SUM(L94:L100) -> -3753
B103: Net Cash Flow | C103: =IFERROR(C78+C91+C101,0) -> 728 | D103: =IFERROR(D78+D91+D101,0) -> -513 | E103: =IFERROR(E78+E91+E101,0) -> -902 | F103: =IFERROR(F78+F91+F101,0) -> 23 | G103: =IFERROR(G78+G91+G101,0) -> -1089 | H103: =IFERROR(H78+H91+H101,0) -> 2286 | I103: =IFERROR(I78+I91+I101,0) -> -3933 | J103: =IFERROR(J78+J91+J101,0) -> -2 | ... L103: =IFERROR(L78+L91+L101,0) -> -839
A105: # | B105: Short Cash Flow Statement
B107: Cash from Operating Activities | C107: =C78 -> 2442 | D107: =D78 -> 925 | E107: =E78 -> 2033 | F107: =F78 -> 2059 | G107: =G78 -> 1894 | H107: =H78 -> 3477 | I107: =I78 -> -1808 | J107: =J78 -> 3422 | ... L107: =L78 -> 3855
B109: Cash From Investing Activities | C109: =C91 -> -865 | D109: =D91 -> -681 | E109: =E91 -> -1556 | F109: =F91 -> -918 | G109: =G91 -> -518 | H109: =H91 -> -541 | I109: =I91 -> -317 | J109: =J91 -> -1283 | ... L109: =L91 -> -941
B111: Cash from Financing Activities | C111: =C101 -> -849 | D111: =D101 -> -757 | E111: =E101 -> -1379 | F111: =F101 -> -1118 | G111: =G101 -> -2465 | H111: =H101 -> -650 | I111: =I101 -> -1808 | J111: =J101 -> -2141 | ... L111: =L101 -> -3753
B113: Net Cash Flow | C113: =SUM(C107:C111) -> 728 | D113: =SUM(D107:D111) -> -513 | E113: =SUM(E107:E111) -> -902 | F113: =SUM(F107:F111) -> 23 | G113: =SUM(G107:G111) -> -1089 | H113: =SUM(H107:H111) -> 2286 | I113: =SUM(I107:I111) -> -3933 | J113: =SUM(J107:J111) -> -2 | ... L113: =SUM(L107:L111) -> -839

Sheet Ratio Analysis
B2: ="Ratio Analysis - "&'Data Sheet'!B1 -> Ratio Analysis - ASIAN PAINTS LTD
B3: Years | C3: ='Data Sheet'!B16 -> 42460 | D3: ='Data Sheet'!C16 -> 42825 | E3: ='Data Sheet'!D16 -> 43190 | F3: ='Data Sheet'!E16 -> 43555 | G3: ='Data Sheet'!F16 -> 43921 | H3: ='Data Sheet'!G16 -> 44286 | I3: ='Data Sheet'!H16 -> 44651 | J3: ='Data Sheet'!I16 -> 45016 | ... L3: ='Data Sheet'!K16 -> 45747 | M3: Trend | N3: Mean | O3: Medin
O4: Medin
B5: SalesGrowth | D5: =IFERROR('Historical FS '!D7,0) -> 0.055390152 | E5: =IFERROR('Historical FS '!E7,0) -> 0.11702039 | F5: =IFERROR('Historical FS '!F7,0) -> 0.14357472 | G5: =IFERROR('Historical FS '!G7,0) -> 0.050473671 | H5: =IFERROR('Historical FS '!H7,0) -> 0.074292288 | I5: =IFERROR('Historical FS '!I7,0) -> 0.34028285 | J5: =IFERROR('Historical FS '!J7,0) -> 0.18512278 | K5: =IFERROR('Historical FS '!K7,0) -> 0.029173127 | L5: =IFERROR('Historical FS '!L7,0) -> -0.044770308 | N5: =IFERROR(AVERAGE(D5:L5),0) -> 0.10561774 | O5: =IFERROR(MEDIAN(D5:L5),0) -> 0.074292288
B6: Gross Margin | D6: =IFERROR('Historical FS '!C13,0) -> 0.34037441 | E6: =IFERROR('Historical FS '!D13,0) -> 0.35382642 | F6: =IFERROR('Historical FS '!E13,0) -> 0.33465264 | G6: =IFERROR('Historical FS '!F13,0) -> 0.32922439 | H6: =IFERROR('Historical FS '!G13,0) -> 0.3481274 | I6: =IFERROR('Historical FS '!H13,0) -> 0.35360357 | J6: =IFERROR('Historical FS '!I13,0) -> 0.2924514 | K6: =IFERROR('Historical FS '!J13,0) -> 0.31088224 | L6: =IFERROR('Historical FS '!K13,0) -> 0.35173503 | N6: =IFERROR(AVERAGE(D6:L6),0) -> 0.33498639 | O6: =IFERROR(MEDIAN(D6:L6),0) -> 0.34037441
B7: EBITDA Growth | D7: =IFERROR('Historical FS '!D18/'Historical FS '!C18-1,0) -> 0.098611397 | E7: =IFERROR('Historical FS '!E18/'Historical FS '!D18-1,0) -> 0.070229411 | F7: =IFERROR('Historical FS '!F18/'Historical FS '!E18-1,0) -> 0.17507124 | G7: =IFERROR('Historical FS '!G18/'Historical FS '!F18-1,0) -> 0.10689413 | H7: =IFERROR('Historical FS '!H18/'Historical FS '!G18-1,0) -> 0.16514173 | I7: =IFERROR('Historical FS '!I18/'Historical FS '!H18-1,0) -> -0.010707225 | J7: =IFERROR('Historical FS '!J18/'Historical FS '!I18-1,0) -> 0.30315325 | K7: =IFERROR('Historical FS '!K18/'Historical FS '!J18-1,0) -> 0.21168912 | L7: =IFERROR('Historical FS '!L18/'Historical FS '!K18-1,0) -> -0.20814425 | N7: =IFERROR(AVERAGE(D7:L7),0) -> 0.10132653 | O7: =IFERROR(MEDIAN(D7:L7),0) -> 0.10689413
B8: EBIT Growth | D8: =IFERROR(('Historical FS '!D18-'Historical FS '!D24)/('Historical FS '!C18-'Historical FS '!C24)-1,0) -> 0.085533138 | E8: =IFERROR(('Historical FS '!E18-'Historical FS '!E24)/('Historical FS '!D18-'Historical FS '!D24)-1,0) -> 0.069414096 | F8: =IFERROR(('Historical FS '!F18-'Historical FS '!F24)/('Historical FS '!E18-'Historical FS '!E24)-1,0) -> 0.10524206 | G8: =IFERROR(('Historical FS '!G18-'Historical FS '!G24)/('Historical FS '!F18-'Historical FS '!F24)-1,0) -> 0.077666412 | H8: =IFERROR(('Historical FS '!H18-'Historical FS '!H24)/('Historical FS '!G18-'Historical FS '!G24)-1,0) -> 0.20001831 | I8: =IFERROR(('Historical FS '!I18-'Historical FS '!I24)/('Historical FS '!H18-'Historical FS '!H24)-1,0) -> -0.018964995 | J8: =IFERROR(('Historical FS '!J18-'Historical FS '!J24)/('Historical FS '!I18-'Historical FS '!I24)-1,0) -> 0.35477334 | K8: =IFERROR(('Historical FS '!K18-'Historical FS '!K24)/('Historical FS '!J18-'Historical FS '!J24)-1,0) -> 0.24624293 | L8: =IFERROR(('Historical FS '!L18-'Historical FS '!L24)/('Historical FS '!K18-'Historical FS '!K24)-1,0) -> -0.26026667 | N8: =IFERROR(AVERAGE(D8:L8),0) -> 0.095517624 | O8: =IFERROR(MEDIAN(D8:L8),0) -> 0.085533138
B9: EBI Growth | D9: =IFERROR('Historical FS '!D27/'Historical FS '!C27-1,9) -> 0.092140673 | E9: =IFERROR('Historical FS '!E27/'Historical FS '!D27-1,9) -> 0.068823332 | F9: =IFERROR('Historical FS '!F27/'Historical FS '!E27-1,9) -> 0.082174964 | G9: =IFERROR('Historical FS '!G27/'Historical FS '!F27-1,9) -> 0.0813269 | H9: =IFERROR('Historical FS '!H27/'Historical FS '!G27-1,9) -> 0.21158057 | I9: =IFERROR('Historical FS '!I27/'Historical FS '!H27-1,9) -> -0.020353915 | J9: =IFERROR('Historical FS '!J27/'Historical FS '!I27-1,9) -> 0.35087003 | K9: =IFERROR('Historical FS '!K27/'Historical FS '!J27-1,9) -> 0.24145913 | L9: =IFERROR('Historical FS '!L27/'Historical FS '!K27-1,9) -> -0.27179587 | N9: =IFERROR(AVERAGE(D9:L9),0) -> 0.092913979 | O9: =IFERROR(MEDIAN(D9:L9),0) -> 0.082174964
B10: Net Profit Growth | D10: =IFERROR('Historical FS '!D33/'Historical FS '!C33-1,0) -> 0.078651902 | E10: =IFERROR('Historical FS '!E33/'Historical FS '!D33-1,0) -> 0.049310335 | F10: =IFERROR('Historical FS '!F33/'Historical FS '!E33-1,0) -> 0.098324352 | G10: =IFERROR('Historical FS '!G33/'Historical FS '!F33-1,0) -> 0.25323249 | H10: =IFERROR('Historical FS '!H33/'Historical FS '!G33-1,0) -> 0.18605332 | I10: =IFERROR('Historical FS '!I33/'Historical FS '!H33-1,0) -> -0.029971131 | J10: =IFERROR('Historical FS '!J33/'Historical FS '!I33-1,0) -> 0.34957493 | K10: =IFERROR('Historical FS '!K33/'Historical FS '!J33-1,0) -> 0.25847333 | L10: =IFERROR('Historical FS '!L33/'Historical FS '!K33-1,0) -> -0.29075755 | N10: =IFERROR(AVERAGE(D10:L10),0) -> 0.10587689 | O10: =IFERROR(MEDIAN(D10:L10),0) -> 0.098324352
B11: Dividend Growth | D11: =IFERROR('Historical FS '!D41/'Historical FS '!C41-1,) -> 0.37333889 | E11: =IFERROR('Historical FS '!E41/'Historical FS '!D41-1,) -> -0.15534727 | F11: =IFERROR('Historical FS '!F41/'Historical FS '!E41-1,) -> 0.20690234 | G11: =IFERROR('Historical FS '!G41/'Historical FS '!F41-1,) -> 0.14285714 | H11: =IFERROR('Historical FS '!H41/'Historical FS '!G41-1,) -> 0.48749826 | I11: =IFERROR('Historical FS '!I41/'Historical FS '!H41-1,) -> 0.072831553 | J11: =IFERROR('Historical FS '!J41/'Historical FS '!I41-1,) -> 0.33942522 | K11: =IFERROR('Historical FS '!K41/'Historical FS '!J41-1,) -> 0.29824618 | L11: =IFERROR('Historical FS '!L41/'Historical FS '!K41-1,) -> -0.25525494 | N11: =IFERROR(AVERAGE(D11:L11),0) -> 0.16783304 | O11: =IFERROR(MEDIAN(D11:L11),0) -> 0.20690234
B13: Gross Margin | C13: =IFERROR('Historical FS '!C13,0) -> 0.34037441 | D13: =IFERROR('Historical FS '!D13,0) -> 0.35382642 | E13: =IFERROR('Historical FS '!E13,0) -> 0.33465264 | F13: =IFERROR('Historical FS '!F13,0) -> 0.32922439 | G13: =IFERROR('Historical FS '!G13,0) -> 0.3481274 | H13: =IFERROR('Historical FS '!H13,0) -> 0.35360357 | I13: =IFERROR('Historical FS '!I13,0) -> 0.2924514 | J13: =IFERROR('Historical FS '!J13,0) -> 0.31088224 | ... L13: =IFERROR('Historical FS '!L13,0) -> 0.32927727 | N13: =IFERROR(AVERAGE(C13:L13),0) -> 0.33441548 | O13: =IFERROR(MEDIAN(C13:L13),0) -> 0.33751352
B14: EBITDA Margin | C14: =IFERROR('Historical FS '!C19,0) -> 0.19094292 | D14: =IFERROR('Historical FS '!D19,0) -> 0.19876258 | E14: =IFERROR('Historical FS '!E19,0) -> 0.19043659 | F14: =IFERROR('Historical FS '!F19,0) -> 0.19568163 | G14: =IFERROR('Historical FS '!G19,0) -> 0.2061916 | H14: =IFERROR('Historical FS '!H19,0) -> 0.22362856 | I14: =IFERROR('Historical FS '!I19,0) -> 0.16506525 | J14: =IFERROR('Historical FS '!J19,0) -> 0.18150467 | ... L14: =IFERROR('Historical FS '!L19,0) -> 0.17714497 | N14: =IFERROR(AVERAGE(C14:L14),0) -> 0.19430519 | O14: =IFERROR(MEDIAN(C14:L14),0) -> 0.19331228
B15: EBIT Margin | C15: =IFERROR(('Historical FS '!C18-'Historical FS '!C24)/'Historical FS '!C6,0) -> 0.1716331 | D15: =IFERROR(('Historical FS '!D18-'Historical FS '!D24)/'Historical FS '!D6,0) -> 0.17653511 | E15: =IFERROR(('Historical FS '!E18-'Historical FS '!E24)/'Historical FS '!E6,0) -> 0.16901136 | F15: =IFERROR(('Historical FS '!F18-'Historical FS '!F24)/'Historical FS '!F6,0) -> 0.16334609 | G15: =IFERROR(('Historical FS '!G18-'Historical FS '!G24)/'Historical FS '!G6,0) -> 0.16757449 | H15: =IFERROR(('Historical FS '!H18-'Historical FS '!H24)/'Historical FS '!H6,0) -> 0.18718599 | I15: =IFERROR(('Historical FS '!I18-'Historical FS '!I24)/'Historical FS '!I6,0) -> 0.13701287 | J15: =IFERROR(('Historical FS '!J18-'Historical FS '!J24)/'Historical FS '!J6,0) -> 0.15662629 | ... L15: =IFERROR(('Historical FS '!L18-'Historical FS '!L24)/'Historical FS '!L6,0) -> 0.14687447 | N15: =IFERROR(AVERAGE(C15:L15),0) -> 0.16654612 | O15: =IFERROR(MEDIAN(C15:L15),0) -> 0.16829292
B16: EBT Margin | C16: =IFERROR('Historical FS '!C28,0) -> 0.16819968 | D16: =IFERROR('Historical FS '!D28,0) -> 0.17405668 | E16: =IFERROR('Historical FS '!E28,0) -> 0.1665465 | F16: =IFERROR('Historical FS '!F28,0) -> 0.15760444 | G16: =IFERROR('Historical FS '!G28,0) -> 0.16223341 | H16: =IFERROR('Historical FS '!H28,0) -> 0.18296589 | I16: =IFERROR('Historical FS '!I28,0) -> 0.13373432 | J16: =IFERROR('Historical FS '!J28,0) -> 0.15243795 | ... L16: =IFERROR('Historical FS '!L28,0) -> 0.14017883 | N16: =IFERROR(AVERAGE(C16:L16),0) -> 0.16218388 | O16: =IFERROR(MEDIAN(C16:L16),0) -> 0.16438996
B17: Net Profit Margin | C17: =IFERROR('Historical FS '!C34,0) -> 0.10902646 | D17: =IFERROR('Historical FS '!D34,0) -> 0.1114295 | E17: =IFERROR('Historical FS '!E34,0) -> 0.10467501 | F17: =IFERROR('Historical FS '!F34,0) -> 0.1005331 | G17: =IFERROR('Historical FS '!G34,0) -> 0.11993766 | H17: =IFERROR('Historical FS '!H34,0) -> 0.13241504 | I17: =IFERROR('Historical FS '!I34,0) -> 0.095835303 | J17: =IFERROR('Historical FS '!J34,0) -> 0.10913377 | ... L17: =IFERROR('Historical FS '!L34,0) -> 0.099083574 | N17: =IFERROR(AVERAGE(C17:L17),0) -> 0.11155183 | O17: =IFERROR(MEDIAN(C17:L17),0) -> 0.10908012
B19: Sales Expense % Sales | C19: =IFERROR('Historical FS '!C16,0) -> 0.14943149 | D19: =IFERROR('Historical FS '!D16,0) -> 0.15506384 | E19: =IFERROR('Historical FS '!E16,0) -> 0.14421604 | F19: =IFERROR('Historical FS '!F16,0) -> 0.13354276 | G19: =IFERROR('Historical FS '!G16,0) -> 0.1419358 | H19: =IFERROR('Historical FS '!H16,0) -> 0.12997501 | I19: =IFERROR('Historical FS '!I16,0) -> 0.12738615 | J19: =IFERROR('Historical FS '!J16,0) -> 0.12937757 | ... L19: =IFERROR('Historical FS '!L16,0) -> 0.1521323 | N19: =IFERROR(AVERAGE(C19:L19),0) -> 0.14011029 | O19: =IFERROR(MEDIAN(C19:L19),0) -> 0.13998885
B20: Depreciation % Sales | C20: =IFERROR('Historical FS '!C25,0) -> 0.019309827 | D20: =IFERROR('Historical FS '!D25,0) -> 0.022227475 | E20: =IFERROR('Historical FS '!E25,0) -> 0.021425239 | F20: =IFERROR('Historical FS '!F25,0) -> 0.03233554 | G20: =IFERROR('Historical FS '!G25,0) -> 0.038617107 | H20: =IFERROR('Historical FS '!H25,0) -> 0.036442576 | I20: =IFERROR('Historical FS '!I25,0) -> 0.028052374 | J20: =IFERROR('Historical FS '!J25,0) -> 0.024878373 | ... L20: =IFERROR('Historical FS '!L25,0) -> 0.030270498 | N20: =IFERROR(AVERAGE(C20:L20),0) -> 0.027759074 | O20: =IFERROR(MEDIAN(C20:L20),0) -> 0.026465374
B21: Operating Income % Sales | C21: =C15 -> 0.1716331 | D21: =D15 -> 0.17653511 | E21: =E15 -> 0.16901136 | F21: =F15 -> 0.16334609 | G21: =G15 -> 0.16757449 | H21: =H15 -> 0.18718599 | I21: =I15 -> 0.13701287 | J21: =J15 -> 0.15662629 | ... L21: =L15 -> 0.14687447 | N21: =IFERROR(AVERAGE(C21:L21),0) -> 0.16654612 | O21: =IFERROR(MEDIAN(C21:L21),0) -> 0.16829292
B23: Return On Capital Employed | C23: =IFERROR(('Historical FS '!C18-'Historical FS '!C24)/SUM('Historical FS '!C48:C50),0) -> 0.35768409 | D23: =IFERROR(('Historical FS '!D18-'Historical FS '!D24)/SUM('Historical FS '!D48:D50),0) -> 0.32568534 | E23: =IFERROR(('Historical FS '!E18-'Historical FS '!E24)/SUM('Historical FS '!E48:E50),0) -> 0.31793919 | F23: =IFERROR(('Historical FS '!F18-'Historical FS '!F24)/SUM('Historical FS '!F48:F50),0) -> 0.29126565 | G23: =IFERROR(('Historical FS '!G18-'Historical FS '!G24)/SUM('Historical FS '!G48:G50),0) -> 0.30109275 | H23: =IFERROR(('Historical FS '!H18-'Historical FS '!H24)/SUM('Historical FS '!H48:H50),0) -> 0.29241025 | I23: =IFERROR(('Historical FS '!I18-'Historical FS '!I24)/SUM('Historical FS '!I48:I50),0) -> 0.25893857 | J23: =IFERROR(('Historical FS '!J18-'Historical FS '!J24)/SUM('Historical FS '!J48:J50),0) -> 0.30135929 | ... L23: =IFERROR(('Historical FS '!L18-'Historical FS '!L24)/SUM('Historical FS '!L48:L50),0) -> 0.22959184 | N23: =IFERROR(AVERAGE(C23:L23),0) -> 0.29934731 | O23: =IFERROR(MEDIAN(C23:L23),0) -> 0.30122602
B24: Retained Earning % | C24: =IFERROR('Historical FS '!C44,0) -> 0.53765175 | D24: =IFERROR('Historical FS '!D44,0) -> 0.41133852 | E24: =IFERROR('Historical FS '!E44,0) -> 0.52615112 | F24: =IFERROR('Historical FS '!F44,0) -> 0.47930744 | G24: =IFERROR('Historical FS '!G44,0) -> 0.52516614 | H24: =IFERROR('Historical FS '!H44,0) -> 0.40448332 | I24: =IFERROR('Historical FS '!I44,0) -> 0.34137106 | J24: =IFERROR('Historical FS '!J44,0) -> 0.34632439 | ... L24: =IFERROR('Historical FS '!L44,0) -> 0.29191038 | N24: =IFERROR(AVERAGE(C24:L24),0) -> 0.41893697 | O24: =IFERROR(MEDIAN(C24:L24),0) -> 0.40791092
B25: Return On Equity | C25: =IFERROR('Historical FS '!C33/SUM('Historical FS '!C48:C49),0) -> 0.23846941 | D25: =IFERROR('Historical FS '!D33/SUM('Historical FS '!D48:D49),0) -> 0.22072255 | E25: =IFERROR('Historical FS '!E33/SUM('Historical FS '!E48:E49),0) -> 0.20940093 | F25: =IFERROR('Historical FS '!F33/SUM('Historical FS '!F48:F49),0) -> 0.20424051 | G25: =IFERROR('Historical FS '!G33/SUM('Historical FS '!G48:G49),0) -> 0.23929434 | H25: =IFERROR('Historical FS '!H33/SUM('Historical FS '!H48:H49),0) -> 0.22450686 | I25: =IFERROR('Historical FS '!I33/SUM('Historical FS '!I48:I49),0) -> 0.20192723 | J25: =IFERROR('Historical FS '!J33/SUM('Historical FS '!J48:J49),0) -> 0.23535617 | ... L25: =IFERROR('Historical FS '!L33/SUM('Historical FS '!L48:L49),0) -> 0.17317128 | N25: =IFERROR(AVERAGE(C25:L25),0) -> 0.22000076 | O25: =IFERROR(MEDIAN(C25:L25),0) -> 0.22261471
B26: Self Sustained Growth Rate | C26: =C24*C25 -> 0.1282135 | D26: =D24*D25 -> 0.090791687 | E26: =E24*E25 -> 0.11017654 | F26: =F24*F25 -> 0.097893998 | G26: =G24*G25 -> 0.12566929 | H26: =H24*H25 -> 0.090809282 | I26: =I24*I25 -> 0.068932112 | J26: =J24*J25 -> 0.081509583 | ... L26: =L24*L25 -> 0.050550495 | N26: =IFERROR(AVERAGE(C26:L26),0) -> 0.092691327 | O26: =IFERROR(MEDIAN(C26:L26),0) -> 0.090800484
B27: Interest Coverage Ratio | C27: =('Historical FS '!C18-'Historical FS '!C24)/'Historical FS '!C21 -> 49.98898 | D27: =('Historical FS '!D18-'Historical FS '!D24)/'Historical FS '!D21 -> 71.22877 | E27: =('Historical FS '!E18-'Historical FS '!E24)/'Historical FS '!E21 -> 68.568604 | F27: =('Historical FS '!F18-'Historical FS '!F24)/'Historical FS '!F21 -> 28.449353 | G27: =('Historical FS '!G18-'Historical FS '!G24)/'Historical FS '!G21 -> 31.374618 | H27: =('Historical FS '!H18-'Historical FS '!H24)/'Historical FS '!H21 -> 44.355888 | I27: =('Historical FS '!I18-'Historical FS '!I24)/'Historical FS '!I21 -> 41.790693 | J27: =('Historical FS '!J18-'Historical FS '!J24)/'Historical FS '!J21 -> 37.395777 | ... L27: =('Historical FS '!L18-'Historical FS '!L24)/'Historical FS '!L21 -> 21.935821 | N27: =IFERROR(AVERAGE(C27:L27),0) -> 42.790022 | O27: =IFERROR(MEDIAN(C27:L27),0) -> 39.593235
B29: Debtor Turnover Ratio | C29: =IFERROR('Historical FS '!C6/'Historical FS '!C60,0) -> 12.02478 | D29: =IFERROR('Historical FS '!D6/'Historical FS '!D60,0) -> 10.411994 | E29: =IFERROR('Historical FS '!E6/'Historical FS '!E60,0) -> 9.7216332 | F29: =IFERROR('Historical FS '!F6/'Historical FS '!F60,0) -> 10.087468 | G29: =IFERROR('Historical FS '!G6/'Historical FS '!G60,0) -> 11.258369 | H29: =IFERROR('Historical FS '!H6/'Historical FS '!H60,0) -> 8.344109 | I29: =IFERROR('Historical FS '!I6/'Historical FS '!I60,0) -> 7.5169136 | J29: =IFERROR('Historical FS '!J6/'Historical FS '!J60,0) -> 7.4377909 | ... L29: =IFERROR('Historical FS '!L6/'Historical FS '!L60,0) -> 7.8600767 | N29: =IFERROR(AVERAGE(C29:L29),0) -> 9.1923181 | O29: =IFERROR(MEDIAN(C29:L29),0) -> 9.0328711
B30: Creditor Turnover Ratio | C30: =IFERROR('Historical FS '!C6/'Historical FS '!C51,0) -> 3.8458091 | D30: =IFERROR('Historical FS '!D6/'Historical FS '!D51,0) -> 3.551552 | E30: =IFERROR('Historical FS '!E6/'Historical FS '!E51,0) -> 3.4907009 | F30: =IFERROR('Historical FS '!F6/'Historical FS '!F51,0) -> 3.524679 | G30: =IFERROR('Historical FS '!G6/'Historical FS '!G51,0) -> 4.1337633 | H30: =IFERROR('Historical FS '!H6/'Historical FS '!H51,0) -> 3.3632319 | I30: =IFERROR('Historical FS '!I6/'Historical FS '!I51,0) -> 3.8493808 | J30: =IFERROR('Historical FS '!J6/'Historical FS '!J51,0) -> 4.390945 | ... L30: =IFERROR('Historical FS '!L6/'Historical FS '!L51,0) -> 3.9128717 | N30: =IFERROR(AVERAGE(C30:L30),0) -> 3.8143684 | O30: =IFERROR(MEDIAN(C30:L30),0) -> 3.8475949
B31: Inventory Turnover | C31: =IFERROR('Historical FS '!C6/'Historical FS '!C61,0) -> 7.14203 | D31: =IFERROR('Historical FS '!D6/'Historical FS '!D61,0) -> 5.7336635 | E31: =IFERROR('Historical FS '!E6/'Historical FS '!E61,0) -> 6.3290399 | F31: =IFERROR('Historical FS '!F6/'Historical FS '!F61,0) -> 6.1082493 | G31: =IFERROR('Historical FS '!G6/'Historical FS '!G61,0) -> 5.9623548 | H31: =IFERROR('Historical FS '!H6/'Historical FS '!H61,0) -> 5.715998 | I31: =IFERROR('Historical FS '!I6/'Historical FS '!I61,0) -> 4.7296237 | J31: =IFERROR('Historical FS '!J6/'Historical FS '!J61,0) -> 5.5531459 | ... L31: =IFERROR('Historical FS '!L6/'Historical FS '!L61,0) -> 5.0460273 | N31: =IFERROR(AVERAGE(C31:L31),0) -> 5.8312412 | O31: =IFERROR(MEDIAN(C31:L31),0) -> 5.8480092
B32: Fixed Asset Turnover | C32: =IFERROR('Historical FS '!C6/'Historical FS '!C54,0) -> 4.1774086 | D32: =IFERROR('Historical FS '!D6/'Historical FS '!D54,0) -> 4.5590724 | E32: =IFERROR('Historical FS '!E6/'Historical FS '!E54,0) -> 4.5078961 | F32: =IFERROR('Historical FS '!F6/'Historical FS '!F54,0) -> 2.9615874 | G32: =IFERROR('Historical FS '!G6/'Historical FS '!G54,0) -> 3.2222977 | H32: =IFERROR('Historical FS '!H6/'Historical FS '!H54,0) -> 3.7061903 | I32: =IFERROR('Historical FS '!I6/'Historical FS '!I54,0) -> 5.2728689 | J32: =IFERROR('Historical FS '!J6/'Historical FS '!J54,0) -> 5.9767488 | ... L32: =IFERROR('Historical FS '!L6/'Historical FS '!L54,0) -> 3.6773592 | N32: =IFERROR(AVERAGE(C32:L32),0) -> 4.3028075 | O32: =IFERROR(MEDIAN(C32:L32),0) -> 4.3426524
B33: Capital Turnover Ratio | C33: =IFERROR('Historical FS '!C6/SUM('Historical FS '!C48:C49),0) -> 2.1872619 | D33: =IFERROR('Historical FS '!D6/SUM('Historical FS '!D48:D49),0) -> 1.9808269 | E33: =IFERROR('Historical FS '!E6/SUM('Historical FS '!E48:E49),0) -> 2.0004863 | F33: =IFERROR('Historical FS '!F6/SUM('Historical FS '!F48:F49),0) -> 2.0315747 | G33: =IFERROR('Historical FS '!G6/SUM('Historical FS '!G48:G49),0) -> 1.995156 | H33: =IFERROR('Historical FS '!H6/SUM('Historical FS '!H48:H49),0) -> 1.6954785 | I33: =IFERROR('Historical FS '!I6/SUM('Historical FS '!I48:I49),0) -> 2.1070234 | J33: =IFERROR('Historical FS '!J6/SUM('Historical FS '!J48:J49),0) -> 2.1565842 | ... L33: =IFERROR('Historical FS '!L6/SUM('Historical FS '!L48:L49),0) -> 1.7477295 | N33: =IFERROR(AVERAGE(C33:L33),0) -> 1.9797367 | O33: =IFERROR(MEDIAN(C33:L33),0) -> 1.9978212
B35: Debtors Days | C35: =IFERROR(365/C29,0) -> 30.353985 | D35: =IFERROR(365/D29,0) -> 35.055726 | E35: =IFERROR(365/E29,0) -> 37.545132 | F35: =IFERROR(365/F29,0) -> 36.183511 | G35: =IFERROR(365/G29,0) -> 32.420325 | H35: =IFERROR(365/H29,0) -> 43.743436 | I35: =IFERROR(365/I29,0) -> 48.557163 | J35: =IFERROR(365/J29,0) -> 49.073711 | ... L35: =IFERROR(365/L29,0) -> 46.437206 | N35: =IFERROR(AVERAGE(C35:L35),0) -> 40.964536 | O35: =IFERROR(MEDIAN(C35:L35),0) -> 40.644284
B36: Payable Days | C36: =IFERROR(365/C30,0) -> 94.908506 | D36: =IFERROR(365/D30,0) -> 102.77197 | E36: =IFERROR(365/E30,0) -> 104.56353 | F36: =IFERROR(365/F30,0) -> 103.55553 | G36: =IFERROR(365/G30,0) -> 88.297268 | H36: =IFERROR(365/H30,0) -> 108.52656 | I36: =IFERROR(365/I30,0) -> 94.820446 | J36: =IFERROR(365/J30,0) -> 83.125613 | ... L36: =IFERROR(365/L30,0) -> 93.281873 | N36: =IFERROR(AVERAGE(C36:L36),0) -> 96.329564 | O36: =IFERROR(MEDIAN(C36:L36),0) -> 94.864476
B37: Inventory Days | C37: =IFERROR(365/C31,0) -> 51.105918 | D37: =IFERROR(365/D31,0) -> 63.659125 | E37: =IFERROR(365/E31,0) -> 57.670675 | F37: =IFERROR(365/F31,0) -> 59.755256 | G37: =IFERROR(365/G31,0) -> 61.217423 | H37: =IFERROR(365/H31,0) -> 63.855866 | I37: =IFERROR(365/I31,0) -> 77.173159 | J37: =IFERROR(365/J31,0) -> 65.728509 | ... L37: =IFERROR(365/L31,0) -> 72.334131 | N37: =IFERROR(AVERAGE(C37:L37),0) -> 63.341177 | O37: =IFERROR(MEDIAN(C37:L37),0) -> 62.438274
B38: Cash Conversion Cycle (In days) | C38: =SUM(C35,C37)-C36 -> -13.448603 | D38: =SUM(D35,D37)-D36 -> -4.0571199 | E38: =SUM(E35,E37)-E36 -> -9.347721 | F38: =SUM(F35,F37)-F36 -> -7.6167625 | G38: =SUM(G35,G37)-G36 -> 5.3404812 | H38: =SUM(H35,H37)-H36 -> -0.92725992 | I38: =SUM(I35,I37)-I36 -> 30.909876 | J38: =SUM(J35,J37)-J36 -> 31.676607 | ... L38: =SUM(L35,L37)-L36 -> 25.489463 | N38: =IFERROR(AVERAGE(C38:L38),0) -> 7.9761485 | O38: =IFERROR(MEDIAN(C38:L38),0) -> 2.2066106
B40: CFO/Sales | C40: =IFERROR('Historical FS '!C107/'Historical FS '!C6,0) -> 0.17111037 | D40: =IFERROR('Historical FS '!D107/'Historical FS '!D6,0) -> 0.061412868 | E40: =IFERROR('Historical FS '!E107/'Historical FS '!E6,0) -> 0.12083533 | F40: =IFERROR('Historical FS '!F107/'Historical FS '!F6,0) -> 0.10701591 | G40: =IFERROR('Historical FS '!G107/'Historical FS '!G6,0) -> 0.093710186 | H40: =IFERROR('Historical FS '!H107/'Historical FS '!H6,0) -> 0.16013603 | I40: =IFERROR('Historical FS '!I107/'Historical FS '!I6,0) -> -0.062127851 | J40: =IFERROR('Historical FS '!J107/'Historical FS '!J6,0) -> 0.099221221 | ... L40: =IFERROR('Historical FS '!L107/'Historical FS '!L6,0) -> 0.11369797 | N40: =IFERROR(AVERAGE(C40:L40),0) -> 0.1037263 | O40: =IFERROR(MEDIAN(C40:L40),0) -> 0.11035694
B41: CFO/total Assets | C41: =IFERROR('Historical FS '!C107/'Historical FS '!C65,0) -> 0.23127037 | D41: =IFERROR('Historical FS '!D107/'Historical FS '!D65,0) -> 0.074565565 | E41: =IFERROR('Historical FS '!E107/'Historical FS '!E65,0) -> 0.14770974 | F41: =IFERROR('Historical FS '!F107/'Historical FS '!F65,0) -> 0.12671674 | G41: =IFERROR('Historical FS '!G107/'Historical FS '!G65,0) -> 0.11736296 | H41: =IFERROR('Historical FS '!H107/'Historical FS '!H65,0) -> 0.17081513 | I41: =IFERROR('Historical FS '!I107/'Historical FS '!I65,0) -> -0.07875103 | J41: =IFERROR('Historical FS '!J107/'Historical FS '!J65,0) -> 0.13274201 | ... L41: =IFERROR('Historical FS '!L107/'Historical FS '!L65,0) -> 0.12699615 | N41: =IFERROR(AVERAGE(C41:L41),0) -> 0.1253904 | O41: =IFERROR(MEDIAN(C41:L41),0) -> 0.12986908
B42: CFO/Total Debt | C42: =IFERROR('Historical FS '!C107/'Historical FS '!C50,0) -> 7.5535897 | D42: =IFERROR('Historical FS '!D107/'Historical FS '!D50,0) -> 1.6507835 | E42: =IFERROR('Historical FS '!E107/'Historical FS '!E50,0) -> 3.8111842 | F42: =IFERROR('Historical FS '!F107/'Historical FS '!F50,0) -> 1.5603213 | G42: =IFERROR('Historical FS '!G107/'Historical FS '!G50,0) -> 1.6933393 | H42: =IFERROR('Historical FS '!H107/'Historical FS '!H50,0) -> 3.1808036 | I42: =IFERROR('Historical FS '!I107/'Historical FS '!I50,0) -> -1.1393426 | J42: =IFERROR('Historical FS '!J107/'Historical FS '!J50,0) -> 1.7706533 | ... L42: =IFERROR('Historical FS '!L107/'Historical FS '!L50,0) -> 1.683193 | N42: =IFERROR(AVERAGE(C42:L42),0) -> 2.4235447 | O42: =IFERROR(MEDIAN(C42:L42),0) -> 1.7319963

Sheet Common Size Statement
B2: ="Common Size Income Statement"&" "&"- "&'Data Sheet'!$B$1 -> Common Size Income Statement - ASIAN PAINTS LTD
B4: Particular | C4: ='Data Sheet'!B16 -> 42460 | D4: ='Data Sheet'!C16 -> 42825 | E4: ='Data Sheet'!D16 -> 43190 | F4: ='Data Sheet'!E16 -> 43555 | G4: ='Data Sheet'!F16 -> 43921 | H4: ='Data Sheet'!G16 -> 44286 | I4: ='Data Sheet'!H16 -> 44651 | J4: ='Data Sheet'!I16 -> 45016 | ... L4: ='Data Sheet'!K16 -> 45747
B6: ='Data Sheet'!A17 -> Sales | C6: ='Data Sheet'!B17/'Data Sheet'!B$17 -> 1 | D6: ='Data Sheet'!C17/'Data Sheet'!C$17 -> 1 | E6: ='Data Sheet'!D17/'Data Sheet'!D$17 -> 1 | F6: ='Data Sheet'!E17/'Data Sheet'!E$17 -> 1 | G6: ='Data Sheet'!F17/'Data Sheet'!F$17 -> 1 | H6: ='Data Sheet'!G17/'Data Sheet'!G$17 -> 1 | I6: ='Data Sheet'!H17/'Data Sheet'!H$17 -> 1 | J6: ='Data Sheet'!I17/'Data Sheet'!I$17 -> 1 | ... L6: ='Data Sheet'!K17/'Data Sheet'!K$17 -> 1
B7: ='Data Sheet'!A18 -> Raw Material Cost | C7: ='Data Sheet'!B18/'Data Sheet'!B$17 -> 0.46034647 | D7: ='Data Sheet'!C18/'Data Sheet'!C$17 -> 0.49479518 | E7: ='Data Sheet'!D18/'Data Sheet'!D$17 -> 0.48311366 | F7: ='Data Sheet'!E18/'Data Sheet'!E$17 -> 0.51841646 | G7: ='Data Sheet'!F18/'Data Sheet'!F$17 -> 0.49409067 | H7: ='Data Sheet'!G18/'Data Sheet'!G$17 -> 0.48015709 | I7: ='Data Sheet'!H18/'Data Sheet'!H$17 -> 0.58840195 | J7: ='Data Sheet'!I18/'Data Sheet'!I$17 -> 0.55048728 | ... L7: ='Data Sheet'!K18/'Data Sheet'!K$17 -> 0.51627164
B8: ='Data Sheet'!A19 -> Change in Inventory | C8: ='Data Sheet'!B19/'Data Sheet'!B$17 -> -0.013967007 | D8: ='Data Sheet'!C19/'Data Sheet'!C$17 -> 0.035094964 | E8: ='Data Sheet'!D19/'Data Sheet'!D$17 -> -0.0084477742 | F8: ='Data Sheet'!E19/'Data Sheet'!E$17 -> 0.015242101 | G8: ='Data Sheet'!F19/'Data Sheet'!F$17 -> 0.011832519 | H8: ='Data Sheet'!G19/'Data Sheet'!G$17 -> 0.0042578591 | I8: ='Data Sheet'!H19/'Data Sheet'!H$17 -> 0.045529612 | J8: ='Data Sheet'!I19/'Data Sheet'!I$17 -> 0.0089806513 | ... L8: ='Data Sheet'!K19/'Data Sheet'!K$17 -> 0.0060461953
B9: ='Data Sheet'!A20 -> Power and Fuel | C9: ='Data Sheet'!B20/'Data Sheet'!B$17 -> 0.0080215871 | D9: ='Data Sheet'!C20/'Data Sheet'!C$17 -> 0.0070389105 | E9: ='Data Sheet'!D20/'Data Sheet'!D$17 -> 0.006555896 | F9: ='Data Sheet'!E20/'Data Sheet'!E$17 -> 0.0062177335 | G9: ='Data Sheet'!F20/'Data Sheet'!F$17 -> 0.005686437 | H9: ='Data Sheet'!G20/'Data Sheet'!G$17 -> 0.0039631019 | I9: ='Data Sheet'!H20/'Data Sheet'!H$17 -> 0.0040283451 | J9: ='Data Sheet'!I20/'Data Sheet'!I$17 -> 0.0040097319 | ... L9: ='Data Sheet'!K20/'Data Sheet'!K$17 -> 0.0043821644
B10: ='Data Sheet'!A21 -> Other Mfr. Exp | C10: ='Data Sheet'!B21/'Data Sheet'!B$17 -> 0.10757251 | D10: ='Data Sheet'!C21/'Data Sheet'!C$17 -> 0.11039378 | E10: ='Data Sheet'!D21/'Data Sheet'!D$17 -> 0.10054831 | F10: ='Data Sheet'!E21/'Data Sheet'!E$17 -> 0.096795084 | G10: ='Data Sheet'!F21/'Data Sheet'!F$17 -> 0.096081143 | H10: ='Data Sheet'!G21/'Data Sheet'!G$17 -> 0.09525768 | I10: ='Data Sheet'!H21/'Data Sheet'!H$17 -> 0.098980182 | J10: ='Data Sheet'!I21/'Data Sheet'!I$17 -> 0.084555501 | ... L10: ='Data Sheet'!K21/'Data Sheet'!K$17 -> 0.079261196
B11: ='Data Sheet'!A22 -> Employee Cost | C11: ='Data Sheet'!B22/'Data Sheet'!B$17 -> 0.069718018 | D11: ='Data Sheet'!C22/'Data Sheet'!C$17 -> 0.069040678 | E11: ='Data Sheet'!D22/'Data Sheet'!D$17 -> 0.066681724 | F11: ='Data Sheet'!E22/'Data Sheet'!E$17 -> 0.064588441 | G11: ='Data Sheet'!F22/'Data Sheet'!F$17 -> 0.067846867 | H11: ='Data Sheet'!G22/'Data Sheet'!G$17 -> 0.071276423 | I11: ='Data Sheet'!H22/'Data Sheet'!H$17 -> 0.061667734 | J11: ='Data Sheet'!I22/'Data Sheet'!I$17 -> 0.059045905 | ... L11: ='Data Sheet'!K22/'Data Sheet'!K$17 -> 0.076853926
B12: ='Data Sheet'!A23 -> Selling and admin | C12: ='Data Sheet'!B23/'Data Sheet'!B$17 -> 0.27413396 | D12: ='Data Sheet'!C23/'Data Sheet'!C$17 -> 0.28973861 | E12: ='Data Sheet'!D23/'Data Sheet'!D$17 -> 0.13402558 | F12: ='Data Sheet'!E23/'Data Sheet'!E$17 -> 0.12301736 | G12: ='Data Sheet'!F23/'Data Sheet'!F$17 -> 0.12978663 | H12: ='Data Sheet'!G23/'Data Sheet'!G$17 -> 0.10342706 | I12: ='Data Sheet'!H23/'Data Sheet'!H$17 -> 0.10109452 | J12: ='Data Sheet'!I23/'Data Sheet'!I$17 -> 0.10150719 | ... L12: ='Data Sheet'!K23/'Data Sheet'!K$17 -> 0.11428607
B13: ='Data Sheet'!A24 -> Other Expenses | C13: ='Data Sheet'!B24/'Data Sheet'!B$17 -> -0.12470247 | D13: ='Data Sheet'!C24/'Data Sheet'!C$17 -> -0.13467477 | E13: ='Data Sheet'!D24/'Data Sheet'!D$17 -> 0.010190466 | F13: ='Data Sheet'!E24/'Data Sheet'!E$17 -> 0.010525397 | G13: ='Data Sheet'!F24/'Data Sheet'!F$17 -> 0.012149174 | H13: ='Data Sheet'!G24/'Data Sheet'!G$17 -> 0.026547947 | I13: ='Data Sheet'!H24/'Data Sheet'!H$17 -> 0.026291627 | J13: ='Data Sheet'!I24/'Data Sheet'!I$17 -> 0.027870377 | ... L13: ='Data Sheet'!K24/'Data Sheet'!K$17 -> 0.037846233
B14: ='Data Sheet'!A25 -> Other Income | C14: ='Data Sheet'!B25/'Data Sheet'!B$17 -> 0.014952188 | D14: ='Data Sheet'!C25/'Data Sheet'!C$17 -> 0.022433955 | E14: ='Data Sheet'!D25/'Data Sheet'!D$17 -> 0.019995186 | F14: ='Data Sheet'!E25/'Data Sheet'!E$17 -> 0.014229114 | G14: ='Data Sheet'!F25/'Data Sheet'!F$17 -> 0.017322036 | H14: ='Data Sheet'!G25/'Data Sheet'!G$17 -> 0.015274407 | I14: ='Data Sheet'!H25/'Data Sheet'!H$17 -> 0.01016725 | J14: ='Data Sheet'!I25/'Data Sheet'!I$17 -> 0.012510224 | ... L14: ='Data Sheet'!K25/'Data Sheet'!K$17 -> 0.010329261
B15: ='Data Sheet'!A26 -> Depreciation | C15: ='Data Sheet'!B26/'Data Sheet'!B$17 -> 0.019309827 | D15: ='Data Sheet'!C26/'Data Sheet'!C$17 -> 0.022227475 | E15: ='Data Sheet'!D26/'Data Sheet'!D$17 -> 0.021425239 | F15: ='Data Sheet'!E26/'Data Sheet'!E$17 -> 0.03233554 | G15: ='Data Sheet'!F26/'Data Sheet'!F$17 -> 0.038617107 | H15: ='Data Sheet'!G26/'Data Sheet'!G$17 -> 0.036442576 | I15: ='Data Sheet'!H26/'Data Sheet'!H$17 -> 0.028052374 | J15: ='Data Sheet'!I26/'Data Sheet'!I$17 -> 0.024878373 | ... L15: ='Data Sheet'!K26/'Data Sheet'!K$17 -> 0.030270498
B16: ='Data Sheet'!A27 -> Interest | C16: ='Data Sheet'!B27/'Data Sheet'!B$17 -> 0.0034334187 | D16: ='Data Sheet'!C27/'Data Sheet'!C$17 -> 0.0024784242 | E16: ='Data Sheet'!D27/'Data Sheet'!D$17 -> 0.0024648505 | F16: ='Data Sheet'!E27/'Data Sheet'!E$17 -> 0.0057416452 | G16: ='Data Sheet'!F27/'Data Sheet'!F$17 -> 0.0053410848 | H16: ='Data Sheet'!G27/'Data Sheet'!G$17 -> 0.0042200933 | I16: ='Data Sheet'!H27/'Data Sheet'!H$17 -> 0.0032785499 | J16: ='Data Sheet'!I27/'Data Sheet'!I$17 -> 0.0041883417 | ... L16: ='Data Sheet'!K27/'Data Sheet'!K$17 -> 0.0066956451
B17: ='Data Sheet'!A28 -> Profit before tax | C17: ='Data Sheet'!B28/'Data Sheet'!B$17 -> 0.18315186 | D17: ='Data Sheet'!C28/'Data Sheet'!C$17 -> 0.19649064 | E17: ='Data Sheet'!D28/'Data Sheet'!D$17 -> 0.18654169 | F17: ='Data Sheet'!E28/'Data Sheet'!E$17 -> 0.17183356 | G17: ='Data Sheet'!F28/'Data Sheet'!F$17 -> 0.17955545 | H17: ='Data Sheet'!G28/'Data Sheet'!G$17 -> 0.1982403 | I17: ='Data Sheet'!H28/'Data Sheet'!H$17 -> 0.14390157 | J17: ='Data Sheet'!I28/'Data Sheet'!I$17 -> 0.16494818 | ... L17: ='Data Sheet'!K28/'Data Sheet'!K$17 -> 0.15050809
... B20: ='Data Sheet'!A31 -> Dividend Amount | C20: ='Data Sheet'!B31/'Data Sheet'!B$17 -> 0.050408191 | D20: ='Data Sheet'!C31/'Data Sheet'!C$17 -> 0.065594254 | E20: ='Data Sheet'!D31/'Data Sheet'!D$17 -> 0.049600138 | F20: ='Data Sheet'!E31/'Data Sheet'!E$17 -> 0.05234684 | G20: ='Data Sheet'!F31/'Data Sheet'!F$17 -> 0.056950461 | H20: ='Data Sheet'!G31/'Data Sheet'!G$17 -> 0.078855366 | I20: ='Data Sheet'!H31/'Data Sheet'!H$17 -> 0.063119904 | J20: ='Data Sheet'!I31/'Data Sheet'!I$17 -> 0.071338086 | ... L20: ='Data Sheet'!K31/'Data Sheet'!K$17 -> 0.07016005
B21: ='Data Sheet'!A33 -> EBIDTA | C21: ='Data Sheet'!B33/'Data Sheet'!B$17 -> 0.20419942 | D21: ='Data Sheet'!C33/'Data Sheet'!C$17 -> 0.21609628 | E21: ='Data Sheet'!D33/'Data Sheet'!D$17 -> 0.20694937 | F21: ='Data Sheet'!E33/'Data Sheet'!E$17 -> 0.20720182 | G21: ='Data Sheet'!F33/'Data Sheet'!F$17 -> 0.22009871 | H21: ='Data Sheet'!G33/'Data Sheet'!G$17 -> 0.23579604 | I21: ='Data Sheet'!H33/'Data Sheet'!H$17 -> 0.17336866 | J21: ='Data Sheet'!I33/'Data Sheet'!I$17 -> 0.19143781 | ... L21: ='Data Sheet'!K33/'Data Sheet'!K$17 -> 0.18622134
B23: ="Common Size Balance Sheet"&" "&"- "&'Data Sheet'!$B$1 -> Common Size Balance Sheet - ASIAN PAINTS LTD
B25: Particular | C25: ='Data Sheet'!B56 -> 42460 | D25: ='Data Sheet'!C56 -> 42825 | E25: ='Data Sheet'!D56 -> 43190 | F25: ='Data Sheet'!E56 -> 43555 | G25: ='Data Sheet'!F56 -> 43921 | H25: ='Data Sheet'!G56 -> 44286 | I25: ='Data Sheet'!H56 -> 44651 | J25: ='Data Sheet'!I56 -> 45016 | ... L25: ='Data Sheet'!K56 -> 45747
B27: Total Laibilities | C27: ='Data Sheet'!B61/'Data Sheet'!B$61 -> 1 | D27: ='Data Sheet'!C61/'Data Sheet'!C$61 -> 1 | E27: ='Data Sheet'!D61/'Data Sheet'!D$61 -> 1 | F27: ='Data Sheet'!E61/'Data Sheet'!E$61 -> 1 | G27: ='Data Sheet'!F61/'Data Sheet'!F$61 -> 1 | H27: ='Data Sheet'!G61/'Data Sheet'!G$61 -> 1 | I27: ='Data Sheet'!H61/'Data Sheet'!H$61 -> 1 | J27: ='Data Sheet'!I61/'Data Sheet'!I$61 -> 1 | ... L27: ='Data Sheet'!K61/'Data Sheet'!K$61 -> 1
B28: ='Data Sheet'!A57 -> Equity Share Capital | C28: ='Data Sheet'!B57/'Data Sheet'!B$61 -> 0.0090841678 | D28: ='Data Sheet'!C57/'Data Sheet'!C$61 -> 0.0077322476 | E28: ='Data Sheet'!D57/'Data Sheet'!D$61 -> 0.0069691677 | F28: ='Data Sheet'!E57/'Data Sheet'!E$61 -> 0.0059031906 | G28: ='Data Sheet'!F57/'Data Sheet'!F$61 -> 0.0059437463 | H28: ='Data Sheet'!G57/'Data Sheet'!G$61 -> 0.004712277 | I28: ='Data Sheet'!H57/'Data Sheet'!H$61 -> 0.004177986 | J28: ='Data Sheet'!I57/'Data Sheet'!I$61 -> 0.0037208104 | ... L28: ='Data Sheet'!K57/'Data Sheet'!K$61 -> 0.0031599147
B29: ='Data Sheet'!A58 -> Reserves | C29: ='Data Sheet'!B58/'Data Sheet'!B$61 -> 0.60885328 | D29: ='Data Sheet'!C58/'Data Sheet'!C$61 -> 0.60522813 | E29: ='Data Sheet'!D58/'Data Sheet'!D$61 -> 0.60408487 | F29: ='Data Sheet'!E58/'Data Sheet'!E$61 -> 0.57694149 | G29: ='Data Sheet'!F58/'Data Sheet'!F$61 -> 0.62177833 | H29: ='Data Sheet'!G58/'Data Sheet'!G$61 -> 0.62442435 | I29: ='Data Sheet'!H58/'Data Sheet'!H$61 -> 0.59741193 | J29: ='Data Sheet'!I58/'Data Sheet'!I$61 -> 0.61663007 | ... L29: ='Data Sheet'!K58/'Data Sheet'!K$61 -> 0.6359325
B30: ='Data Sheet'!A59 -> Borrowings | C30: ='Data Sheet'!B59/'Data Sheet'!B$61 -> 0.030617396 | D30: ='Data Sheet'!C59/'Data Sheet'!C$61 -> 0.045169804 | E30: ='Data Sheet'!D59/'Data Sheet'!D$61 -> 0.038756913 | F30: ='Data Sheet'!E59/'Data Sheet'!E$61 -> 0.081211951 | G30: ='Data Sheet'!F59/'Data Sheet'!F$61 -> 0.069308593 | H30: ='Data Sheet'!G59/'Data Sheet'!G$61 -> 0.053701879 | I30: ='Data Sheet'!H59/'Data Sheet'!H$61 -> 0.069119709 | J30: ='Data Sheet'!I59/'Data Sheet'!I$61 -> 0.074967813 | ... L30: ='Data Sheet'!K59/'Data Sheet'!K$61 -> 0.075449552
B31: ='Data Sheet'!A60 -> Other Liabilities | C31: ='Data Sheet'!B60/'Data Sheet'!B$61 -> 0.35144516 | D31: ='Data Sheet'!C60/'Data Sheet'!C$61 -> 0.34186981 | E31: ='Data Sheet'!D60/'Data Sheet'!D$61 -> 0.35018905 | F31: ='Data Sheet'!E60/'Data Sheet'!E$61 -> 0.33594337 | G31: ='Data Sheet'!F60/'Data Sheet'!F$61 -> 0.30296933 | H31: ='Data Sheet'!G60/'Data Sheet'!G$61 -> 0.31716149 | I31: ='Data Sheet'!H60/'Data Sheet'!H$61 -> 0.32929037 | J31: ='Data Sheet'!I60/'Data Sheet'!I$61 -> 0.30468131 | ... L31: ='Data Sheet'!K60/'Data Sheet'!K$61 -> 0.28545803
B33: Total Assets | C33: ='Data Sheet'!B76/'Data Sheet'!B$76 -> 1 | D33: ='Data Sheet'!C76/'Data Sheet'!C$76 -> 1 | E33: ='Data Sheet'!D76/'Data Sheet'!D$76 -> 1 | F33: ='Data Sheet'!E76/'Data Sheet'!E$76 -> 1 | G33: ='Data Sheet'!F76/'Data Sheet'!F$76 -> 1 | H33: ='Data Sheet'!G76/'Data Sheet'!G$76 -> 1 | I33: ='Data Sheet'!H76/'Data Sheet'!H$76 -> 1 | J33: ='Data Sheet'!I76/'Data Sheet'!I$76 -> 1 | ... L33: ='Data Sheet'!K76/'Data Sheet'!K$76 -> 1
B34: ='Data Sheet'!A62 -> Net Block | C34: ='Data Sheet'!B62/'Data Sheet'!B$76 -> 0.32354771 | D34: ='Data Sheet'!C62/'Data Sheet'!C$76 -> 0.26631918 | E34: ='Data Sheet'!D62/'Data Sheet'!D$76 -> 0.27116979 | F34: ='Data Sheet'!E62/'Data Sheet'!E$76 -> 0.39981685 | G34: ='Data Sheet'!F62/'Data Sheet'!F$76 -> 0.38866784 | H34: ='Data Sheet'!G62/'Data Sheet'!G$76 -> 0.28781244 | I34: ='Data Sheet'!H62/'Data Sheet'!H$76 -> 0.24039362 | J34: ='Data Sheet'!I62/'Data Sheet'!I$76 -> 0.22384057 | ... L34: ='Data Sheet'!K62/'Data Sheet'!K$76 -> 0.30373988
B35: ='Data Sheet'!A63 -> Capital Work in Progress | C35: ='Data Sheet'!B63/'Data Sheet'!B$76 -> 0.010094677 | D35: ='Data Sheet'!C63/'Data Sheet'!C$76 -> 0.020760665 | E35: ='Data Sheet'!D63/'Data Sheet'!D$76 -> 0.10208973 | F35: ='Data Sheet'!E63/'Data Sheet'!E$76 -> 0.01290369 | G35: ='Data Sheet'!F63/'Data Sheet'!F$76 -> 0.0086900645 | H35: ='Data Sheet'!G63/'Data Sheet'!G$76 -> 0.0089892873 | I35: ='Data Sheet'!H63/'Data Sheet'!H$76 -> 0.018574005 | J35: ='Data Sheet'!I63/'Data Sheet'!I$76 -> 0.039550679 | ... L35: ='Data Sheet'!K63/'Data Sheet'!K$76 -> 0.041326953
B36: ='Data Sheet'!A64 -> Investments | C36: ='Data Sheet'!B64/'Data Sheet'!B$76 -> 0.25685409 | D36: ='Data Sheet'!C64/'Data Sheet'!C$76 -> 0.21378068 | E36: ='Data Sheet'!D64/'Data Sheet'!D$76 -> 0.15553479 | F36: ='Data Sheet'!E64/'Data Sheet'!E$76 -> 0.15807775 | G36: ='Data Sheet'!F64/'Data Sheet'!F$76 -> 0.12509938 | H36: ='Data Sheet'!G64/'Data Sheet'!G$76 -> 0.23270552 | I36: ='Data Sheet'!H64/'Data Sheet'!H$76 -> 0.14145262 | J36: ='Data Sheet'!I64/'Data Sheet'!I$76 -> 0.165315 | ... L36: ='Data Sheet'!K64/'Data Sheet'!K$76 -> 0.15564853
B37: ='Data Sheet'!A65 -> Other Assets | C37: ='Data Sheet'!B74/'Data Sheet'!B$76 -> 0.067688036 | D37: ='Data Sheet'!C74/'Data Sheet'!C$76 -> 0.10617895 | E37: ='Data Sheet'!D74/'Data Sheet'!D$76 -> 0.1229224 | F37: ='Data Sheet'!E74/'Data Sheet'!E$76 -> 0.09058862 | G37: ='Data Sheet'!F74/'Data Sheet'!F$76 -> 0.10774032 | H37: ='Data Sheet'!G74/'Data Sheet'!G$76 -> 0.12603671 | I37: ='Data Sheet'!H74/'Data Sheet'!H$76 -> 0.12529864 | J37: ='Data Sheet'!I74/'Data Sheet'!I$76 -> 0.11777536 | ... L37: ='Data Sheet'!K74/'Data Sheet'!K$76 -> 0.11006366
B38: ='Data Sheet'!A67 -> Receivables | C38: ='Data Sheet'!B67/'Data Sheet'!B$76 -> 0.11240048 | D38: ='Data Sheet'!C67/'Data Sheet'!C$76 -> 0.11661248 | E38: ='Data Sheet'!D67/'Data Sheet'!D$76 -> 0.12574073 | F38: ='Data Sheet'!E67/'Data Sheet'!E$76 -> 0.11738253 | G38: ='Data Sheet'!F67/'Data Sheet'!F$76 -> 0.111242 | H38: ='Data Sheet'!G67/'Data Sheet'!G$76 -> 0.12783722 | I38: ='Data Sheet'!H67/'Data Sheet'!H$76 -> 0.16862826 | J38: ='Data Sheet'!I67/'Data Sheet'!I$76 -> 0.17987046 | ... L38: ='Data Sheet'!K67/'Data Sheet'!K$76 -> 0.14210557
B39: ='Data Sheet'!A68 -> Inventory | C39: ='Data Sheet'!B68/'Data Sheet'!B$76 -> 0.18924466 | D39: ='Data Sheet'!C68/'Data Sheet'!C$76 -> 0.21176137 | E39: ='Data Sheet'!D68/'Data Sheet'!D$76 -> 0.19314229 | F39: ='Data Sheet'!E68/'Data Sheet'!E$76 -> 0.19385138 | G39: ='Data Sheet'!F68/'Data Sheet'!F$76 -> 0.21005182 | H39: ='Data Sheet'!G68/'Data Sheet'!G$76 -> 0.18661442 | I39: ='Data Sheet'!H68/'Data Sheet'!H$76 -> 0.26800526 | J39: ='Data Sheet'!I68/'Data Sheet'!I$76 -> 0.24091549 | ... L39: ='Data Sheet'!K68/'Data Sheet'!K$76 -> 0.22135446
B40: ='Data Sheet'!A69 -> Cash & Bank | C40: ='Data Sheet'!B69/'Data Sheet'!B$76 -> 0.040174145 | D40: ='Data Sheet'!C69/'Data Sheet'!C$76 -> 0.064586677 | E40: ='Data Sheet'!D69/'Data Sheet'!D$76 -> 0.029400268 | F40: ='Data Sheet'!E69/'Data Sheet'!E$76 -> 0.027379185 | G40: ='Data Sheet'!F69/'Data Sheet'!F$76 -> 0.048508579 | H40: ='Data Sheet'!G69/'Data Sheet'!G$76 -> 0.030004412 | I40: ='Data Sheet'!H69/'Data Sheet'!H$76 -> 0.037647609 | J40: ='Data Sheet'!I69/'Data Sheet'!I$76 -> 0.032732426 | ... L40: ='Data Sheet'!K69/'Data Sheet'!K$76 -> 0.025760947

Sheet Forecasting
T3: SUMMARY OUTPUT
T5: Regression Statistics
B6: ='Data Sheet'!$B$1&" - "&'Data Sheet'!A17&" Forecasting " -> ASIAN PAINTS LTD - Sales Forecasting | G6: ='Data Sheet'!$B$1&" - "&'Historical FS '!B18&" Forecasting " -> ASIAN PAINTS LTD - EBITDA Forecasting | L6: ='Data Sheet'!$B$1&" - "&'Historical FS '!B38&" Forecasting " -> ASIAN PAINTS LTD - Earning per Shares Forecasting | T6: Multiple R | U6: 0.87815403
B7: Year Weight | C7: Year | D7: Sales | E7: Sales Growth | G7: Year Weight | H7: Year | I7: EBITDA | J7: EBITDA Growth | L7: Year Weight | M7: Year | N7: EPS | O7: EPS Growth | T7: R Square | U7: 0.7711545
B8: 1 | C8: ='Data Sheet'!$B$16 -> 42460 | D8: {=TRANSPOSE('Data Sheet'!B17:K17)} -> 14271.49 | G8: 1 | H8: ='Data Sheet'!$B$16 -> 42460 | I8: {=TRANSPOSE('Historical FS '!C18:L18)} -> 2725.04 | L8: 1 | M8: ='Data Sheet'!$B$16 -> 42460 | N8: {=TRANSPOSE('Historical FS '!C38:L38)} -> 16.221539 | T8: Adjusted R Square | U8: 0.74254881
B9: =B8+1 -> 2 | C9: =C8+365 -> 42825 | D9: 15061.99 | E9: =D9/D8-1 -> 0.055390152 | G9: =G8+1 -> 2 | H9: =H8+365 -> 42825 | I9: 2993.76 | J9: =I9/I8-1 -> 0.098611397 | L9: =L8+1 -> 2 | M9: =M8+365 -> 42825 | N9: 17.497394 | O9: =N9/N8-1 -> 0.078651902 | T9: Standard Error | U9: 762.91459
B10: =B9+1 -> 3 | C10: =C9+365 -> 43190 | D10: 16824.55 | E10: =D10/D9-1 -> 0.11702039 | G10: =G9+1 -> 3 | H10: =H9+365 -> 43190 | I10: 3204.01 | J10: =I10/I9-1 -> 0.070229411 | L10: =L9+1 -> 3 | M10: =M9+365 -> 43190 | N10: 18.360196 | O10: =N10/N9-1 -> 0.049310335 | T10: Observations | U10: 10
B11: =B10+1 -> 4 | C11: =C10+365 -> 43555 | D11: 19240.13 | E11: =D11/D10-1 -> 0.14357472 | G11: =G10+1 -> 4 | H11: =H10+365 -> 43555 | I11: 3764.94 | J11: =I11/I10-1 -> 0.17507124 | L11: =L10+1 -> 4 | M11: =M10+365 -> 43555 | N11: 20.16545 | O11: =N11/N10-1 -> 0.098324352
B12: =B11+1 -> 5 | C12: =C11+365 -> 43920 | D12: 20211.25 | E12: =D12/D11-1 -> 0.050473671 | G12: =G11+1 -> 5 | H12: =H11+365 -> 43920 | I12: 4167.39 | J12: =I12/I11-1 -> 0.10689413 | L12: =L11+1 -> 5 | M12: =M11+365 -> 43920 | N12: 25.271997 | O12: =N12/N11-1 -> 0.25323249 | T12: ANOVA
B13: =B12+1 -> 6 | C13: =C12+365 -> 44285 | D13: 21712.79 | E13: =D13/D12-1 -> 0.074292288 | G13: =G12+1 -> 6 | H13: =H12+365 -> 44285 | I13: 4855.6 | J13: =I13/I12-1 -> 0.16514173 | L13: =L12+1 -> 6 | M13: =M12+365 -> 44285 | N13: 29.973937 | O13: =N13/N12-1 -> 0.18605332 | U13: df | V13: SS | W13: MS | X13: F | Y13: Significance F
B14: =B13+1 -> 7 | C14: =C13+365 -> 44650 | D14: 29101.28 | E14: =D14/D13-1 -> 0.34028285 | G14: =G13+1 -> 7 | H14: =H13+365 -> 44650 | I14: 4803.61 | J14: =I14/I13-1 -> -0.010707225 | L14: =L13+1 -> 7 | M14: =M13+365 -> 44650 | N14: 29.075584 | O14: =N14/N13-1 -> -0.029971131 | T14: Regression | U14: 1 | V14: 15690647 | W14: 15690647 | X14: 26.958083 | Y14: 0.00083035856
B15: =B14+1 -> 8 | C15: =C14+365 -> 45015 | D15: 34488.59 | E15: =D15/D14-1 -> 0.18512278 | G15: =G14+1 -> 8 | H15: =H14+365 -> 45015 | I15: 6259.84 | J15: =I15/I14-1 -> 0.30315325 | L15: =L14+1 -> 8 | M15: =M14+365 -> 45015 | N15: 39.239679 | O15: =N15/N14-1 -> 0.34957493 | T15: Residual | U15: 8 | V15: 4656309.4 | W15: 582038.68
B16: =B15+1 -> 9 | C16: =C15+365 -> 45380 | D16: 35494.73 | E16: =D16/D15-1 -> 0.029173127 | G16: =G15+1 -> 9 | H16: =H15+365 -> 45380 | I16: 7584.98 | J16: =I16/I15-1 -> 0.21168912 | L16: =L15+1 -> 9 | M16: =M15+365 -> 45380 | N16: 49.382089 | O16: =N16/N15-1 -> 0.25847333 | T16: Total | U16: 9 | V16: 20346956
B17: =B16+1 -> 10 | C17: =C16+365 -> 45745 | D17: 33905.62 | E17: =D17/D16-1 -> -0.044770308 | G17: =G16+1 -> 10 | H17: =H16+365 -> 45745 | I17: 6006.21 | J17: =I17/I16-1 -> -0.20814425 | L17: =L16+1 -> 10 | M17: =M16+365 -> 45745 | N17: 35.023874 | O17: =N17/N16-1 -> -0.29075755
B18: =B17+1 -> 11 | C18: =C17+365 -> 46110 | D18: =FORECAST(B18,$D$8:$D$17,$B$8:$B$17) -> 38669.293 | E18: =D18/D17-1 -> 0.14049805 | G18: =G17+1 -> 11 | H18: =H17+365 -> 46110 | I18: =FORECAST(G18,$I$8:$I$17,$G$8:$G$17) -> 7328.286 | J18: =I18/I17-1 -> 0.22011818 | L18: =L17+1 -> 11 | M18: =M17+365 -> 46110 | N18: =FORECAST(L18,$N$8:$N$17,$L$8:$L$17) -> 45.629295 | O18: =N18/N17-1 -> 0.30280549 | U18: Coefficients | V18: Standard Error | W18: t Stat | X18: P-value | Y18: Lower 95% | Z18: Upper 95% | AA18: Lower 95.0% | AB18: Upper 95.0%
B19: =B18+1 -> 12 | C19: =C18+365 -> 46475 | D19: =FORECAST(B19,$D$8:$D$17,$B$8:$B$17) -> 41330.757 | E19: =D19/D18-1 -> 0.068826287 | G19: =G18+1 -> 12 | H19: =H18+365 -> 46475 | I19: =FORECAST(G19,$I$8:$I$17,$G$8:$G$17) -> 7817.6947 | J19: =I19/I18-1 -> 0.066783519 | L19: =L18+1 -> 12 | M19: =M18+365 -> 46475 | N19: =FORECAST(L19,$N$8:$N$17,$L$8:$L$17) -> 48.830772 | O19: =N19/N18-1 -> 0.070162745 | T19: Intercept | U19: 1877.1473 | V19: 521.16988 | W19: 3.6017955 | X19: 0.0069641169 | Y19: 675.32742 | Z19: 3078.9672 | AA19: 675.32742 | AB19: 3078.9672
B20: =B19+1 -> 13 | C20: =C19+365 -> 46840 | D20: =FORECAST(B20,$D$8:$D$17,$B$8:$B$17) -> 43992.221 | E20: =D20/D19-1 -> 0.064394269 | G20: =G19+1 -> 13 | H20: =H19+365 -> 46840 | I20: =FORECAST(G20,$I$8:$I$17,$G$8:$G$17) -> 8307.1035 | J20: =I20/I19-1 -> 0.062602691 | L20: =L19+1 -> 13 | M20: =M19+365 -> 46840 | N20: =FORECAST(L20,$N$8:$N$17,$L$8:$L$17) -> 52.032248 | O20: =N20/N19-1 -> 0.065562687 | T20: X Variable 1 | U20: 436.10739 | V20: 83.994132 | W20: 5.1921174 | X20: 0.00083035856 | Y20: 242.41658 | Z20: 629.79821 | AA20: 242.41658 | AB20: 629.79821
B21: =B20+1 -> 14 | C21: =C20+365 -> 47205 | D21: =FORECAST(B21,$D$8:$D$17,$B$8:$B$17) -> 46653.685 | E21: =D21/D20-1 -> 0.060498511 | G21: =G20+1 -> 14 | H21: =H20+365 -> 47205 | I21: =FORECAST(G21,$I$8:$I$17,$G$8:$G$17) -> 8796.5122 | J21: =I21/I20-1 -> 0.058914486 | L21: =L20+1 -> 14 | M21: =M20+365 -> 47205 | N21: =FORECAST(L21,$N$8:$N$17,$L$8:$L$17) -> 55.233725 | O21: =N21/N20-1 -> 0.0615287
B22: =B21+1 -> 15 | C22: =C21+365 -> 47570 | D22: =FORECAST(B22,$D$8:$D$17,$B$8:$B$17) -> 49315.149 | E22: =D22/D21-1 -> 0.057047238 | G22: =G21+1 -> 15 | H22: =H21+365 -> 47570 | I22: =FORECAST(G22,$I$8:$I$17,$G$8:$G$17) -> 9285.9209 | J22: =I22/I21-1 -> 0.055636679 | L22: =L21+1 -> 15 | M22: =M21+365 -> 47570 | N22: =FORECAST(L22,$N$8:$N$17,$L$8:$L$17) -> 58.435202 | O22: =N22/N21-1 -> 0.057962352
B25: ='Data Sheet'!$B$1&" - "&'Data Sheet'!A34&" Forecasting " -> ASIAN PAINTS LTD - EBIT Forecasting | G25: ='Data Sheet'!$B$1&" - "&'Historical FS '!B33&" Forecasting " -> ASIAN PAINTS LTD - Net Profit Forecasting
B26: Year Weight | C26: Year | D26: EBIT | E26: EBIT Growth | G26: Year Weight | H26: Year | I26: Net Profit | J26: EPS Growth
B27: 1 | C27: ='Data Sheet'!$B$16 -> 42460 | D27: {=TRANSPOSE('Data Sheet'!B34:K34)} -> 2638.65 | G27: 1 | H27: ='Data Sheet'!$B$16 -> 42460 | I27: {=TRANSPOSE('Historical FS '!C33:L33)} -> 1555.97
B28: =B27+1 -> 2 | C28: =C27+365 -> 42825 | D28: 2920.05 | E28: =D28/D27-1 -> 0.10664544 | G28: =G27+1 -> 2 | H28: =H27+365 -> 42825 | I28: 1678.35 | J28: =I28/I27-1 -> 0.078651902
B29: =B28+1 -> 3 | C29: =C28+365 -> 43190 | D29: 3121.36 | E29: =D29/D28-1 -> 0.0689406 | G29: =G28+1 -> 3 | H29: =H28+365 -> 43190 | I29: 1761.11 | J29: =I29/I28-1 -> 0.049310335
B30: =B29+1 -> 4 | C30: =C29+365 -> 43555 | D30: 3364.45 | E30: =D30/D29-1 -> 0.077879514 | G30: =G29+1 -> 4 | H30: =H29+365 -> 43555 | I30: 1934.27 | J30: =I30/I29-1 -> 0.098324352
B31: =B30+1 -> 5 | C31: =C30+365 -> 43920 | D31: 3667.97 | E31: =D31/D30-1 -> 0.090213854 | G31: =G30+1 -> 5 | H31: =H30+365 -> 43920 | I31: 2424.09 | J31: =I31/I30-1 -> 0.25323249
B32: =B31+1 -> 6 | C32: =C31+365 -> 44285 | D32: 4328.52 | E32: =D32/D31-1 -> 0.18008599 | G32: =G31+1 -> 6 | H32: =H31+365 -> 44285 | I32: 2875.1 | J32: =I32/I31-1 -> 0.18605332
B33: =B32+1 -> 7 | C33: =C32+365 -> 44650 | D33: 4228.89 | E33: =D33/D32-1 -> -0.023017105 | G33: =G32+1 -> 7 | H33: =H32+365 -> 44650 | I33: 2788.93 | J33: =I33/I32-1 -> -0.029971131
B34: =B33+1 -> 8 | C34: =C33+365 -> 45015 | D34: 5744.4 | E34: =D34/D33-1 -> 0.35837064 | G34: =G33+1 -> 8 | H34: =H33+365 -> 45015 | I34: 3763.87 | J34: =I34/I33-1 -> 0.34957493
B35: =B34+1 -> 9 | C35: =C34+365 -> 45380 | D35: 7455.48 | E35: =D35/D34-1 -> 0.29786923 | G35: =G34+1 -> 9 | H35: =H34+365 -> 45380 | I35: 4736.73 | J35: =I35/I34-1 -> 0.25847333
B36: =B35+1 -> 10 | C36: =C35+365 -> 45745 | D36: 5287.61 | E36: =D36/D35-1 -> -0.29077538 | G36: =G35+1 -> 10 | H36: =H35+365 -> 45745 | I36: 3359.49 | J36: =I36/I35-1 -> -0.29075755
B37: =B36+1 -> 11 | C37: =C36+365 -> 46110 | D37: =FORECAST(B37,$D$27:$D$36,$B$27:$B$36) -> 6674.3287 | E37: =D37/D36-1 -> 0.26225812 | G37: =G36+1 -> 11 | H37: =H36+365 -> 46110 | I37: =FORECAST(G37,$I$27:$I$36,$G$27:$G$36) -> 4376.762 | J37: =I37/I36-1 -> 0.30280549
B38: =B37+1 -> 12 | C38: =C37+365 -> 46475 | D38: =FORECAST(B38,$D$27:$D$36,$B$27:$B$36) -> 7110.4361 | E38: =D38/D37-1 -> 0.065341013 | G38: =G37+1 -> 12 | H38: =H37+365 -> 46475 | I38: =FORECAST(G38,$I$27:$I$36,$G$27:$G$36) -> 4683.8476 | J38: =I38/I37-1 -> 0.070162745
B39: =B38+1 -> 13 | C39: =C38+365 -> 46840 | D39: =FORECAST(B39,$D$27:$D$36,$B$27:$B$36) -> 7546.5435 | E39: =D39/D38-1 -> 0.061333425 | G39: =G38+1 -> 13 | H39: =H38+365 -> 46840 | I39: =FORECAST(G39,$I$27:$I$36,$G$27:$G$36) -> 4990.9333 | J39: =I39/I38-1 -> 0.065562687
B40: =B39+1 -> 14 | C40: =C39+365 -> 47205 | D40: =FORECAST(B40,$D$27:$D$36,$B$27:$B$36) -> 7982.6508 | E40: =D40/D39-1 -> 0.057789026 | G40: =G39+1 -> 14 | H40: =H39+365 -> 47205 | I40: =FORECAST(G40,$I$27:$I$36,$G$27:$G$36) -> 5298.0189 | J40: =I40/I39-1 -> 0.0615287
B41: =B40+1 -> 15 | C41: =C40+365 -> 47570 | D41: =FORECAST(B41,$D$27:$D$36,$B$27:$B$36) -> 8418.7582 | E41: =D41/D40-1 -> 0.054631901 | G41: =G40+1 -> 15 | H41: =H40+365 -> 47570 | I41: =FORECAST(G41,$I$27:$I$36,$G$27:$G$36) -> 5605.1045 | J41: =I41/I40-1 -> 0.057962352

Sheet Beta - Regression
B5: Regression Beta | C5: (5 year Data)
B7: Asian Paints Ltd Monthly Return | F7: NIFTY Returns | I7: Beta Drifting
B9: Date | C9: Closing Price | D9: Return | F9: Closing Price | G9: Return | I9: Levered Raw Beta | J9: =J17 -> 1.2350587 | L9: SUMMARY OUTPUT
B10: 44287 | C10: 2427.77 | F10: 14631.1 | I10: Raw Beta Weight | J10: 0.75
B11: 44317 | C11: 2849.98 | D11: =C11/C10-1 -> 0.17390857 | E11: Asian Paints Ltd Month+L9:V27ly Return | F11: 15582.8 | G11: =F11/F10-1 -> 0.065046374 | L11: Regression Statistics
B12: 44348 | C12: 2864.53 | D12: =C12/C11-1 -> 0.005105299 | F12: 15721.5 | G12: =F12/F11-1 -> 0.0089008394 | I12: Market Beta | J12: 1 | L12: Multiple R | M12: 0.61735541
B13: 44378 | C13: 2845.76 | D13: =C13/C12-1 -> -0.0065525584 | F13: 15763.05 | G13: =F13/F12-1 -> 0.0026428776 | I13: Market Beta Weight | J13: 0.25 | L13: R Square | M13: 0.38112771
B14: 44409 | C14: 3079.41 | D14: =C14/C13-1 -> 0.082104605 | F14: 17132.2 | G14: =F14/F13-1 -> 0.086858191 | L14: Adjusted R Square | M14: 0.3702703
B15: 44440 | C15: 3121.06 | D15: =C15/C14-1 -> 0.013525318 | F15: 17618.15 | G15: =F15/F14-1 -> 0.028364717 | I15: Adjusted Beta | J15: =(J9*J10)*(J12*J13) -> 0.2315735 | L15: Standard Error | M15: 0.059663662
B16: 44470 | C16: 2982.02 | D16: =C16/C15-1 -> -0.044548967 | F16: 17671.65 | G16: =F16/F15-1 -> 0.0030366412 | L16: Observations | M16: 59
B17: 44501 | C17: 3027.48 | D17: =C17/C16-1 -> 0.0152447 | F17: 16983.2 | G17: =F17/F16-1 -> -0.038957879 | I17: Beta1 | J17: =M26 -> 1.2350587
B18: 44531 | C18: 3257.93 | D18: =C18/C17-1 -> 0.076119413 | F18: 17354.05 | G18: =F18/F17-1 -> 0.021836285 | L18: ANOVA
B19: 44562 | C19: 3035.76 | D19: =C19/C18-1 -> -0.068193608 | F19: 17339.85 | G19: =F19/F18-1 -> -0.0008182528 | M19: df | N19: SS | O19: MS | P19: F | Q19: Significance F | V19: Beta1 | W19: =SLOPE(D11:D112,G11:G112) -> 1.2350587
B20: 44593 | C20: 3057.33 | D20: =C20/C19-1 -> 0.0071053048 | F20: 16793.9 | G20: =F20/F19-1 -> -0.031485278 | L20: Regression | M20: 1 | N20: 0.12495803 | O20: 0.12495803 | P20: 35.103008 | Q20: 1.9096094e-07 | V20: Beta2 | W20: =_xlfn.COVARIANCE.S(D11:D112,G11:G112)/_xlfn.VAR.S(G11:G112) -> 1.2350587
B21: 44621 | C21: 2966.13 | D21: =C21/C20-1 -> -0.02982995 | F21: 17464.75 | G21: =F21/F20-1 -> 0.039946052 | L21: Residual | M21: 57 | N21: 0.2029059 | O21: 0.0035597526
B22: 44652 | C22: 3117.57 | D22: =C22/C21-1 -> 0.051056427 | F22: 17102.55 | G22: =F22/F21-1 -> -0.020738917 | L22: Total | M22: 58 | N22: 0.32786392
B23: 44682 | C23: 2753.97 | D23: =C23/C22-1 -> -0.1166293 | F23: 16584.55 | G23: =F23/F22-1 -> -0.030287881
B24: 44713 | C24: 2595.6 | D24: =C24/C23-1 -> -0.057506073 | F24: 15780.25 | G24: =F24/F23-1 -> -0.048496944 | M24: Coefficients | N24: Standard Error | O24: t Stat | P24: P-value | Q24: Lower 95% | R24: Upper 95% | S24: Lower 95.0% | T24: Upper 95.0%
B25: 44743 | C25: 3229.05 | D25: =C25/C24-1 -> 0.24404762 | F25: 17158.25 | G25: =F25/F24-1 -> 0.087324345 | L25: Intercept | M25: -0.0094275643 | N25: 0.0079657151 | O25: -1.1835176 | P25: 0.24151655 | Q25: -0.025378634 | R25: 0.0065235049 | S25: -0.025378634 | T25: 0.0065235049
B26: 44774 | C26: 3285.09 | D26: =C26/C25-1 -> 0.01735495 | F26: 17759.3 | G26: =F26/F25-1 -> 0.035029796 | L26: X Variable 1 | M26: 1.2350587 | N26: 0.20845649 | O26: 5.9247792 | P26: 1.9096094e-07 | Q26: 0.81763175 | R26: 1.6524856 | S26: 0.81763175 | T26: 1.6524856
B27: 44805 | C27: 3237.48 | D27: =C27/C26-1 -> -0.014492754 | F27: 17094.35 | G27: =F27/F26-1 -> -0.037442354
B28: 44835 | C28: 3010.1 | D28: =C28/C27-1 -> -0.070233639 | F28: 18012.2 | G28: =F28/F27-1 -> 0.053693179
B29: 44866 | C29: 3079.87 | D29: =C29/C28-1 -> 0.023178632 | F29: 18758.35 | G29: =F29/F28-1 -> 0.041424701
B30: 44896 | C30: 2995.24 | D30: =C30/C29-1 -> -0.027478433 | F30: 18105.3 | G30: =F30/F29-1 -> -0.03481383
B31: 44927 | C31: 2644.06 | D31: =C31/C30-1 -> -0.11724603 | F31: 17662.15 | G31: =F31/F30-1 -> -0.024476258
B32: 44958 | C32: 2743.92 | D32: =C32/C31-1 -> 0.037767675 | F32: 17303.95 | G32: =F32/F31-1 -> -0.020280657
B33: 44986 | C33: 2678.78 | D33: =C33/C32-1 -> -0.023739759 | F33: 17359.75 | G33: =F33/F32-1 -> 0.0032246973
B34: 45017 | C34: 2815.26 | D34: =C34/C33-1 -> 0.050948566 | F34: 18065 | G34: =F34/F33-1 -> 0.040625585
B35: 45047 | C35: 3097.14 | D35: =C35/C34-1 -> 0.10012574 | F35: 18534.4 | G35: =F35/F34-1 -> 0.025983947
B36: 45078 | C36: 3261.17 | D36: =C36/C35-1 -> 0.052961765 | F36: 19189.05 | G36: =F36/F35-1 -> 0.035320809
B37: 45108 | C37: 3297.82 | D37: =C37/C36-1 -> 0.011238298 | F37: 19753.8 | G37: =F37/F36-1 -> 0.029430847
B38: 45139 | C38: 3179.43 | D38: =C38/C37-1 -> -0.035899473 | F38: 19253.8 | G38: =F38/F37-1 -> -0.025311586
... B69: 46082 | C69: 2195.4 | D69: =C69/C68-1 -> -0.076087871 | F69: 23114.5 | G69: =F69/F68-1 -> -0.08198017

Sheet Beta - Comps
B5: Regression Beta of Comps (5 year Data)
B7: Berger Paints India Ltd Monthly Return | F7: Kansai Nerolac PaintsLtd Monthly Return | I7: Indigo Paints Ltd Monthly Return | L7: NIFTY Returns
B9: Date | C9: Closing Price | D9: Return | F9: Closing Price | G9: Return | I9: Closing Price | J9: Return | L9: Closing Price | M9: Return
B10: 44287 | C10: 570.09 | F10: 530.67 | I10: 2293.66 | L10: 14631.1
B11: 44317 | C11: 652.62 | D11: =C11/C10-1 -> 0.14476662 | F11: 545.79 | G11: =F11/F10-1 -> 0.028492283 | I11: 2497.56 | J11: =I11/I10-1 -> 0.088897221 | L11: 15582.8 | M11: =L11/L10-1 -> 0.065046374
B12: 44348 | C12: 651.93 | D12: =C12/C11-1 -> -0.0010572768 | F12: 537.25 | G12: =F12/F11-1 -> -0.015647044 | I12: 2488.85 | J12: =I12/I11-1 -> -0.0034874037 | L12: 15721.5 | M12: =L12/L11-1 -> 0.0089008394
B13: 44378 | C13: 683.21 | D13: =C13/C12-1 -> 0.047980611 | F13: 601.37 | G13: =F13/F12-1 -> 0.11934853 | I13: 2580.52 | J13: =I13/I12-1 -> 0.036832272 | L13: 15763.05 | M13: =L13/L12-1 -> 0.0026428776
B14: 44409 | C14: 664.45 | D14: =C14/C13-1 -> -0.027458614 | F14: 595.56 | G14: =F14/F13-1 -> -0.0096612734 | I14: 2561.55 | J14: =I14/I13-1 -> -0.0073512315 | L14: 17132.2 | M14: =L14/L13-1 -> 0.086858191
B15: 44440 | C15: 658.37 | D15: =C15/C14-1 -> -0.0091504252 | F15: 608.43 | G15: =F15/F14-1 -> 0.021609913 | I15: 2536.1 | J15: =I15/I14-1 -> -0.0099353907 | L15: 17618.15 | M15: =L15/L14-1 -> 0.028364717
B16: 44470 | C16: 603 | D16: =C16/C15-1 -> -0.084101645 | F16: 523.76 | G16: =F16/F15-1 -> -0.13916145 | I16: 2367.8 | J16: =I16/I15-1 -> -0.066361737 | L16: 17671.65 | M16: =L16/L15-1 -> 0.0030366412
B17: 44501 | C17: 613.66 | D17: =C17/C16-1 -> 0.017678275 | F17: 567.99 | G17: =F17/F16-1 -> 0.084447075 | I17: 2201.43 | J17: =I17/I16-1 -> -0.070263536 | L17: 16983.2 | M17: =L17/L16-1 -> -0.038957879
B18: 44531 | C18: 627.78 | D18: =C18/C17-1 -> 0.023009484 | F18: 568.46 | G18: =F18/F17-1 -> 0.00082747936 | I18: 2110.65 | J18: =I18/I17-1 -> -0.041236832 | L18: 17354.05 | M18: =L18/L17-1 -> 0.021836285
B19: 44562 | C19: 587.75 | D19: =C19/C18-1 -> -0.063764376 | F19: 546.61 | G19: =F19/F18-1 -> -0.038437181 | I19: 2003.52 | J19: =I19/I18-1 -> -0.050756876 | L19: 17339.85 | M19: =L19/L18-1 -> -0.0008182528
B20: 44593 | C20: 561.87 | D20: =C20/C19-1 -> -0.044032327 | F20: 437.74 | G20: =F20/F19-1 -> -0.19917309 | I20: 1773.76 | J20: =I20/I19-1 -> -0.11467817 | L20: 16793.9 | M20: =L20/L19-1 -> -0.031485278
B21: 44621 | C21: 569.4 | D21: =C21/C20-1 -> 0.013401677 | F21: 449.72 | G21: =F21/F20-1 -> 0.027367844 | I21: 1590.7 | J21: =I21/I20-1 -> -0.10320449 | L21: 17464.75 | M21: =L21/L20-1 -> 0.039946052
B22: 44652 | C22: 584.78 | D22: =C22/C21-1 -> 0.027010889 | F22: 452.13 | G22: =F22/F21-1 -> 0.00535889 | I22: 1541.32 | J22: =I22/I21-1 -> -0.031042937 | L22: 17102.55 | M22: =L22/L21-1 -> -0.020738917
... B69: 46108 | C69: 414.95 | D69: =C69/C68-1 -> -0.1357009 | F69: 170.05 | G69: =F69/F68-1 -> -0.23469847 | I69: 730.8 | J69: =I69/I68-1 -> -0.21989752 | L69: 23114.5 | M69: =L69/L68-1 -> -0.08198017
B72: Beta1 | C72: =SLOPE(D11:D69,M11:M69) -> 1.1107726 | F72: Beta1 | G72: =SLOPE(G11:G69,M11:M69) -> 0.92242955 | I72: Beta1 | J72: =SLOPE(J11:J69,M11:M69) -> 1.0513967
B73: Beta2 | C73: =_xlfn.COVARIANCE.S(D11:D69,M11:M69)/_xlfn.VAR.S(M11:M69) -> 1.1107726 | F73: Beta2 | G73: =_xlfn.COVARIANCE.S(G11:G69,M11:M69)/_xlfn.VAR.S(M11:M69) -> 0.92242955 | I73: Beta2 | J73: =_xlfn.COVARIANCE.S(J11:J69,M11:M69)/_xlfn.VAR.S(M11:M69) -> 1.0513967
B74: Beta3 | C74: =C95 -> 1.1107726 | F74: Beta3 | G74: =C117 -> 0.92242955 | I74: Beta3 | J74: =C161 -> 1.0513967
A77: Berger Paints India Ltd Monthly Return
B78: SUMMARY OUTPUT
B80: Regression Statistics
B81: Multiple R | C81: 0.59061233
B82: R Square | C82: 0.34882292
B83: Adjusted R Square | C83: 0.33739876
B84: Standard Error | C84: 0.057534623
B85: Observations | C85: 59
B87: ANOVA
C88: df | D88: SS | E88: MS | F88: F | G88: Significance F
B89: Regression | C89: 1 | D89: 0.10107396 | E89: 0.10107396 | F89: 30.533793 | G89: 8.4800053e-07
B90: Residual | C90: 57 | D90: 0.18868327 | E90: 0.0033102328
B91: Total | C91: 58 | D91: 0.28975723
C93: Coefficients | D93: Standard Error | E93: t Stat | F93: P-value | G93: Lower 95% | H93: Upper 95%
B94: Intercept | C94: -0.012277637 | D94: 0.0076814663 | E94: -1.5983455 | F94: 0.11549538 | G94: -0.027659508 | H94: 0.0031042341
B95: X Variable 1 | C95: 1.1107726 | D95: 0.20101792 | E95: 5.5257392 | F95: 8.4800053e-07 | G95: 0.70824116 | H95: 1.5133041
B98: Kansai Nerolac PaintsLtd Monthly Return
B100: SUMMARY OUTPUT
B102: Regression Statistics
B103: Multiple R | C103: 0.39115846
B104: R Square | C104: 0.15300494
B105: Adjusted R Square | C105: 0.13814538
B106: Standard Error | C106: 0.082276912
B107: Observations | C107: 59
B109: ANOVA
C110: df | D110: SS | E110: MS | F110: F | G110: Significance F
B111: Regression | C111: 1 | D111: 0.06970363 | E111: 0.06970363 | F111: 10.296732 | G111: 0.0021889587
B112: Residual | C112: 57 | D112: 0.38586094 | E112: 0.0067694902
B113: Total | C113: 58 | D113: 0.45556457
C115: Coefficients | D115: Standard Error | E115: t Stat | F115: P-value | G115: Lower 95% | H115: Upper 95%
B116: Intercept | C116: -0.022902738 | D116: 0.010984817 | E116: -2.0849449 | F116: 0.041564494 | G116: -0.044899456 | H116: -0.00090602106
B117: X Variable 1 | C117: 0.92242955 | D117: 0.28746402 | E117: 3.2088522 | F117: 0.0021889587 | G117: 0.34679278 | H117: 1.4980663
B120: Akzo Nobel India Ltd Monthly Return
B122: SUMMARY OUTPUT
B124: Regression Statistics
B125: Multiple R | C125: 0.20416101
B126: R Square | C126: 0.041681716
B127: Adjusted R Square | C127: 0.024869115
B128: Standard Error | C128: 0.069176116
B129: Observations | C129: 59
B131: ANOVA
C132: df | D132: SS | E132: MS | F132: F | G132: Significance F
B133: Regression | C133: 1 | D133: 0.011863778 | E133: 0.011863778 | F133: 2.4791949 | G133: 0.12089595
B134: Residual | C134: 57 | D134: 0.27276409 | E134: 0.004785335
B135: Total | C135: 58 | D135: 0.28462787
C137: Coefficients | D137: Standard Error | E137: t Stat | F137: P-value | G137: Lower 95% | H137: Upper 95%
B138: Intercept | C138: 0.0067899458 | D138: 0.0092357258 | E138: 0.7351827 | F138: 0.46524249 | G138: -0.011704276 | H138: 0.025284168
B139: X Variable 1 | C139: 0.38055464 | D139: 0.24169167 | E139: 1.5745459 | F139: 0.12089595 | G139: -0.10342458 | H139: 0.86453386
B142: Indigo Paints Ltd Monthly Return
B144: SUMMARY OUTPUT
B146: Regression Statistics
B147: Multiple R | C147: 0.39956424
B148: R Square | C148: 0.15965158
B149: Adjusted R Square | C149: 0.14490862
B150: Standard Error | C150: 0.091446428
B151: Observations | C151: 59
B153: ANOVA
C154: df | D154: SS | E154: MS | F154: F | G154: Significance F
B155: Regression | C155: 1 | D155: 0.090557031 | E155: 0.090557031 | F155: 10.829008 | G155: 0.0017176487
B156: Residual | C156: 57 | D156: 0.4766596 | E156: 0.0083624491
B157: Total | C157: 58 | D157: 0.56721663
C159: Coefficients | D159: Standard Error | E159: t Stat | F159: P-value | G159: Lower 95% | H159: Upper 95%
B160: Intercept | C160: -0.023424599 | D160: 0.012209042 | E160: -1.918627 | F160: 0.060044448 | G160: -0.047872784 | H160: 0.0010235871
B161: X Variable 1 | C161: 1.0513967 | D161: 0.31950103 | E161: 3.2907459 | F161: 0.0017176487 | G161: 0.41160691 | H161: 1.6911864

Sheet Market Return
B2: Return on Markets
B4: Year | C4: Annual
B5: 2000 | C5: -0.1465
B6: 2001 | C6: -0.1618 | E6: Average Return | F6: =AVERAGE(C5:C30) -> 0.15149231 | J6: Average formula)
B7: 2002 | C7: 0.0325 | E7: Divedend Yield | F7: 1.28% 1
B8: 2003 | C8: 0.719 | E8: Divedend Yield | F8: {=GEOMEAN(1+C5:C30)-1} -> 0.11650334
B9: 2004 | C9: 0.1068
B10: 2005 | C10: 0.3634 | J10: (Using geomean formuala)
B11: 2006 | C11: 0.3983 | E11: Divedend Yield | F11: =SUM(F6:F7) -> 0.15149231
B12: 2007 | C12: 0.5477
B13: 2008 | C13: -0.5179
B14: 2009 | C14: 0.7576
B15: 2010 | C15: 0.1795
B16: 2011 | C16: -0.2462
B17: 2012 | C17: 0.277
B18: 2013 | C18: 0.0676
B19: 2014 | C19: 0.3139
B20: 2015 | C20: -0.0406
B21: 2016 | C21: 0.0301
B22: 2017 | C22: 0.2865
B23: 2018 | C23: 0.0315
... B30: 2025 | C30: 0.1051

Sheet Intrisic Growth
B2: Asian Paints Limited
B7: Calculation of ROIC | G7: ='Raw FS'!J$2 -> 44256 | H7: ='Raw FS'!K$2 -> 44621 | I7: ='Raw FS'!L$2 -> 44986 | J7: ='Raw FS'!M$2 -> 45352 | K7: ='Raw FS'!N$2 -> 45717
B9: Current Assets
B10: ='Raw FS'!B35 -> Inventories | G10: ='Raw FS'!J35 -> 3799 | H10: ='Raw FS'!K35 -> 6153 | I10: ='Raw FS'!L35 -> 6211 | J10: ='Raw FS'!M35 -> 5923 | K10: ='Raw FS'!N35 -> 6719
B11: ='Raw FS'!B36 -> Trade Reveivable | G11: ='Raw FS'!J36 -> 2602 | H11: ='Raw FS'!K36 -> 3871 | I11: ='Raw FS'!L36 -> 4637 | J11: ='Raw FS'!M36 -> 4889 | K11: ='Raw FS'!N36 -> 4314
B12: ='Raw FS'!B38 -> Loans n Advances | G12: ='Raw FS'!J38 -> 12 | H12: ='Raw FS'!K38 -> 8 | I12: ='Raw FS'!L38 -> 12 | J12: ='Raw FS'!M38 -> 17 | K12: ='Raw FS'!N38 -> 22
B13: ='Raw FS'!B39 -> Other asset items | G13: ='Raw FS'!J39 -> 2554 | H13: ='Raw FS'!K39 -> 2869 | I13: ='Raw FS'!L39 -> 3024 | J13: ='Raw FS'!M39 -> 3555 | K13: ='Raw FS'!N39 -> 3319
B14: Total Current Assets | G14: =SUM(G10:G13) -> 8967 | H14: =SUM(H10:H13) -> 12901 | I14: =SUM(I10:I13) -> 13884 | J14: =SUM(J10:J13) -> 14384 | K14: =SUM(K10:K13) -> 14374
B16: Current Liabilities
B17: ='Raw FS'!B13 -> Trade Payables | G17: ='Raw FS'!J13 -> 3379 | H17: ='Raw FS'!K13 -> 4164 | I17: ='Raw FS'!L13 -> 3635 | J17: ='Raw FS'!M13 -> 3831 | K17: ='Raw FS'!N13 -> 3848
B18: ='Raw FS'!B14 -> Advance from Customers | G18: ='Raw FS'!J14 -> 41 | H18: ='Raw FS'!K14 -> 76 | I18: ='Raw FS'!L14 -> 108 | J18: ='Raw FS'!M14 -> 154 | K18: ='Raw FS'!N14 -> 173
B19: ='Raw FS'!B15 -> Other liability items | G19: ='Raw FS'!J15 -> 2613 | H19: ='Raw FS'!K15 -> 2932 | I19: ='Raw FS'!L15 -> 3657 | J19: ='Raw FS'!M15 -> 4017 | K19: ='Raw FS'!N15 -> 3985
B20: Total Current Liabilities | G20: =SUM(G17:G19) -> 6033 | H20: =SUM(H17:H19) -> 7172 | I20: =SUM(I17:I19) -> 7400 | J20: =SUM(J17:J19) -> 8002 | K20: =SUM(K17:K19) -> 8006
A22: # | B22: Net Working Capital | G22: =G14-G20 -> 2934 | H22: =H14-H20 -> 5729 | I22: =I14-I20 -> 6484 | J22: =J14-J20 -> 6382 | K22: =K14-K20 -> 6368
B24: Non Current Assets
B25: ='Raw FS'!B19 -> Land | G25: ='Raw FS'!J19 -> 644 | H25: ='Raw FS'!K19 -> 644 | I25: ='Raw FS'!L19 -> 804 | J25: ='Raw FS'!M19 -> 1126 | K25: ='Raw FS'!N19 -> 1050
B26: ='Raw FS'!B20 -> Building | G26: ='Raw FS'!J20 -> 2249 | H26: ='Raw FS'!K20 -> 2325 | I26: ='Raw FS'!L20 -> 2883 | J26: ='Raw FS'!M20 -> 3390 | K26: ='Raw FS'!N20 -> 4136
B27: ='Raw FS'!B21 -> Plant Machinery | G27: ='Raw FS'!J21 -> 4340 | H27: ='Raw FS'!K21 -> 4531 | I27: ='Raw FS'!L21 -> 4825 | J27: ='Raw FS'!M21 -> 5422 | K27: ='Raw FS'!N21 -> 7576
B28: ='Raw FS'!B22 -> Equipments | G28: ='Raw FS'!J22 -> 243 | H28: ='Raw FS'!K22 -> 253 | I28: ='Raw FS'!L22 -> 270 | J28: ='Raw FS'!M22 -> 298 | K28: ='Raw FS'!N22 -> 325
B29: ='Raw FS'!B23 -> Furniture n fittings | G29: ='Raw FS'!J23 -> 99 | H29: ='Raw FS'!K23 -> 113 | I29: ='Raw FS'!L23 -> 146 | J29: ='Raw FS'!M23 -> 175 | K29: ='Raw FS'!N23 -> 203
B30: ='Raw FS'!B24 -> Vehicles | G30: ='Raw FS'!J24 -> 38 | H30: ='Raw FS'!K24 -> 32 | I30: ='Raw FS'!L24 -> 36 | J30: ='Raw FS'!M24 -> 40 | K30: ='Raw FS'!N24 -> 39
B31: ='Raw FS'!B25 -> Intangible Assets | G31: ='Raw FS'!J25 -> 476 | H31: ='Raw FS'!K25 -> 345 | I31: ='Raw FS'!L25 -> 422 | J31: ='Raw FS'!M25 -> 850 | K31: ='Raw FS'!N25 -> 827
B32: ='Raw FS'!B26 -> Other fixed assets | G32: ='Raw FS'!J26 -> 302 | H32: ='Raw FS'!K26 -> 294 | I32: ='Raw FS'!L26 -> 289 | J32: ='Raw FS'!M26 -> 321 | K32: ='Raw FS'!N26 -> 328
B34: Gross Block | G34: =SUM(G25:G32) -> 8391 | H34: =SUM(H25:H32) -> 8537 | I34: =SUM(I25:I32) -> 9675 | J34: =SUM(J25:J32) -> 11622 | K34: =SUM(K25:K32) -> 14484
B35: ='Raw FS'!B28 -> Accumulated Depreciation | G35: =-'Raw FS'!J28 -> -2533 | H35: =-'Raw FS'!K28 -> -3019 | I35: =-'Raw FS'!L28 -> -3905 | J35: =-'Raw FS'!M28 -> -4475 | K35: =-'Raw FS'!N28 -> -5264
A36: # | B36: Net Non Current Assets | G36: =SUM(G34:G35) -> 5858 | H36: =SUM(H34:H35) -> 5518 | I36: =SUM(I34:I35) -> 5770 | J36: =SUM(J34:J35) -> 7147 | K36: =SUM(K34:K35) -> 9220
A38: # | B38: Invested Capital | G38: =G36+G22 -> 8792 | H38: =H36+H22 -> 11247 | I38: =I36+I22 -> 12254 | J38: =J36+J22 -> 13529 | K38: =K36+K22 -> 15588
B39: EBIT | G39: ='Historical FS '!H27+'Historical FS '!H21 -> 4064.33 | H39: ='Historical FS '!I27+'Historical FS '!I21 -> 3987.25 | I39: ='Historical FS '!J27+'Historical FS '!J21 -> 5401.82 | J39: ='Historical FS '!K27+'Historical FS '!K21 -> 6731.98 | K39: ='Historical FS '!L27+'Historical FS '!L21 -> 4979.87
A41: # | B41: ROIC | G41: =G39/G38 -> 0.46227593 | H41: =H39/H38 -> 0.35451676 | I41: =I39/I38 -> 0.44082096 | J41: =J39/J38 -> 0.49759627 | K41: =K39/K38 -> 0.31946818
A44: # | B44: Calculation of Reinvestment Rate | G44: =G7 -> 44256 | H44: =H7 -> 44621 | I44: =I7 -> 44986 | J44: =J7 -> 45352 | K44: =K7 -> 45717
B46: Net Capex | G46: =-SUM('Cash Flow Data'!J16:J17) -> 261 | H46: =-SUM('Cash Flow Data'!K16:K17) -> 511 | I46: =-SUM('Cash Flow Data'!L16:L17) -> 1420 | J46: =-SUM('Cash Flow Data'!M16:M17) -> 2491 | K46: =-SUM('Cash Flow Data'!N16:N17) -> 1820
B47: Change in Working capital | H47: =H22-G22 -> 2795 | I47: =I22-H22 -> 755 | J47: =J22-I22 -> -102 | K47: =K22-J22 -> -14
B49: EBIT | G49: =G39 -> 4064.33 | H49: =H39 -> 3987.25 | I49: =I39 -> 5401.82 | J49: =J39 -> 6731.98 | K49: =K39 -> 4979.87
B50: Marginal Tax Rate | G50: 0.25 | H50: 0.25 | I50: 0.25 | J50: 0.25 | K50: 0.25
B51: EBIT(1-TAX) | G51: =G49*(1-G50) -> 3048.2475 | H51: =H49*(1-H50) -> 2990.4375 | I51: =I49*(1-I50) -> 4051.365 | J51: =J49*(1-J50) -> 5048.985 | K51: =K49*(1-K50) -> 3734.9025
B53: Reinvestment | H53: =SUM(H46:H47) -> 3306 | I53: =SUM(I46:I47) -> 2175 | J53: =SUM(J46:J47) -> 2389 | K53: =SUM(K46:K47) -> 1806
B55: Reinvestment Rate | H55: =H53/H51 -> 1.1055239 | I55: =I53/I51 -> 0.5368561 | J55: =J53/J51 -> 0.47316441 | K55: =K53/K51 -> 0.48354676
J57: 4 Year Average | K57: =AVERAGE(H55:K55) -> 0.64977278
J58: 4 Year Median | K58: =MEDIAN(H55:K55) -> 0.51020143
A60: # | B60: Calculation of Growth Rate | G60: =G44 -> 44256 | H60: =H44 -> 44621 | I60: =I44 -> 44986 | J60: =J44 -> 45352 | K60: =K44 -> 45717
B62: Reinvestment Rate | H62: =H55 -> 1.1055239 | I62: =I55 -> 0.5368561 | J62: =J55 -> 0.47316441 | K62: =K55 -> 0.48354676
B63: ROIC | H63: =H41 -> 0.35451676 | I63: =I41 -> 0.44082096 | J63: =J41 -> 0.49759627 | K63: =K41 -> 0.31946818
B65: Intrinsic Growth | H65: =H62*H63 -> 0.39192674 | I65: =I62*I63 -> 0.23665742 | J65: =J62*J63 -> 0.23544485 | K65: =K62*K63 -> 0.1544778
J67: 4 Year Average | K67: =AVERAGE(H65:K65) -> 0.2546267
J68: 4 Year Median | K68: =MEDIAN(H65:K65) -> 0.23605113

Sheet Comparable Valuation
B4: Asian paints
B7: Figures in crores
B8: Comparable Company Valuation
D10: Market Data | K10: Financials | O10: Valuation
B11: Company | C11: Ticker | D11: Share Price | E11: Share Outstanding | F11: Equtiy Value | G11: Net Debt | H11: Enterprise Value | K11: Revenue | L11: EBITDA | M11: Net Income | O11: EV/Revenue | P11: EV/EBITDA | Q11: P/E
B13: =DATA!B4 -> Asian Paints | D13: =DATA!C4 -> 2485.1 | E13: =DATA!D4 -> 95.92 | F13: =D13*E13 -> 238370.79 | G13: =DATA!F4-DATA!H4 -> 2546.42 | H13: =DATA!K4 -> 240917.21 | K13: =DATA!G4 -> 34695.75 | L13: =DATA!L4 -> 7163.7589 | M13: =DATA!I4 -> 3910.03 | O13: =H13/K13 -> 6.9437096 | P13: =H13/L13 -> 33.63 | Q13: =F13/M13 -> 60.963929
B14: =DATA!B5 -> Berger Paints | D14: =DATA!C5 -> 460.4 | E14: =DATA!D5 -> 116.6 | F14: =D14*E14 -> 53682.64 | G14: =DATA!F5-DATA!H5 -> 247.5 | H14: =DATA!K5 -> 53930.14 | K14: =DATA!G5 -> 11716.25 | L14: =DATA!L5 -> 1930.2126 | M14: =DATA!I5 -> 1055.68 | O14: =H14/K14 -> 4.6030206 | P14: =H14/L14 -> 27.94 | Q14: =F14/M14 -> 50.851243
B15: =DATA!B6 -> Kansai Nerolac | D15: =DATA!C6 -> 197.15 | E15: =DATA!D6 -> 80.87 | F15: =D15*E15 -> 15943.521 | G15: =DATA!F6-DATA!H6 -> 9.11 | H15: =DATA!K6 -> 15952.631 | K15: =DATA!G6 -> 7914.85 | L15: =DATA!L6 -> 1076.4258 | M15: =DATA!I6 -> 568.38 | O15: =H15/K15 -> 2.0155316 | P15: =H15/L15 -> 14.82 | Q15: =F15/M15 -> 28.050812
B16: =DATA!B7 -> JSW Dulux | D16: =DATA!C7 -> 2947.8 | E16: =DATA!D7 -> 4.55 | F16: =D16*E16 -> 13412.49 | G16: =DATA!F7-DATA!H7 -> -202.8 | H16: =DATA!K7 -> 13209.69 | K16: =DATA!G7 -> 3759.8 | L16: =DATA!L7 -> 574.08475 | M16: =DATA!I7 -> 1955.3 | O16: =H16/K16 -> 3.5134023 | P16: =H16/L16 -> 23.01 | Q16: =F16/M16 -> 6.8595561
B17: =DATA!B8 -> Indigo Paints | D17: =DATA!C8 -> 860.05 | E17: =DATA!D8 -> 4.77 | F17: =D17*E17 -> 4102.4385 | G17: =DATA!F8-DATA!H8 -> 8.55 | H17: =DATA!K8 -> 4110.9885 | K17: =DATA!G8 -> 1299.42 | L17: =DATA!L8 -> 259.04149 | M17: =DATA!I8 -> 144.95 | O17: =H17/K17 -> 3.1637103 | P17: =H17/L17 -> 15.87 | Q17: =F17/M17 -> 28.302439
B18: =DATA!B9 -> Sirca Paints | D18: =DATA!C9 -> 437.3 | E18: =DATA!D9 -> 5.68 | F18: =D18*E18 -> 2483.864 | G18: =DATA!F9-DATA!H9 -> -7.62 | H18: =DATA!K9 -> 2476.244 | K18: =DATA!G9 -> 459.12 | L18: =DATA!L9 -> 95.570976 | M18: =DATA!I9 -> 61.5 | O18: =H18/K18 -> 5.393457 | P18: =H18/L18 -> 25.91 | Q18: =F18/M18 -> 40.388033
B19: =DATA!B10 -> Shalimar Paints | D19: =DATA!C10 -> 50.1 | E19: =DATA!D10 -> 8.37 | F19: =D19*E19 -> 419.337 | G19: =DATA!F10-DATA!H10 -> 141.53 | H19: =DATA!K10 -> 560.867 | K19: =DATA!G10 -> 597.53 | L19: =DATA!L10 -> -19.41388 | M19: =DATA!I10 -> -67.08 | O19: =H19/K19 -> 0.93864241 | P19: =H19/L19 -> -28.89 | Q19: =F19/M19 -> -6.251297
B20: =DATA!B11 -> Kamdhenu Venture | D20: =DATA!C11 -> 5.62 | E20: =DATA!D11 -> 32.9 | F20: =D20*E20 -> 184.898 | G20: =DATA!F11-DATA!H11 -> 25.47 | H20: =DATA!K11 -> 210.368 | K20: =DATA!G11 -> 253.02 | L20: =DATA!L11 -> 16.244633 | M20: =DATA!I11 -> 4.76 | O20: =H20/K20 -> 0.83142835 | P20: =H20/L20 -> 12.95 | Q20: =F20/M20 -> 38.844118
B21: =DATA!B12 -> Siddhika Coatins | D21: =DATA!C12 -> 221.95 | E21: =DATA!D12 -> 0.62 | F21: =D21*E21 -> 137.609 | G21: =DATA!F12-DATA!H12 -> -5.9 | H21: =DATA!K12 -> 131.709 | K21: =DATA!G12 -> 51.6 | L21: =DATA!L12 -> 11.854995 | M21: =DATA!I12 -> 8.54 | O21: =H21/K21 -> 2.5525 | P21: =H21/L21 -> 11.11 | Q21: =F21/M21 -> 16.113466
B23: High | O23: =MAX(O13:O21) -> 6.9437096 | P23: =MAX(P13:P21) -> 33.63 | Q23: =MAX(Q13:Q21) -> 60.963929
B24: 75th Percentile | O24: =QUARTILE(O13:O21,3) -> 4.6030206 | P24: =QUARTILE(P13:P21,3) -> 25.91 | Q24: =QUARTILE(Q13:Q21,3) -> 40.388033
B25: Average | O25: =AVERAGE(O13:O21) -> 3.328378 | P25: =AVERAGE(P13:P21) -> 15.15 | Q25: =AVERAGE(Q13:Q21) -> 29.346922
B26: Median | O26: =MEDIAN(O13:O21) -> 3.1637103 | P26: =MEDIAN(P13:P21) -> 15.87 | Q26: =MEDIAN(Q13:Q21) -> 28.302439
B27: 25th Percentile | O27: =QUARTILE(O13:O21,1) -> 2.0155316 | P27: =QUARTILE(P13:P21,1) -> 12.95 | Q27: =QUARTILE(Q13:Q21,1) -> 16.113466
B28: Low | O28: =MIN(O13:O21) -> 0.83142835 | P28: =MIN(P13:P21) -> -28.89 | Q28: =MIN(Q13:Q21) -> -6.251297
B30: Asian Paints Comparable Valuation | O30: EV/Revenue | P30: EV/EBITDA | Q30: P/E
B32: Implied Enterprise Value | O32: =O$26*K13 -> 109767.3 | P32: =P$26*L13 -> 113688.85 | Q32: =+Q33+Q34 -> 113209.8
B33: Net Debt | O33: =$G$13 -> 2546.42 | P33: =$G$13 -> 2546.42 | Q33: =$G$13 -> 2546.42
B34: Implied Market Value | O34: =O32-O33 -> 107220.88 | P34: =P32-P33 -> 111142.43 | Q34: =M13*Q26 -> 110663.38
B35: Shares Outstanding | O35: =$E$13 -> 95.92 | P35: =$E$13 -> 95.92 | Q35: =$E$13 -> 95.92
B37: Implied Value per Share | O37: =O34/O35 -> 1117.8157 | P37: =P34/P35 -> 1158.6993 | Q37: =Q34/Q35 -> 1153.705
B39: Source: The Valuation School.in
O40: =IF(O37>$D$13,"Undervalued","Overvalued") -> Overvalued | P40: =IF(P37>$D$13,"Undervalued","Overvalued") -> Overvalued | Q40: =IF(Q37>$D$13,"Undervalued","Overvalued") -> Overvalued

Sheet Football Analysis
L7: Football Field Analysis - Data
N8: OpenLow | O8: Low | P8: OpenHigh | Q8: High
L9: Comps | N9: =O9 -> 1117.8157 | O9: ='Comparable Valuation'!O37 -> 1117.8157 | P9: =Q9 -> 1158.6993 | Q9: ='Comparable Valuation'!P37 -> 1158.6993
L10: DCF Bear | N10: =O10 -> 91221.243 | O10: =DCF!L34 -> 91221.243 | P10: =Q10 -> 106614.99 | Q10: =DCF!L38 -> 106614.99
L11: DCF Base | N11: =O11 -> 96231.041 | O11: =DCF!K34 -> 96231.041 | P11: =Q11 -> 113924.25 | Q11: =DCF!K38 -> 113924.25
L12: DCF Bull | N12: =O12 -> 113212.31 | O12: =DCF!H34 -> 113212.31 | P12: =Q12 -> 140201.34 | Q12: =DCF!H38 -> 140201.34
L13: 52W H/L | N13: =O13 -> 2115 | O13: 2115 | P13: =Q13 -> 2985.7 | Q13: 2985.7

Sheet DCF 1
B2: ="DCF Vatuation - "&'Data Sheet'!B1 -> DCF Vatuation - ASIAN PAINTS LTD
B7: Calculation of PV of FCFF | F7: ='Raw FS'!N2 -> 45717 | G7: =F7+366 -> 46083 | H7: =G7+366 -> 46449 | I7: =H7+366 -> 46815 | J7: =I7+366 -> 47181 | K7: =J7+366 -> 47547 | M7: Sensitivity Analysis
B9: EBIT | F9: ='Data Sheet'!K33-'Data Sheet'!K26 -> 5287.61 | G9: =F9*(1+$E$19) -> 6535.7563 | H9: =G9*(1+$E$19) -> 8078.529 | I9: =H9*(1+$E$19) -> 9985.4749 | J9: =I9*(1+$E$19) -> 12342.558 | K9: =J9*(1+$E$19) -> 15256.032 | M9: =E35 -> 81037.156 | N9: 0.11 | O9: 0.115 | P9: 0.12 | Q9: 0.1252 | R9: 0.1305 | S9: 0.1395 | T9: 0.1415 | U9: 0.145 | V9: 0.15 | W9: 0.1569 | X9: 0.15
B10: Tax Rate | F10: 0.25 | G10: =F10 -> 0.25 | H10: =G10 -> 0.25 | I10: =H10 -> 0.25 | J10: =I10 -> 0.25 | K10: =J10 -> 0.25 | M10: 0.04 | N10: 112025.02 | O10: 105427.7 | P10: 99655.05 | Q10: 94370.225 | R10: 89608.717 | S10: 82685.186 | T10: 81313.364 | U10: 79038.426 | V10: 76039.645 | W10: 72322.592 | X10: 76039.645
B11: EBIT(1-T) | F11: =F9*(1-F10) -> 3965.7075 | G11: =G9*(1-G10) -> 4901.8172 | H11: =H9*(1-H10) -> 6058.8968 | I11: =I9*(1-I10) -> 7489.1062 | J11: =J9*(1-J10) -> 9256.9182 | K11: =K9*(1-K10) -> 11442.024 | M11: 0.045 | N11: 119637.32 | O11: 112025.02 | P11: 105427.7 | Q11: 99439.115 | R11: 94084.944 | S11: 86368.781 | T11: 84849.537 | U11: 82337.086 | V11: 79038.426 | W11: 74970.374 | X11: 79038.426
B12: Less: Reinvestment | F12: ='Intrisic Growth'!K55 -> 0.48354676 | G12: =F12+(($K$12-F12))/4 -> 0.49021043 | H12: =G12+(($K$12-G12))/4 -> 0.49520818 | I12: =H12+(($K$12-H12))/4 -> 0.49895649 | J12: =I12+(($K$12-I12))/4 -> 0.50176772 | K12: ='Intrisic Growth'!K58 -> 0.51020143 | M12: 0.05 | N12: 128518.32 | O12: 119637.32 | P12: 112025.02 | Q12: 105182.06 | R12: 99117.225 | S12: 90463.952 | T12: 88772.176 | U12: 85982.973 | V12: 82337.086 | W12: 77865.844 | X12: 82337.086
B13: Free Cash Flow to Firm | F13: =F11*(1-F12) -> 2048.1025 | G13: =G11*(1-G12) -> 2498.8953 | H13: =H11*(1-H12) -> 3058.4815 | I13: =I11*(1-I12) -> 3752.3681 | J13: =J11*(1-J12) -> 4612.0954 | K13: =K11*(1-K12) -> 5604.2871 | M13: 0.055 | N13: 139014.06 | O13: 128518.32 | P13: 119637.32 | Q13: 111743.09 | R13: 104816.03 | S13: 95043.758 | T13: 93148.3 | U13: 90033.959 | V13: 85982.973 | W13: 81045.462 | X13: 85982.973
B14: Mid Convertion | G14: 0.5 | H14: =G14+1 -> 1.5 | I14: =H14+1 -> 2.5 | J14: =I14+1 -> 3.5 | K14: =J14+1 -> 4.5 | M14: 0.06 | N14: 151608.94 | O14: 139014.06 | P14: 128518.32 | Q14: 119310.41 | R14: 111323.18 | S14: 100199.64 | T14: 98061.372 | U14: 94561.531 | V14: 90033.959 | W14: 84553.214 | X14: 90033.959
B15: Discounting Factor | G15: =1/(1+$E$21)^G14 -> 0.92971482 | H15: =1/(1+$E$21)^H14 -> 0.80361726 | I15: =1/(1+$E$21)^I14 -> 0.69462237 | J15: =1/(1+$E$21)^J14 -> 0.60041048 | K15: =1/(1+$E$21)^K14 -> 0.5189766 | M15: 0.065 | N15: 167002.69 | O15: 151608.94 | P15: 139014.06 | Q15: 128134.76 | R15: 118823.79 | S15: 106047.59 | T15: 103616.68 | U15: 99655.05 | V15: 94561.531 | W15: 88442.658 | X15: 94561.531
M16: 0.07 | N16: 186244.87 | O16: 167002.69 | P16: 151608.94 | Q16: 138557.72 | R16: 127564.16 | S16: 112736.96 | T16: 109948.94 | U16: 105427.7 | V16: 99655.05 | W16: 92779.679 | X16: 99655.05
B17: PV of FCFF | G17: =G13*G15 -> 2323.26 | H17: =H13*H15 -> 2457.8486 | I17: =I13*I15 -> 2606.4788 | J17: =J13*J15 -> 2769.1504 | K17: =K13*K15 -> 2908.4939
B19: Expected Growth | E19: ='Intrisic Growth'!K68 -> 0.23605113
B20: Terminal Growth | E20: 0.055
B21: WACC | E21: ='WACC(Arithmetic)'!J46 -> 0.15691245
B23: Calculation of Terminal Value
B25: FCFF (n+1) | E25: =K13*(1+E19) -> 6927.1854
B26: WACC | E26: =E21 -> 0.15691245
B27: Terminal Growth Rate | E27: =E20 -> 0.055
B29: Terminal Value | E29: =E25/(E26-E27) -> 67971.925
B31: Calculation of Equity Value
B33: PV of FCFF | E33: =SUM(G17:K17) -> 13065.232
B34: Terminal Value | E34: =E29 -> 67971.925
B35: Value of Operating Assets | E35: =SUM(E33:E34) -> 81037.156
B37: Add: Cash | E37: ='Data Sheet'!K69 -> 781.98
B38: Less: Debt | E38: =SUM('Raw FS'!N7:N8) -> 864
B39: Value of Equity | E39: =E35+E37-E38 -> 80955.136
B40: No of Share | E40: ='Data Sheet'!B6 -> 95.961577
B42: Equity Value per Share | E42: =E39/E40 -> 843.62032
B44: Share Price | E44: 2207
B45: Discount/Premium | E45: =E44/E42 -> 2.6161058

Sheet WACC(Arithmetic)
B3: WACC
B7: Wieghhted Average Cost of Capitall
B9: All Figures are in unless stated otherwise
B11: Peers Comps
G12: Debt / | H12: Debt / | I12: Levered | J12: Unleverd
B13: Name OF the Com | C13: Country | D13: Total Debt | E13: Total Equity | F13: Tax Rate 1 | G13: Equity | H13: Capital | I13: Beta 2 | J13: Beta 3
B15: Asian Paints | C15: India | D15: 3557.09 | E15: 203411.79 | F15: 0.3 | G15: =D15/E15 -> 0.017487138 | H15: =D15/(D15+E15) -> 0.017186593 | I15: ='Beta - Regression'!J17 -> 1.2350587 | J15: =I15/(1+(1-F15)*G15) -> 1.2201231
B16: Berger Paints | C16: India | D16: 697.33 | E16: 48348.31 | F16: 0.3 | G16: =D16/E16 -> 0.014423048 | H16: =D16/(D16+E16) -> 0.014217981 | I16: ='Beta - Comps'!C74 -> 1.1107726 | J16: =I16/(1+(1-F16)*G16) -> 1.0996702
B17: Kansai Nerolac | C17: India | D17: 275.42 | E17: 13787.62 | F17: 0.3 | G17: =D17/E17 -> 0.019975891 | H17: =D17/(D17+E17) -> 0.01958467 | I17: ='Beta - Comps'!G74 -> 0.92242955 | J17: =I17/(1+(1-F17)*G17) -> 0.90970898
B18: Indigo Paints | C18: India | D18: 17.2 | E18: 3484.14 | F18: 0.3 | G18: =D18/E18 -> 0.0049366558 | H18: =D18/(D18+E18) -> 0.004912405 | I18: ='Beta - Comps'!J74 -> 1.0513967 | J18: =I18/(1+(1-F18)*G18) -> 1.0477759
E20: Average | F20: =AVERAGE(F15:F18) -> 0.3 | G20: =AVERAGE(G16:G18) -> 0.013111865 | H20: =AVERAGE(H15:H18) -> 0.013975413 | I20: =AVERAGE(I16:I18) -> 1.0281996 | J20: =AVERAGE(J16:J18) -> 1.0190517
E21: Median | F21: =MEDIAN(F15:F18) -> 0.3 | G21: =MEDIAN(G15:G18) -> 0.015955093 | H21: =MEDIAN(H15:H18) -> 0.015702287 | I21: =MEDIAN(I15:I18) -> 1.0810846 | J21: =MEDIAN(J15:J18) -> 1.0737231
B24: Cost of DEBT | G24: Cost of Equity
B26: Pre-Tax Cost of Debt | E26: =227/3557.09 -> 0.063816209 | G26: Risk Free Rate | J26: 0.0684
B27: Tax Rate | E27: =F15 -> 0.3 | G27: Equity Risk Premium | J27: ='Market Return'!F11-'WACC(Arithmetic)'!J26 -> 0.083092308
B28: Post Tax Cost of Debt | E28: =E26*(1-E27) -> 0.044671347 | G28: Levered Beta 4 | J28: =J36 -> 1.0843759
G29: Cost of Equity | J29: =J26+J27*J28 -> 0.1585033
B31: Capital Structure | G31: Levered Beta
D33: Current | E33: Target | G33: Comps Median Unlevered Beta | J33: =J21 -> 1.0737231
B34: Total Debt | C34: =D15 -> 3557.09 | D34: =C34/C36 -> 0.017186593 | E34: =H20 -> 0.013975413 | G34: Target Debt / Equity | J34: =E38 -> 0.014173493
B35: Market Capitalization | C35: =E15 -> 203411.79 | D35: =C35/C36 -> 0.98281341 | E35: =E36-E34 -> 0.98602459 | G35: Tax Rate | J35: =E27 -> 0.3
B36: Total Capital | C36: =SUM(C34:C35) -> 206968.88 | D36: =SUM(D34:D35) -> 1 | E36: =D36 -> 1 | G36: Levered Beta | J36: =J33*(1+(1-J35)*J34) -> 1.0843759
B38: Debt / Equity | D38: =D34/D35 -> 0.017487138 | E38: =E34/E35 -> 0.014173493 | G38: Weight Average Cost of Capital
B40: Notes: | G40: Cost of Equity | J40: =J29 -> 0.1585033
B41: 1. Tax Rate considered as Marginal Tax Rate for the country | G41: Equity Weight | J41: =E35 -> 0.98602459
B42: 2. Levered beta is based on 5 year monthly data
B43: 3. Unlevered Beta = Levered Beta/(1+(1-tax rate)*Debt/Equity) | G43: Cost of Debt | J43: =E28 -> 0.044671347
B44: 4. Levered Beta = Unlevered Beta *(1+(1-Tax Rate)*Debt/Equity) | G44: Debt Weight | J44: =E34 -> 0.013975413
B45: 5. Market return has been calculated using the average
B46: method; therefore, WACC is slightly higher | G46: WACC | J46: =(J40*J41)+(J43*J44) -> 0.15691245

Sheet Data Room>

Sheet Cash Flow Data
B3: Particular | C3: 41699 | D3: 42064 | E3: 42430 | F3: 42795 | G3: 43160 | H3: 43525 | I3: 43891 | J3: 44256 | K3: 44621 | L3: 44986 | M3: 45352 | N3: 45717
B5: Cash From Operating Acticities
B6: Profit from operations | C6: 2051 | D6: 2271 | E6: 2848 | F6: 3056 | G6: 3274 | H6: 3861 | I6: 4380 | J6: 4970 | K6: 4957 | L6: 6460 | M6: 7929 | N6: 6390
B7: Receivables | C7: -254 | D7: -155 | E7: -146 | F7: -475 | G7: -483 | H7: -205 | I7: 160 | J7: -1342 | K7: -1326 | L7: -834 | M7: -362 | N7: 282
B8: Inventory | C8: -231 | D8: -144 | E8: 202 | F8: -629 | G8: -39 | H8: -492 | I8: -251 | J8: -409 | K8: -2354 | L8: -56 | M8: 315 | N8: -805
B9: Payables | C9: 317 | D9: -151 | E9: 142 | F9: 501 | G9: 442 | H9: 287 | I9: -647 | J9: 1544 | K9: 644 | L9: -539 | M9: 269 | N9: -160
B10: Other WC items | C10: 0 | D10: 0 | E10: 0 | F10: 0 | G10: 0 | H10: 0 | I10: 0 | J10: 0 | K10: 242 | L10: 657 | M10: -212 | N10: 114
B11: Working capital changes | C11: -168 | D11: -450 | E11: 198 | F11: -603 | G11: -80 | H11: -410 | I11: -737 | J11: -206 | K11: -2795 | L11: -772 | M11: 10 | N11: -570
B12: Direct taxes | C12: -480 | D12: -633 | E12: -802 | F12: -925 | G12: -1081 | H12: -982 | I12: -1011 | J12: -1080 | K12: -1176 | L12: -1494 | M12: -1835 | N12: -1396
B13: Net Operating Acticities | C13: =SUM(C6:C12) -> 1235 | D13: =SUM(D6:D12) -> 738 | E13: =SUM(E6:E12) -> 2442 | F13: =SUM(F6:F12) -> 925 | G13: =SUM(G6:G12) -> 2033 | H13: =SUM(H6:H12) -> 2059 | I13: =SUM(I6:I12) -> 1894 | J13: =SUM(J6:J12) -> 3477 | ... N13: =SUM(N6:N12) -> 3855
B15: Cash From Investing Activities
B16: Fixed assets purchased | C16: -251 | D16: -454 | E16: -817 | F16: -684 | G16: -1426 | H16: -1151 | I16: -414 | J16: -289 | K16: -551 | L16: -1446 | M16: -2496 | N16: -1830
B17: Fixed assets sold | C17: 16 | D17: 16 | E17: 15 | F17: 17 | G17: 17 | H17: 17 | I17: 37 | J17: 28 | K17: 40 | L17: 26 | M17: 5 | N17: 10
B18: Investments purchased | C18: -872 | D18: -243 | E18: -282 | F18: -153 | G18: -320 | H18: -573 | I18: -25 | J18: -140 | K18: 0 | L18: -146 | M18: -212 | N18: -1
B19: Investments sold | C19: 463 | D19: 278 | E19: 205 | F19: 357 | G19: 362 | H19: 733 | I19: 118 | J19: 272 | K19: 207 | L19: 446 | M19: 240 | N19: 421
B20: Interest received | C20: 14 | D20: 11 | E20: 15 | F20: 32 | G20: 39 | H20: 40 | I20: 65 | J20: 73 | K20: 77 | L20: 87 | M20: 135 | N20: 155
B21: Dividends received | C21: 65 | D21: 71 | E21: 69 | F21: 74 | G21: 38 | H21: 40 | I21: 27 | J21: 8 | K21: 15 | L21: 56 | M21: 129 | N21: 136
B22: Investment in group cos | C22: 0 | D22: 0 | E22: 0 | F22: 0 | G22: 0 | H22: 0 | I22: 0 | J22: 0 | K22: 0 | L22: -180 | M22: 0 | N22: 0
B23: Redemp n Canc of Shares | C23: 0 | D23: 0 | E23: 0 | F23: 0 | G23: 141 | H23: 0 | I23: 17 | J23: 0 | K23: 0 | L23: 0 | M23: 0 | N23: 38
B24: Acquisition of companies | C24: 0 | D24: 0 | E24: 0 | F24: 0 | G24: -525 | H24: 0 | I24: 0 | J24: 0 | K24: 0 | L24: 0 | M24: 0 | N24: 0
B25: Other investing items | C25: -21 | D25: -144 | E25: -70 | F25: -324 | G25: 118 | H25: -24 | I25: -343 | J25: -493 | K25: -105 | L25: -126 | M25: -350 | N25: 130
B26: Net Investing Activities | C26: =SUM(C16:C25) -> -586 | D26: =SUM(D16:D25) -> -465 | E26: =SUM(E16:E25) -> -865 | F26: =SUM(F16:F25) -> -681 | G26: =SUM(G16:G25) -> -1556 | H26: =SUM(H16:H25) -> -918 | I26: =SUM(I16:I25) -> -518 | J26: =SUM(J16:J25) -> -541 | ... N26: =SUM(N16:N25) -> -941
B28: Cash From Financing Activities
B29: Proceeds from shares | C29: 0 | D29: 0 | E29: 0 | F29: 0 | G29: 0 | H29: 0 | I29: 0 | J29: 0 | K29: 0 | L29: 0 | M29: 1 | N29: 0
B30: Proceeds from borrowings | C30: 44 | D30: 239 | E30: 8 | F30: 271 | G30: 10 | H30: 243 | I30: 221 | J30: 155 | K30: 418 | L30: 254 | M30: 101 | N30: 415
B31: Repayment of borrowings | C31: -81 | D31: -86 | E31: -119 | F31: -58 | G31: -54 | H31: -26 | I31: -279 | J31: -14 | K31: -8 | L31: -25 | M31: -98 | N31: -428
B32: Interest paid fin | C32: -42 | D32: -35 | E32: -40 | F32: -36 | G32: -35 | H32: -106 | I32: -101 | J32: -89 | K32: -94 | L32: -142 | M32: -191 | N32: -203
B33: Dividends paid | C33: -547 | D33: -695 | E33: -764 | F33: -947 | G33: -1218 | H33: -1049 | I33: -2121 | J33: -499 | K33: -1763 | L33: -1936 | M33: -2551 | N33: -3140
B34: Financial liabilities | C34: 0 | D34: 0 | E34: 0 | F34: 0 | G34: 0 | H34: -180 | I34: -179 | J34: -203 | K34: -221 | L34: -256 | M34: -286 | N34: -325
B35: Other financing items | C35: 0 | D35: 0 | E35: 66 | F35: 13 | G35: -82 | H35: 0 | I35: -6 | J35: 0 | K35: -140 | L35: -36 | M35: 41 | N35: -72
B36: Net Cash Flow | C36: 190 | D36: 147 | E36: 528 | F36: 90 | G36: -822 | H36: 434 | I36: -351 | J36: 2492 | K36: -1138 | L36: 771 | M36: 573 | N36: -270
B37: Net Financing Activities | C37: =SUM(C29:C35) -> -626 | D37: =SUM(D29:D35) -> -577 | E37: =SUM(E29:E35) -> -849 | F37: =SUM(F29:F35) -> -757 | G37: =SUM(G29:G35) -> -1379 | H37: =SUM(H29:H35) -> -1118 | I37: =SUM(I29:I35) -> -2465 | J37: =SUM(J29:J35) -> -650 | ... N37: =SUM(N29:N35) -> -3753
B39: Net Cash Flow | C39: =SUM(C13,C37,C26) -> 23 | D39: =SUM(D13,D37,D26) -> -304 | E39: =SUM(E13,E37,E26) -> 728 | F39: =SUM(F13,F37,F26) -> -513 | G39: =SUM(G13,G37,G26) -> -902 | H39: =SUM(H13,H37,H26) -> 23 | I39: =SUM(I13,I37,I26) -> -1089 | J39: =SUM(J13,J37,J26) -> 2286 | ... N39: =SUM(N13,N37,N26) -> -839

Sheet Data Sheet
A1: COMPANY NAME | B1: ASIAN PAINTS LTD | E1: =IF(B2<>B3, "A NEW VERSION OF THE WORKSHEET IS AVAILABLE", "")
A2: LATEST VERSION | B2: 2.1 | E2: PLEASE DO NOT MAKE ANY CHANGES TO THIS SHEET
A3: CURRENT VERSION | B3: 2.1
A5: META
A6: Number of shares | B6: =IF(B9>0, B9/B8, 0) -> 95.961577
A7: Face Value | B7: 1
A8: Current Price | B8: 2364.2
A9: Market Capitalization | B9: 226872.36
B14: =B17- SUM(B18:B22) -> 5256.31
A15: PROFIT & LOSS
A16: Report Date | B16: 42460 | C16: 42825 | D16: 43190 | E16: 43555 | F16: 43921 | G16: 44286 | H16: 44651 | I16: 45016 | J16: 45382 | K16: 45747
A17: Sales | B17: 14271.49 | C17: 15061.99 | D17: 16824.55 | E17: 19240.13 | F17: 20211.25 | G17: 21712.79 | H17: 29101.28 | I17: 34488.59 | J17: 35494.73 | K17: 33905.62
A18: Raw Material Cost | B18: 6569.83 | C18: 7452.6 | D18: 8128.17 | E18: 9974.4 | F18: 9986.19 | G18: 10425.55 | H18: 17123.25 | I18: 18985.53 | J18: 17410.84 | K18: 17504.51
A19: Change in Inventory | B19: -199.33 | C19: 528.6 | D19: -142.13 | E19: 293.26 | F19: 239.15 | G19: 92.45 | H19: 1324.97 | I19: 309.73 | J19: -363.8 | K19: 205
A20: Power and Fuel | B20: 114.48 | C20: 106.02 | D20: 110.3 | E20: 119.63 | F20: 114.93 | G20: 86.05 | H20: 117.23 | I20: 138.29 | J20: 133.25 | K20: 148.58
A21: Other Mfr. Exp | B21: 1535.22 | C21: 1662.75 | D21: 1691.68 | E21: 1862.35 | F21: 1941.92 | G21: 2068.31 | H21: 2880.45 | I21: 2916.2 | J21: 2767.18 | K21: 2687.4
A22: Employee Cost | B22: 994.98 | C22: 1039.89 | D22: 1121.89 | E22: 1242.69 | F22: 1371.27 | G22: 1547.61 | H22: 1794.61 | I22: 2036.41 | J22: 2334.92 | K22: 2605.78
A23: Selling and admin | B23: 3912.3 | C23: 4364.04 | D23: 2254.92 | E23: 2366.87 | F23: 2623.15 | G23: 2245.69 | H23: 2941.98 | I23: 3500.84 | J23: 3811.86 | K23: 3874.94
A24: Other Expenses | B24: -1779.69 | C24: -2028.47 | D24: 171.45 | E24: 202.51 | F24: 245.55 | G24: 576.43 | H24: 765.12 | I24: 961.21 | J24: 1087.9 | K24: 1283.2
A25: Other Income | B25: 213.39 | C25: 337.9 | D25: 336.41 | E25: 273.77 | F25: 350.1 | G25: 331.65 | H25: 295.88 | I25: 431.46 | J25: 820.96 | K25: 350.22
A26: Depreciation | B26: 275.58 | C26: 334.79 | D26: 360.47 | E26: 622.14 | F26: 780.5 | G26: 791.27 | H26: 816.36 | I26: 858.02 | J26: 853 | K26: 1026.34
A27: Interest | B27: 49 | C27: 37.33 | D27: 41.47 | E27: 110.47 | F27: 107.95 | G27: 91.63 | H27: 95.41 | I27: 144.45 | J27: 205.17 | K27: 227.02
... A31: Dividend Amount | B31: 719.4 | C31: 987.98 | D31: 834.5 | E31: 1007.16 | F31: 1151.04 | G31: 1712.17 | H31: 1836.87 | I31: 2460.35 | J31: 3194.14 | K31: 2378.82
A33: EBIDTA | B33: =B30+B29+B27+B26 -> 2914.23 | C33: =C30+C29+C27+C26 -> 3254.84 | D33: =D30+D29+D27+D26 -> 3481.83 | E33: =E30+E29+E27+E26 -> 3986.59 | F33: =F30+F29+F27+F26 -> 4448.47 | G33: =G30+G29+G27+G26 -> 5119.79 | H33: =H30+H29+H27+H26 -> 5045.25 | I33: =I30+I29+I27+I26 -> 6602.42 | ... K33: =K30+K29+K27+K26 -> 6313.95
A34: EBIT | B34: =B33-B26 -> 2638.65 | C34: =C33-C26 -> 2920.05 | D34: =D33-D26 -> 3121.36 | E34: =E33-E26 -> 3364.45 | F34: =F33-F26 -> 3667.97 | G34: =G33-G26 -> 4328.52 | H34: =H33-H26 -> 4228.89 | I34: =I33-I26 -> 5744.4 | ... K34: =K33-K26 -> 5287.61
A40: Quarters
A41: Report Date | B41: 45199 | C41: 45291 | D41: 45382 | E41: 45473 | F41: 45565 | G41: 45657 | H41: 45747 | I41: 45838 | J41: 45930 | K41: 46022
A42: Sales | B42: 8478.57 | C42: 9103.09 | D42: 8730.76 | E42: 8969.73 | F42: 8027.54 | G42: 8549.44 | H42: 8358.91 | I42: 8938.55 | J42: 8531.27 | K42: 8867.02
A43: Expenses | B43: 6762.34 | C43: 7047 | D43: 7039.39 | E43: 7275.96 | F43: 6788.03 | G43: 6912.71 | H43: 6922.71 | I43: 7313.58 | J43: 7027.89 | K43: 7086.06
A44: Other Income | B44: 194.33 | C44: 186.46 | D44: 212.43 | E44: 192.93 | F44: 24.53 | G44: 192.82 | H44: -60.06 | I44: 229.11 | J44: 236.94 | K44: 69.14
A45: Depreciation | B45: 208.72 | C45: 220.35 | D45: 225.61 | E45: 227.7 | F45: 241.99 | G45: 255.55 | H45: 301.1 | I45: 300.87 | J45: 304.93 | K45: 313.07
A46: Interest | B46: 50.9 | C46: 54.42 | D46: 54.1 | E46: 55.38 | F46: 63.01 | G46: 55.84 | H46: 52.79 | I46: 44.5 | J46: 43.87 | K46: 47.94
A47: Profit before tax | B47: 1650.94 | C47: 1967.78 | D47: 1624.09 | E47: 1603.62 | F47: 959.04 | G47: 1518.16 | H47: 1022.25 | I47: 1508.71 | J47: 1391.52 | K47: 1489.09
A48: Tax | B48: 418.55 | C48: 492.62 | D48: 348.79 | E48: 416.83 | F48: 265.38 | G48: 389.73 | H48: 321.42 | I48: 391.66 | J48: 373.29 | K48: 415.17
A49: Net profit | B49: 1205.42 | C49: 1447.72 | D49: 1256.72 | E49: 1169.98 | F49: 694.64 | G49: 1110.48 | H49: 692.13 | I49: 1099.77 | J49: 993.59 | K49: 1059.87
A50: Operating Profit | B50: 1716.23 | C50: 2056.09 | D50: 1691.37 | E50: 1693.77 | F50: 1239.51 | G50: 1636.73 | H50: 1436.2 | I50: 1624.97 | J50: 1503.38 | K50: 1780.96
A55: BALANCE SHEET
A56: Report Date | B56: 42460 | C56: 42825 | D56: 43190 | E56: 43555 | F56: 43921 | G56: 44286 | H56: 44651 | I56: 45016 | J56: 45382 | K56: 45747
A57: Equity Share Capital | B57: 95.92 | C57: 95.92 | D57: 95.92 | E57: 95.92 | F57: 95.92 | G57: 95.92 | H57: 95.92 | I57: 95.92 | J57: 95.92 | K57: 95.92
A58: Reserves | B58: 6428.9 | C58: 7507.97 | D58: 8314.31 | E58: 9374.63 | F58: 10034.24 | G58: 12710.37 | H58: 13715.64 | I58: 15896.31 | J58: 18632.38 | K58: 19303.89
A59: Borrowings | B59: 323.29 | C59: 560.34 | D59: 533.43 | E59: 1319.6 | F59: 1118.5 | G59: 1093.12 | H59: 1586.88 | I59: 1932.62 | J59: 2474.38 | K59: 2290.29
A60: Other Liabilities | B60: 3710.92 | C60: 4240.96 | D60: 4819.82 | E60: 5458.69 | F60: 4889.31 | G60: 6455.93 | H60: 7559.99 | I60: 7854.48 | J60: 8698.09 | K60: 8665.15
A61: Total | B61: 10559.03 | C61: 12405.19 | D61: 13763.48 | E61: 16248.84 | F61: 16137.97 | G61: 20355.34 | H61: 22958.43 | I61: 25779.33 | J61: 29900.77 | K61: 30355.25
A62: Net Block | B62: 3416.35 | C62: 3303.74 | D62: 3732.24 | E62: 6496.56 | F62: 6272.31 | G62: 5858.52 | H62: 5519.06 | I62: 5770.46 | J62: 7146.62 | K62: 9220.1
A63: Capital Work in Progress | B63: 106.59 | C63: 257.54 | D63: 1405.11 | E63: 209.67 | F63: 140.24 | G63: 182.98 | H63: 426.43 | I63: 1019.59 | J63: 2698.37 | K63: 1254.49
A64: Investments | B64: 2712.13 | C64: 2651.99 | D64: 2140.7 | E64: 2568.58 | F64: 2018.85 | G64: 4736.8 | H64: 3247.53 | I64: 4261.71 | J64: 4587.92 | K64: 4724.75
A65: Other Assets | B65: 4324 | C65: 6191.92 | D65: 6485.43 | E65: 6974.03 | F65: 7706.57 | G65: 9577.04 | H65: 13765.41 | I65: 14727.57 | J65: 15467.86 | K65: 15155.91
A66: Total | B66: 10559.03 | C66: 12405.19 | D66: 13763.48 | E66: 16248.84 | F66: 16137.97 | G66: 20355.34 | H66: 22958.43 | I66: 25779.33 | J66: 29900.77 | K66: 30355.25
A67: Receivables | B67: 1186.84 | C67: 1446.6 | D67: 1730.63 | E67: 1907.33 | F67: 1795.22 | G67: 2602.17 | H67: 3871.44 | I67: 4636.94 | J67: 4889.05 | K67: 4313.65
... A70: No. of Equity Shares | B70: 959197790 | C70: 959197790 | D70: 959197790 | E70: 959197790 | F70: 959197790 | G70: 959197790 | H70: 959197790 | I70: 959197790 | J70: 959197790 | K70: 959197790
A71: New Bonus Shares
A72: Face value | B72: 1 | C72: 1 | D72: 1 | E72: 1 | F72: 1 | G72: 1 | H72: 1 | I72: 1 | J72: 1 | K72: 1
A74: Other Assets | B74: =B65-SUM(B67:B69) -> 714.72 | C74: =C65-SUM(C67:C69) -> 1317.17 | D74: =D65-SUM(D67:D69) -> 1691.84 | E74: =E65-SUM(E67:E69) -> 1471.96 | F74: =F65-SUM(F67:F69) -> 1738.71 | G74: =G65-SUM(G67:G69) -> 2565.52 | H74: =H65-SUM(H67:H69) -> 2876.66 | I74: =I65-SUM(I67:I69) -> 3036.17 | ... K74: =K65-SUM(K67:K69) -> 3341.01
A76: Total Assets | B76: =B61 -> 10559.03 | C76: =C61 -> 12405.19 | D76: =D61 -> 13763.48 | E76: =E61 -> 16248.84 | F76: =F61 -> 16137.97 | G76: =G61 -> 20355.34 | H76: =H61 -> 22958.43 | I76: =I61 -> 25779.33 | ... K76: =K61 -> 30355.25
A80: CASH FLOW:
A81: Report Date | B81: 42460 | C81: 42825 | D81: 43190 | E81: 43555 | F81: 43921 | G81: 44286 | H81: 44651 | I81: 45016 | J81: 45382 | K81: 45747
A82: Cash from Operating Activity | B82: 2242.95 | C82: 1527.33 | D82: 2113.44 | E82: 2469.54 | F82: 2631.89 | G82: 3683.35 | H82: 986.49 | I82: 4193.43 | J82: 6103.6 | K82: 4423.96
A83: Cash from Investing Activity | B83: -866.21 | C83: -681.11 | D83: -1556.14 | E83: -917.79 | F83: -517.91 | G83: -540.54 | H83: -316.75 | I83: -1282.34 | J83: -2548.48 | K83: -940.91
A84: Cash from Financing Activity | B84: -848.98 | C84: -756.43 | D84: -1379.14 | E84: -1117.46 | F84: -2465.2 | G84: -650.4 | H84: -1807.61 | I84: -2140.05 | J84: -2982.5 | K84: -3752.58
A85: Net Cash Flow | B85: 527.76 | C85: 89.79 | D85: -821.84 | E85: 434.29 | F85: -351.22 | G85: 2492.41 | H85: -1137.87 | I85: 771.04 | J85: 572.62 | K85: -269.53
A90: PRICE: | B90: 868.4 | C90: 1073.5 | D90: 1120.4 | E90: 1492.7 | F90: 1666.5 | G90: 2537.4 | H90: 3079.95 | I90: 2761.65 | J90: 2846.75 | K90: 2340.65
A92: DERIVED:
A93: Adjusted Equity Shares in Cr | B93: 95.92 | C93: 95.92 | D93: 95.92 | E93: 95.92 | F93: 95.92 | G93: 95.92 | H93: 95.92 | I93: 95.92 | J93: 95.92 | K93: 95.92

Sheet Raw FS
B2: Particular | C2: 41699 | D2: 42064 | E2: 42430 | F2: 42795 | G2: 43160 | H2: 43525 | I2: 43891 | J2: 44256 | K2: 44621 | L2: 44986 | M2: 45352 | N2: 45717
B4: Equity Capital | C4: 96 | D4: 96 | E4: 96 | F4: 96 | G4: 96 | H4: 96 | I4: 96 | J4: 96 | K4: 96 | L4: 96 | M4: 96 | N4: 96
B5: Reserves | C5: 3943 | D5: 4646 | E5: 6429 | F5: 7508 | G5: 8314 | H5: 9375 | I5: 10034 | J5: 12710 | K5: 13716 | L5: 15896 | M5: 18632 | N5: 19304
B6: Borrowings -
B7: Long term Borrowings | C7: 41 | D7: 78 | E7: 73 | F7: 41 | G7: 28 | H7: 19 | I7: 19 | J7: 15 | K7: 45 | L7: 76 | M7: 54 | N7: 260
B8: Short term Borrowings | C8: 199 | D8: 332 | E8: 231 | F8: 504 | G8: 492 | H8: 597 | I8: 321 | J8: 326 | K8: 731 | L8: 896 | M8: 1053 | N8: 604
B9: Lease Liabilities | C9: 0 | D9: 0 | E9: 0 | F9: 0 | G9: 0 | H9: 693 | I9: 764 | J9: 745 | K9: 811 | L9: 960 | M9: 1367 | N9: 1427
B10: Other Borrowings | C10: 9 | D10: 8 | E10: 20 | F10: 15 | G10: 13 | H10: 11 | I10: 15 | J10: 8 | K10: 0 | L10: 0 | M10: 0 | N10: 0
B11: Other Liabilities -
B12: Non controlling int | C12: 246 | D12: 264 | E12: 384 | F12: 375 | G12: 328 | H12: 361 | I12: 404 | J12: 423 | K12: 388 | L12: 454 | M12: 695 | N12: 659
B13: Trade Payables | C13: 1746 | D13: 1549 | E13: 1565 | F13: 1923 | G13: 2160 | H13: 2394 | I13: 2137 | J13: 3379 | K13: 4164 | L13: 3635 | M13: 3831 | N13: 3848
B14: Advance from Customers | C14: 0 | D14: 5 | E14: 12 | F14: 17 | G14: 16 | H14: 13 | I14: 29 | J14: 41 | K14: 76 | L14: 108 | M14: 154 | N14: 173
B15: Other liability items | C15: 1795 | D15: 1937 | E15: 1750 | F15: 1925 | G15: 2316 | H15: 2690 | I15: 2320 | J15: 2613 | K15: 2932 | L15: 3657 | M15: 4017 | N15: 3985
B16: Total Liabilities | C16: 8075 | D16: 8914 | E16: 10559 | F16: 12405 | G16: 13763 | H16: 16249 | I16: 16138 | J16: 20355 | K16: 22958 | L16: 25779 | M16: 29901 | N16: 30355
B18: Fixed Assets -
B19: Land | C19: 247 | D19: 251 | E19: 429 | F19: 408 | G19: 586 | H19: 605 | I19: 640 | J19: 644 | K19: 644 | L19: 804 | M19: 1126 | N19: 1050
B20: Building | C20: 931 | D20: 962 | E20: 923 | F20: 931 | G20: 957 | H20: 2402 | I20: 2257 | J20: 2249 | K20: 2325 | L20: 2883 | M20: 3390 | N20: 4136
B21: Plant Machinery | C21: 2054 | D21: 2132 | E21: 1793 | F21: 1980 | G21: 2157 | H21: 4006 | I21: 4208 | J21: 4340 | K21: 4531 | L21: 4825 | M21: 5422 | N21: 7576
B22: Equipments | C22: 155 | D22: 171 | E22: 97 | F22: 119 | G22: 200 | H22: 221 | I22: 241 | J22: 243 | K22: 253 | L22: 270 | M22: 298 | N22: 325
B23: Furniture n fittings | C23: 71 | D23: 83 | E23: 49 | F23: 59 | G23: 72 | H23: 88 | I23: 94 | J23: 99 | K23: 113 | L23: 146 | M23: 175 | N23: 203
B24: Vehicles | C24: 14 | D24: 18 | E24: 11 | F24: 14 | G24: 27 | H24: 47 | I24: 43 | J24: 38 | K24: 32 | L24: 36 | M24: 40 | N24: 39
B25: Intangible Assets | C25: 203 | D25: 351 | E25: 339 | F25: 276 | G25: 468 | H25: 512 | I25: 505 | J25: 476 | K25: 345 | L25: 422 | M25: 850 | N25: 827
B26: Other fixed assets | C26: 128 | D26: 145 | E26: 103 | F26: 128 | G26: 238 | H26: 261 | I26: 293 | J26: 302 | K26: 294 | L26: 289 | M26: 321 | N26: 328
B27: Gross Block | C27: 3804 | D27: 4112 | E27: 3744 | F27: 3914 | G27: 4705 | H27: 8141 | I27: 8282 | J27: 8392 | K27: 8538 | L27: 9676 | M27: 11622 | N27: 14484
B28: Accumulated Depreciation | C28: 1242 | D28: 1452 | E28: 327 | F28: 610 | G28: 973 | H28: 1644 | I28: 2010 | J28: 2533 | K28: 3019 | L28: 3905 | M28: 4475 | N28: 5264
B29: Net Block | C29: =C27-C28 -> 2562 | D29: =D27-D28 -> 2660 | E29: =E27-E28 -> 3417 | F29: =F27-F28 -> 3304 | G29: =G27-G28 -> 3732 | H29: =H27-H28 -> 6497 | I29: =I27-I28 -> 6272 | J29: =J27-J28 -> 5859 | ... N29: =N27-N28 -> 9220
B31: CWIP | C31: 72 | D31: 196 | E31: 107 | F31: 258 | G31: 1405 | H31: 210 | I31: 140 | J31: 183 | K31: 426 | L31: 1020 | M31: 2698 | N31: 1254
B32: Investments | C32: 1424 | D32: 1588 | E32: 2712 | F32: 2652 | G32: 2141 | H32: 2569 | I32: 2019 | J32: 4737 | K32: 3248 | L32: 4262 | M32: 4588 | N32: 4725
B34: Other Assets -
B35: Inventories | C35: 2070 | D35: 2259 | E35: 1998 | F35: 2627 | G35: 2658 | H35: 3150 | I35: 3390 | J35: 3799 | K35: 6153 | L35: 6211 | M35: 5923 | N35: 6719
B36: Trade Reveivable | C36: 1110 | D36: 1182 | E36: 1187 | F36: 1447 | G36: 1731 | H36: 1907 | I36: 1795 | J36: 2602 | K36: 3871 | L36: 4637 | M36: 4889 | N36: 4314
B37: Cash Equivalents | C37: 229 | D37: 204 | E37: 424 | F37: 801 | G37: 405 | H37: 445 | I37: 783 | J37: 611 | K37: 864 | L37: 844 | M37: 1084 | N37: 782
B38: Loans n Advances | C38: 7 | D38: 8 | E38: 9 | F38: 14 | G38: 13 | H38: 16 | I38: 12 | J38: 12 | K38: 8 | L38: 12 | M38: 17 | N38: 22
B39: Other asset items | C39: 603 | D39: 817 | E39: 705 | F39: 1303 | G39: 1678 | H39: 1456 | I39: 1727 | J39: 2554 | K39: 2869 | L39: 3024 | M39: 3555 | N39: 3319
B40: Total Assets | C40: 8075 | D40: 8914 | E40: 10559 | F40: 12405 | G40: 13763 | H40: 16249 | I40: 16138 | J40: 20355 | K40: 22958 | L40: 25779 | M40: 29901 | N40: 30355

Sheet Referance
B4: https://finance.yahoo.com/quote/BERGEPAINT.BO/history/?frequency=1wk&period1=1711065600&period2=1774137600
B5: https://finance.yahoo.com/quote/066575.KS/history/?frequency=1wk&period1=1711065600&period2=1774137600
B6: https://finance.yahoo.com/quote/HAVELLS.BO/history/?period1=1711065600&period2=1774137600&frequency=1wk
B7: https://finance.yahoo.com/quote/DIXON.NS/history/?period1=1711065600&period2=1774137600&frequency=1wk
B8: https://finance.yahoo.com/quote/%5EDJI/history/?frequency=1wk&period1=1711065600&period2=1774137600
B9: https://finance.yahoo.com/quote/ASIANPAINT.BO/history/?period1=1711065600&period2=1774137600&frequency=1wk
B10: Nifty 50 returns - 20 years worth of powerful, downloadable data
B11: India 10-Year Bond Yield - Investing.com India
B12: Beta/Volatility of Berger Paints India Ltd. on Daily/ Weekly/ Monthly Period
B13: Stock Analysis of S&P CNX NIFTY (NIFTY) - Birds Eye View

Sheet DATA
A3: S.No. | B3: Name | C3: CMP Rs. | D3: No. Eq. Shares Cr. | E3: MA CAP | F3: Debt Rs.Cr. | G3: Sales Rs.Cr. | H3: Cash Rs.Cr. | I3: NP 12M Rs.Cr. | J3: EV / EBITDA | K3: EV | L3: EBITDA
A4: 1 | B4: Asian Paints | C4: 2485.1 | D4: 95.92 | E4: =C4*D4 -> 238370.79 | F4: 3557.09 | G4: 34695.75 | H4: 1010.67 | I4: 3910.03 | J4: 33.63 | K4: =E4+F4-H4 -> 240917.21 | L4: =K4/J4 -> 7163.7589
A5: 2 | B5: Berger Paints | C5: 460.4 | D5: 116.6 | E5: =C5*D5 -> 53682.64 | F5: 697.33 | G5: 11716.25 | H5: 449.83 | I5: 1055.68 | J5: 27.94 | K5: =E5+F5-H5 -> 53930.14 | L5: =K5/J5 -> 1930.2126
A6: 3 | B6: Kansai Nerolac | C6: 197.15 | D6: 80.87 | E6: =C6*D6 -> 15943.521 | F6: 276.42 | G6: 7914.85 | H6: 267.31 | I6: 568.38 | J6: 14.82 | K6: =E6+F6-H6 -> 15952.631 | L6: =K6/J6 -> 1076.4258
A7: 4 | B7: JSW Dulux | C7: 2947.8 | D7: 4.55 | E7: =C7*D7 -> 13412.49 | F7: 71.2 | G7: 3759.8 | H7: 274 | I7: 1955.3 | J7: 23.01 | K7: =E7+F7-H7 -> 13209.69 | L7: =K7/J7 -> 574.08475
A8: 5 | B8: Indigo Paints | C8: 860.05 | D8: 4.77 | E8: =C8*D8 -> 4102.4385 | F8: 17.64 | G8: 1299.42 | H8: 9.09 | I8: 144.95 | J8: 15.87 | K8: =E8+F8-H8 -> 4110.9885 | L8: =K8/J8 -> 259.04149
A9: 6 | B9: Sirca Paints | C9: 437.3 | D9: 5.68 | E9: =C9*D9 -> 2483.864 | F9: 45.22 | G9: 459.12 | H9: 52.84 | I9: 61.5 | J9: 25.91 | K9: =E9+F9-H9 -> 2476.244 | L9: =K9/J9 -> 95.570976
A10: 7 | B10: Shalimar Paints | C10: 50.1 | D10: 8.37 | E10: =C10*D10 -> 419.337 | F10: 189.6 | G10: 597.53 | H10: 48.07 | I10: -67.08 | J10: -28.89 | K10: =E10+F10-H10 -> 560.867 | L10: =K10/J10 -> -19.41388
A11: 8 | B11: Kamdhenu Venture | C11: 5.62 | D11: 32.9 | E11: =C11*D11 -> 184.898 | F11: 32.23 | G11: 253.02 | H11: 6.76 | I11: 4.76 | J11: 12.95 | K11: =E11+F11-H11 -> 210.368 | L11: =K11/J11 -> 16.244633
A12: 9 | B12: Siddhika Coatins | C12: 221.95 | D12: 0.62 | E12: =C12*D12 -> 137.609 | F12: 0 | G12: 51.6 | H12: 5.9 | I12: 8.54 | J12: 11.11 | K12: =E12+F12-H12 -> 131.709 | L12: =K12/J12 -> 11.854995
